Workbook
Name _Box1: #REF!
Name _Box10: #REF!
Name _Box11: #REF!
Name _Box12: #REF!
Name _Box13: #REF!
Name _Box2: #REF!
Name _Box3: #REF!
Name _Box4: #REF!
Name _Box5: #REF!
Name _Box6: #REF!
Name _Box7: #REF!
Name _Box8: #REF!
Name _Box9: #REF!
Name _dep01: [2]Sheet1!$M$126
Name _dep93: [2]Sheet1!$E$166
Name _dep94: [2]Sheet1!$F$166
Name _dep95: [2]Sheet1!$G$166
Name _dep96: [2]Sheet1!$H$166
Name _dep97: [2]Sheet1!$I$166
Name _dep98: [2]Sheet1!$J$166
Name _dep99: [2]Sheet1!$K$126
Name _dps01: [2]Sheet1!$M$14
Name _dps93: [2]Sheet1!$E$14
Name _dps94: [2]Sheet1!$F$14
Name _dps95: [2]Sheet1!$G$14
Name _dps96: [2]Sheet1!$H$14
Name _dps97: [2]Sheet1!$I$14
Name _dps98: [2]Sheet1!$J$14
Name _dps99: [2]Sheet1!$K$14
Name _dpu99: #REF!
Name _gcf99: #REF!
Name _int01: [2]Sheet1!$M$44
Name _int93: [2]Sheet1!$E$44
Name _int94: [2]Sheet1!$F$44
Name _int95: [2]Sheet1!$G$44
Name _int96: [2]Sheet1!$H$44
Name _int97: [2]Sheet1!$I$44
Name _int98: [2]Sheet1!$J$44
Name _int99: [2]Sheet1!$K$44
Name _nde01: [2]Sheet1!$M$150
Name _nde93: [2]Sheet1!$E$150
Name _nde94: [2]Sheet1!$F$150
Name _nde95: [2]Sheet1!$G$150
Name _nde96: [2]Sheet1!$H$150
Name _nde97: [2]Sheet1!$I$150
Name _nde98: [2]Sheet1!$J$150
Name _nde99: [2]Sheet1!$K$150
Name _nta01: [2]Sheet1!$M$16
Name _nta93: [2]Sheet1!$E$16
Name _nta94: [2]Sheet1!$F$16
Name _nta95: [2]Sheet1!$G$16
Name _nta96: [2]Sheet1!$H$16
Name _nta97: [2]Sheet1!$I$16
Name _nta98: [2]Sheet1!$J$16
Name _nta99: [2]Sheet1!$K$16
Name _roa01: [2]Sheet1!$M$155
Name _roa93: [2]Sheet1!$E$155
Name _roa94: [2]Sheet1!$F$155
Name _roa95: [2]Sheet1!$G$155
Name _roa96: [2]Sheet1!$H$155

Sheet __FDSCACHE__
B1: This sheet contains FactSet XML data for use with this workbook's =FDS codes. Modifying the worksheet's contents may damage the workbook's =FDS functionality.

Sheet IS
A1: Tutor Perini | Y1: =+Y79 -> 0 | AX1: **NOTE - I DID NOT CREATE THIS MODEL, IT WAS PROVIDED AS PART OF A MODELING TEST ON AN INTERVIEW. I HAVE BEEN UPDATING IT QUARTERLY SINCE Q12018
A2: Income Statement (US$ Millions) | F2: 40268 | G2: =EOMONTH(F2,3) -> 40359 | H2: =EOMONTH(G2,3) -> 40451 | I2: =EOMONTH(H2,3) -> 40543 | K2: =+EOMONTH(F2,12) -> 40633 | L2: =+EOMONTH(G2,12) -> 40724 | M2: =+EOMONTH(H2,12) -> 40816 | N2: =+EOMONTH(I2,12) -> 40908 | P2: =+EOMONTH(K2,12) -> 40999 | Q2: =+EOMONTH(L2,12) -> 41090 | R2: =+EOMONTH(M2,12) -> 41182 | S2: =+EOMONTH(N2,12) -> 41274 | U2: =+EOMONTH(P2,12) -> 41364 | V2: =+EOMONTH(Q2,12) -> 41455 | W2: =+EOMONTH(R2,12) -> 41547 | X2: =+EOMONTH(S2,12) -> 41639 | Y2: =+Y19-T19 -> 425.633 | Z2: =+EOMONTH(U2,12) -> 41729 | AA2: =+EOMONTH(V2,12) -> 41820 | AB2: =+EOMONTH(W2,12) -> 41912 | AC2: =+EOMONTH(X2,12) -> 42004 | AD2: =#REF! -> #REF! | AE2: =+EOMONTH(Z2,12) -> 42094 | AF2: =+EOMONTH(AA2,12) -> 42185 | AG2: =+EOMONTH(X2,12) -> 42004 | AH2: =+EOMONTH(AC2,12) -> 42369 | AJ2: =+EOMONTH(AE2,12) -> 42460 | AK2: =+EOMONTH(AF2,12) -> 42551 | AL2: =+EOMONTH(AG2,12) -> 42369 | AM2: =+EOMONTH(AH2,12) -> 42735 | AO2: =+EOMONTH(AJ2,12) -> 42825 | AP2: =+EOMONTH(AK2,12) -> 42916 | AQ2: =+EOMONTH(AL2,12) -> 42735 | AR2: =+EOMONTH(AM2,12) -> 43100 | AS2: =#REF! -> #REF! | AT2: =+EOMONTH(AO2,12) -> 43190 | AU2: =+EOMONTH(AP2,12) -> 43281 | AV2: =+EOMONTH(AQ2,12) -> 43100 | AW2: =+EOMONTH(AR2,12) -> 43465 | AX2: =#REF! -> #REF! | AY2: =+EOMONTH(AT2,12) -> 43555 | AZ2: =+EOMONTH(AU2,12) -> 43646 | BA2: =+EOMONTH(AV2,12) -> 43465 | BB2: =+EOMONTH(AW2,12) -> 43830 | BD2: =+EOMONTH(AY2,12) -> 43921 | BE2: =+EOMONTH(AZ2,12) -> 44012 | BF2: =+EOMONTH(BA2,12) -> 43830 | BG2: =+EOMONTH(BB2,12) -> 44196 | BI2: =+EOMONTH(BD2,12) -> 44286 | BJ2: =+EOMONTH(BE2,12) -> 44377 | BK2: =+EOMONTH(BF2,12) -> 44196 | BL2: =+EOMONTH(BG2,12) -> 44561 | BN2: =+EOMONTH(BI2,12) -> 44651 | BO2: =+EOMONTH(BJ2,12) -> 44742 | BP2: =+EOMONTH(BK2,12) -> 44561 | BQ2: =+EOMONTH(BL2,12) -> 44926
A3: TPC | F3: 2010 | J3: =+F3 -> 2010 | K3: 2011 | O3: =+K3 -> 2011 | P3: 2012 | T3: =+P3 -> 2012 | U3: 2013 | Y3: =+U3 -> 2013 | Z3: 2014 | AD3: =+Z3 -> 2014 | AE3: 2015 | AI3: =+AE3 -> 2015 | AJ3: 2016 | AN3: =+AJ3 -> 2016 | AO3: 2017 | AS3: =+AO3 -> 2017 | AT3: 2018 | AX3: =+AT3 -> 2018 | AY3: 2019 | BC3: =+AY3 -> 2019 | BD3: 2020E | BH3: =+BD3 -> 2020E | BI3: 2021E | BM3: =+BI3 -> 2021E | BN3: 2022E | BR3: =+BN3 -> 2022E
A4: Fiscal YE December | F4: 1Q | G4: 2Q | H4: 3Q | I4: 4Q | J4: Year | K4: 1Q | L4: 2Q | M4: 3Q | N4: 4Q | O4: Year | P4: 1Q | Q4: 2Q | R4: 3Q | S4: 4Q | T4: Year | U4: 1Q | V4: 2QE | W4: 3QE | X4: 4QE | Y4: Year | Z4: 1Q | AA4: 2Q | AB4: 3Q | AC4: 4Q | AD4: Year | AE4: 1Q | AF4: 2Q | AG4: 3Q | AH4: 4Q | AI4: Year | AJ4: 1Q | AK4: 2Q | AL4: 3Q | AM4: 4Q | AN4: Year | AO4: 1Q | AP4: 2Q | AQ4: 3Q | AR4: 4Q | AS4: Year | AT4: 1Q | AU4: 2Q | AV4: 3Q | AW4: 4Q | AX4: Year | AY4: 1Q | AZ4: 2Q | BA4: 3Q | BB4: 4QE | BC4: Year | BD4: 1QE | BE4: 2QE | BF4: 3QE | BG4: 4QE | BH4: Year | BI4: 1QE | BJ4: 2QE | BK4: 3QE | BL4: 4QE | BM4: Year | BN4: 1QE | BO4: 2QE | BP4: 3QE | BQ4: 4QE | BR4: Year
A5: Revenues by Segment
A6: Building | F6: 686.284 | G6: 663.157 | H6: 520.671 | I6: =J6-H6-G6-F6 -> 456.868 | J6: 2326.98 | K6: 440.429 | L6: 599.977 | M6: 567.676 | N6: =O6-M6-L6-K6 -> 343.948 | O6: 1952.03 | P6: 343.039 | Q6: 331.924 | R6: 391.531 | S6: =T6-R6-Q6-P6 -> 412.014 | T6: 1478.508 | U6: 425.114 | V6: 422.366 | W6: 352.013 | X6: =Y6-W6-V6-U6 -> 337.734 | Y6: 1537.227 | Z6: 311.315 | AA6: 390.353 | AB6: 420.404 | AC6: 436.359 | AD6: =SUM(Z6:AC6) -> 1558.431 | AE6: 416.063 | AF6: 472.247 | AG6: 506.259 | AH6: 505.924 | AI6: =+SUM(AE6:AH6) -> 1900.493 | AJ6: 487.994 | AK6: 523.521 | AL6: 560.795 | AM6: 551.801 | AN6: =+SUM(AJ6:AM6) -> 2124.111 | AO6: 515.251 | AP6: 508.769 | AQ6: 500.42 | AR6: 462.501 | AS6: =+SUM(AO6:AR6) -> 1986.941 | AT6: 490.617 | AU6: 447.975 | AV6: 457.304 | AW6: 471.006 | AX6: =+SUM(AT6:AW6) -> 1866.902 | AY6: 436.243 | AZ6: 433.559 | BA6: 421.241 | BB6: =AX6*BB81 -> 517.08347 | BC6: =Backlog!W35 -> 1822.4582 | BD6: =$BC6*BD81 -> 388.89198 | BE6: =$BC6*BE81 -> 457.09044 | BF6: =$BC6*BF81 -> 466.79635 | BG6: =$BC6*BG81 -> 509.67947 | BH6: =Backlog!X35 -> 1988.2877 | BI6: =$BC6*BI81 -> 381.44193 | BJ6: =$BC6*BJ81 -> 459.06958 | BK6: =$BC6*BK81 -> 463.20683 | BL6: =$BC6*BL81 -> 518.73991 | BM6: =Backlog!Y35 -> 2040.4516 | BN6: =$BC6*BN81 -> 358.65303 | BO6: =$BC6*BO81 -> 457.17395 | BP6: =$BC6*BP81 -> 464.25997 | BQ6: =$BC6*BQ81 -> 542.37131 | BR6: =Backlog!Z35 -> 2053.8202
A7: Civil | F7: 124.66 | G7: 197.431 | H7: 169.88 | I7: =J7-H7-G7-F7 -> 175.733 | J7: 667.704 | K7: 128.825 | L7: 141.442 | M7: 281.355 | N7: =O7-M7-L7-K7 -> 345.274 | O7: 896.896 | P7: 250.589 | Q7: 327.072 | R7: 350.542 | S7: =T7-R7-Q7-P7 -> 362.407 | T7: 1290.61 | U7: 283.975 | V7: 332.223 | W7: 379.765 | X7: =Y7-W7-V7-U7 -> 427.809 | Y7: 1423.772 | Z7: 376.392 | AA7: 398.123 | AB7: 496.142 | AC7: 459.811 | AD7: =SUM(Z7:AC7) -> 1730.468 | AE7: 392.876 | AF7: 573.36 | AG7: 604.317 | AH7: 434.64 | AI7: =+SUM(AE7:AH7) -> 2005.193 | AJ7: 367.501 | AK7: 465.707 | AL7: 506.1 | AM7: 452.327 | AN7: =+SUM(AJ7:AM7) -> 1791.635 | AO7: 338.108 | AP7: 538.552 | AQ7: 458.487 | AR7: 492.314 | AS7: =+SUM(AO7:AR7) -> 1827.461 | AT7: 325.4 | AU7: 461.614 | AV7: 479.581 | AW7: 543.637 | AX7: =+SUM(AT7:AW7) -> 1810.232 | AY7: 383.622 | AZ7: 541.117 | BA7: 591.884 | BB7: =AX7*BB82 -> 469.37366 | BC7: =Backlog!W33 -> 3021.1949 | BD7: =$BC7*BD82 -> 546.95096 | BE7: =$BC7*BE82 -> 830.33826 | BF7: =$BC7*BF82 -> 828.41794 | BG7: =$BC7*BG82 -> 815.48769 | BH7: =Backlog!X33 -> 3555.3498 | BI7: =$BC7*BI82 -> 528.76148 | BJ7: =$BC7*BJ82 -> 841.59494 | BK7: =$BC7*BK82 -> 822.16609 | BL7: =$BC7*BL82 -> 828.67233 | BM7: =Backlog!Y33 -> 4586.0774 | BN7: =$BC7*BN82 -> 521.21014 | BO7: =$BC7*BO82 -> 829.40746 | BP7: =$BC7*BP82 -> 838.21266 | BQ7: =$BC7*BQ82 -> 832.36459 | BR7: =Backlog!Z33 -> 5582.3667
A8: Specialty Contractors | M8: 335.921 | N8: =O8-M8-L8-K8 -> 466.614 | O8: 802.535 | P8: 267.736 | Q8: 275.902 | R8: 315.27 | S8: =T8-R8-Q8-P8 -> 324.61 | T8: 1183.518 | U8: 301.877 | V8: 284.036 | W8: 287.633 | X8: =Y8-W8-V8-U8 -> 309.298 | Y8: 1182.844 | Z8: 292.145 | AA8: 321.959 | AB8: 355.932 | AC8: 331.292 | AD8: =SUM(Z8:AC8) -> 1301.328 | AE8: 293.017 | AF8: 326.798 | AG8: 325.365 | AH8: 282.849 | AI8: =+SUM(AE8:AH8) -> 1228.029 | AJ8: 281.773 | AK8: 318.902 | AL8: 331.613 | AM8: 301.983 | AN8: =+SUM(AJ8:AM8) -> 1234.271 | AO8: 315.696 | AP8: 281.857 | AQ8: 310.137 | AR8: 306.018 | AS8: =+SUM(AO8:AR8) -> 1213.708 | AT8: 274.801 | AU8: 270.633 | AV8: 236.157 | AW8: 225.279 | AX8: =+SUM(AT8:AW8) -> 1006.87 | AY8: 191.527 | AZ8: 223.299 | BA8: 249.453 | BB8: =AX7*BB83 -> 481.26714 | BC8: =Backlog!W38 -> 1232.3809 | BD8: =$BC8*BD83 -> 264.23834 | BE8: =$BC8*BE83 -> 306.11383 | BF8: =$BC8*BF83 -> 323.44155 | BG8: =$BC8*BG83 -> 338.58717 | BH8: =Backlog!X38 -> 1263.4234 | BI8: =$BC8*BI83 -> 259.96255 | BJ8: =$BC8*BJ83 -> 303.03887 | BK8: =$BC8*BK83 -> 321.52565 | BL8: =$BC8*BL83 -> 347.85382 | BM8: =Backlog!Y38 -> 1269.5185 | BN8: =$BC8*BN83 -> 244.81495 | BO8: =$BC8*BO83 -> 307.25025 | BP8: =$BC8*BP83 -> 323.17994 | BQ8: =$BC8*BQ83 -> 357.13575 | BR8: =Backlog!Z38 -> 1271.0805
A9: Management Services | F9: 54.131 | G9: 53.788 | H9: 41.255 | I9: =J9-H9-G9-F9 -> 55.352 | J9: 204.526 | K9: 46.035 | L9: 78.439 | M9: 85.482 | N9: =O9-M9-L9-K9 -> 66.019 | O9: 275.975 | P9: 68.112 | Q9: 64.773 | R9: 51.744 | S9: =T9-R9-Q9-P9 -> 56.854 | T9: 241.483 | U9: 47.369 | V9: 45.744 | W9: 37.031 | X9: =Y9-W9-V9-U9 -> 50.932 | Y9: 181.076 | AD9: =SUM(Z9:AC9) -> 0 | AI9: =+SUM(AE9:AH9) -> 0 | AN9: =+SUM(AJ9:AM9) -> 0 | AS9: =+SUM(AO9:AR9) -> 0 | AX9: =+SUM(AT9:AW9) -> 0
A10: Eliminations | M10: -104.024 | N10: =O10-M10-L10-K10 -> -107.095 | O10: -211.119 | P10: -16.942 | Q10: -14.325 | R10: =R11-SUM(R6:R9) -> -9.694 | S10: =S11-SUM(S6:S9) -> -41.687 | T10: =SUM(P10:S10) -> -82.648 | U10: =U11-SUM(U6:U9) -> -65.407 | V10: =V11-SUM(V6:V9) -> -31.304 | W10: =W11-SUM(W6:W9) -> -26.054 | X10: =X11-SUM(X6:X9) -> -26.482 | Y10: -149.247 | Z10: =Z11-SUM(Z6:Z9) -> -24.619 | AA10: =AA11-SUM(AA6:AA9) -> -25.925 | AB10: =X11-SUM(X6:X9) -> -26.482 | AC10: -25.585 | AD10: =SUM(Z10:AC10) -> -102.611 | AE10: -35.491 | AF10: -59.967 | AG10: -95.202 | AH10: -22.583 | AI10: =+SUM(AE10:AH10) -> -213.243 | AJ10: -51.899 | AK10: -61.859 | AL10: -65.53 | AM10: -59.512 | AN10: =+SUM(AJ10:AM10) -> -238.8 | AO10: -51.694 | AP10: -81.904 | AQ10: -69.539 | AR10: -67.765 | AS10: =+SUM(AO10:AR10) -> -270.902 | AT10: -62.662 | AU10: -60.137 | AV10: -49.905 | AW10: -56.638 | AX10: =+SUM(AT10:AW10) -> -229.342 | AY10: -52.905 | AZ10: -72.7 | BA10: -73.233 | BB10: =+BC10-BA10-AZ10-AY10 -> -101.162 | BC10: -300 | BD10: =+BH10/4 -> -77.5 | BE10: =+(BH10-BD10)/3 -> -77.5 | BF10: =+(BH10-BE10-BD10)/2 -> -77.5 | BG10: =+BH10-BF10-BE10-BD10 -> -77.5 | BH10: -310 | BI10: =+BM10/4 -> -77.5 | BJ10: =+(BM10-BI10)/3 -> -77.5 | BK10: =+(BM10-BJ10-BI10)/2 -> -77.5 | BL10: =+BM10-BK10-BJ10-BI10 -> -77.5 | BM10: -310 | BN10: =+BR10/4 -> -77.5 | BO10: =+(BR10-BN10)/3 -> -77.5 | BP10: =+(BR10-BO10-BN10)/2 -> -77.5 | BQ10: =+BR10-BP10-BO10-BN10 -> -77.5 | BR10: -310
A11: Total Revenue | F11: 865.075 | G11: 914.376 | H11: 731.806 | I11: =J11-H11-G11-F11 -> 687.953 | J11: 3199.21 | K11: 615.289 | L11: 819.858 | M11: 1166.41 | N11: =O11-M11-L11-K11 -> 1114.76 | O11: 3716.317 | P11: 912.534 | Q11: 985.346 | R11: 1099.393 | S11: =T11-R11-Q11-P11 -> 1114.198 | T11: 4111.471 | U11: 992.928 | V11: 1053.065 | W11: 1030.388 | X11: =Y11-W11-V11-U11 -> 1099.291 | Y11: 4175.672 | Z11: 955.233 | AA11: 1084.51 | AB11: 1250.689 | AC11: =SUM(AC6:AC10) -> 1201.877 | AD11: =SUM(AD6:AD10) -> 4487.616 | AE11: =SUM(AE6:AE10) -> 1066.465 | AF11: =SUM(AF6:AF10) -> 1312.438 | AG11: =SUM(AG6:AG10) -> 1340.739 | AH11: =SUM(AH6:AH10) -> 1200.83 | AI11: =SUM(AE11:AH11) -> 4920.472 | AJ11: =SUM(AJ6:AJ10) -> 1085.369 | AK11: =SUM(AK6:AK10) -> 1246.271 | AL11: =SUM(AL6:AL10) -> 1332.978 | AM11: =SUM(AM6:AM10) -> 1246.599 | AN11: =SUM(AJ11:AM11) -> 4911.217 | AO11: =SUM(AO6:AO10) -> 1117.361 | AP11: =SUM(AP6:AP10) -> 1247.274 | AQ11: =SUM(AQ6:AQ10) -> 1199.505 | AR11: =SUM(AR6:AR10) -> 1193.068 | AS11: =SUM(AO11:AR11) -> 4757.208 | AT11: =SUM(AT6:AT10) -> 1028.156 | AU11: =SUM(AU6:AU10) -> 1120.085 | AV11: =SUM(AV6:AV10) -> 1123.137 | AW11: =SUM(AW6:AW10) -> 1183.284 | AX11: =SUM(AT11:AW11) -> 4454.662 | AY11: =SUM(AY6:AY10) -> 958.487 | AZ11: =SUM(AZ6:AZ10) -> 1125.275 | BA11: =SUM(BA6:BA10) -> 1189.345 | BB11: =SUM(BB6:BB10) -> 1366.5623 | BC11: =SUM(AY11:BB11) -> 4639.6693 | BD11: =SUM(BD6:BD10) -> 1122.5813 | BE11: =SUM(BE6:BE10) -> 1516.0425 | BF11: =SUM(BF6:BF10) -> 1541.1559 | BG11: =SUM(BG6:BG10) -> 1586.2543 | BH11: =SUM(BD11:BG11) -> 5766.034 | BI11: =SUM(BI6:BI10) -> 1092.666 | BJ11: =SUM(BJ6:BJ10) -> 1526.2034 | BK11: =SUM(BK6:BK10) -> 1529.3986 | BL11: =SUM(BL6:BL10) -> 1617.7661 | BM11: =SUM(BI11:BL11) -> 5766.034 | BN11: =SUM(BN6:BN10) -> 1047.1781 | BO11: =SUM(BO6:BO10) -> 1516.3317 | BP11: =SUM(BP6:BP10) -> 1548.1526 | BQ11: =SUM(BQ6:BQ10) -> 1654.3717 | BR11: =SUM(BN11:BQ11) -> 5766.034
A13: Operating Income by Segment
A14: Building | F14: 32.31 | G14: 29.686 | H14: 28.174 | I14: =J14-H14-G14-F14 -> 5.687 | J14: 95.857 | K14: 13.118 | L14: 24.921 | M14: 8.876 | N14: =O14-M14-L14-K14 -> -0.653 | O14: 46.262 | P14: -8.897 | Q14: -297.095 | R14: 20.847 | S14: =T14-R14-Q14-P14 -> -1.561 | T14: -286.706 | U14: 4.237 | V14: 3.024 | W14: 13.53 | X14: =Y14-W14-V14-U14 -> 3.008 | Y14: 23.799 | Z14: 1.823 | AA14: 7.674 | AB14: 19.159 | AC14: -3.959 | AD14: =SUM(Z14:AC14) -> 24.697 | AE14: -2.279 | AF14: -12.592 | AG14: 6.763 | AH14: 6.867 | AI14: =SUM(AE14:AH14) -> -1.241 | AJ14: 12.45 | AK14: 13.223 | AL14: 13.296 | AM14: 12.596 | AN14: =SUM(AJ14:AM14) -> 51.565 | AO14: 5.242 | AP14: 5.736 | AQ14: 14.058 | AR14: 9.164 | AS14: =SUM(AO14:AR14) -> 34.2 | AT14: 6.425 | AU14: 12.536 | AV14: 8.853 | AW14: 16.125 | AX14: =SUM(AT14:AW14) -> 43.939 | AY14: 3.133 | AZ14: -3.81 | BA14: 7.58 | BB14: =BB6*BB71 -> 10.341669 | BC14: =SUM(AY14:BB14) -> 17.244669 | BD14: =BD6*BD71 -> 15.555679 | BE14: =BE6*BE71 -> 18.283618 | BF14: =BF6*BF71 -> 18.671854 | BG14: =BG6*BG71 -> 20.387179 | BH14: =SUM(BD14:BG14) -> 72.89833 | BI14: =BI6*BI71 -> 15.257677 | BJ14: =BJ6*BJ71 -> 18.362783 | BK14: =BK6*BK71 -> 18.528273 | BL14: =BL6*BL71 -> 20.749596 | BM14: =SUM(BI14:BL14) -> 72.89833 | BN14: =BN6*BN71 -> 14.346121 | BO14: =BO6*BO71 -> 18.286958 | BP14: =BP6*BP71 -> 18.570399 | BQ14: =BQ6*BQ71 -> 21.694852 | BR14: =SUM(BN14:BQ14) -> 72.89833
A15: Civil | F15: 8.29 | G15: 29.72 | H15: 27.298 | I15: =J15-H15-G15-F15 -> 22.474 | J15: 87.782 | K15: 12.114 | L15: 15.283 | M15: 23.805 | N15: =O15-M15-L15-K15 -> 27.344 | O15: 78.546 | P15: 16.842 | Q15: -39.741 | R15: 26.28 | S15: =T15-R15-Q15-P15 -> 43.7 | T15: 47.081 | U15: 21.554 | V15: 29.199 | W15: 47.532 | X15: =Y15-W15-V15-U15 -> 69.583 | Y15: 167.868 | Z15: 44.345 | AA15: 58.002 | AB15: 53.684 | AC15: 64.523 | AD15: =SUM(Z15:AC15) -> 220.554 | AE15: 30.593 | AF15: 46.329 | AG15: 43.183 | AH15: 25.107 | AI15: =SUM(AE15:AH15) -> 145.212 | AJ15: 33.665 | AK15: 45.056 | AL15: 50.307 | AM15: 43.64 | AN15: =SUM(AJ15:AM15) -> 172.668 | AO15: 31.888 | AP15: 58.144 | AQ15: 38.144 | AR15: 64.031 | AS15: =SUM(AO15:AR15) -> 192.207 | AT15: 2.839 | AU15: 49.439 | AV15: 41.282 | AW15: 74.696 | AX15: =SUM(AT15:AW15) -> 168.256 | AY15: 41.745 | AZ15: -164.472 | BA15: 50.695 | BB15: =BB7*BB72 -> 49.284235 | BC15: =SUM(AY15:BB15) -> -22.747765 | BD15: =BD7*BD72 -> 57.429851 | BE15: =BE7*BE72 -> 87.185517 | BF15: =BF7*BF72 -> 86.983884 | BG15: =BG7*BG72 -> 85.626207 | BH15: =SUM(BD15:BG15) -> 317.22546 | BI15: =BI7*BI72 -> 55.519956 | BJ15: =BJ7*BJ72 -> 88.367469 | BK15: =BK7*BK72 -> 86.32744 | BL15: =BL7*BL72 -> 87.010595 | BM15: =SUM(BI15:BL15) -> 317.22546 | BN15: =BN7*BN72 -> 54.727064 | BO15: =BO7*BO72 -> 87.087784 | BP15: =BP7*BP72 -> 88.01233 | BQ15: =BQ7*BQ72 -> 87.398282 | BR15: =SUM(BN15:BQ15) -> 317.22546
A16: Specialty Contractors | M16: 33.132 | N16: =O16-M16-L16-K16 -> 32.45 | O16: 65.582 | P16: 19.748 | Q16: 8.379 | R16: 14.236 | S16: =T16-R16-Q16-P16 -> 25.228 | T16: 67.591 | U16: 19.286 | V16: 15.985 | W16: 9.312 | X16: =Y16-W16-V16-U16 -> 4.425 | Y16: 49.008 | Z16: 7.817 | AA16: 12.633 | AB16: 10.876 | AC16: 19.672 | AD16: =SUM(Z16:AC16) -> 50.998 | AE16: 10.524 | AF16: 13.743 | AG16: 4.741 | AH16: -13.326 | AI16: =SUM(AE16:AH16) -> 15.682 | AJ16: 9.413 | AK16: 5.413 | AL16: 11.084 | AM16: 11.999 | AN16: =SUM(AJ16:AM16) -> 37.909 | AO16: 14.762 | AP16: -14.007 | AQ16: 14.575 | AR16: 3.608 | AS16: =SUM(AO16:AR16) -> 18.938 | AT16: 7.235 | AU16: 7.454 | AV16: 11.561 | AW16: 17.18 | AX16: =SUM(AT16:AW16) -> 43.43 | AY16: -7.488 | AZ16: -159.795 | BA16: 7.247 | BB16: =BB8*BB73 -> 24.063357 | BC16: =SUM(AY16:BB16) -> -135.97264 | BD16: =BD8*BD73 -> 13.211917 | BE16: =BE8*BE73 -> 15.305691 | BF16: =BF8*BF73 -> 16.172078 | BG16: =BG8*BG73 -> 16.929358 | BH16: =SUM(BD16:BG16) -> 61.619045 | BI16: =BI8*BI73 -> 12.998128 | BJ16: =BJ8*BJ73 -> 15.151944 | BK16: =BK8*BK73 -> 16.076282 | BL16: =BL8*BL73 -> 17.392691 | BM16: =SUM(BI16:BL16) -> 61.619045 | BN16: =BN8*BN73 -> 12.240747 | BO16: =BO8*BO73 -> 15.362513 | BP16: =BP8*BP73 -> 16.158997 | BQ16: =BQ8*BQ73 -> 17.856788 | BR16: =SUM(BN16:BQ16) -> 61.619045
A17: Management Services | F17: 3.093 | G17: 6.848 | H17: 2.934 | I17: =J17-H17-G17-F17 -> 9.278 | J17: 22.153 | K17: 2.641 | L17: 6.519 | M17: 5.383 | N17: =O17-M17-L17-K17 -> 7.779 | O17: 22.322 | P17: 1.886 | Q17: -15.122 | R17: 2.841 | S17: =T17-R17-Q17-P17 -> 5.712 | T17: -4.683 | U17: 2.806 | V17: 2.112 | W17: 1.344 | X17: =Y17-W17-V17-U17 -> 4.317 | Y17: 10.579 | AD17: =SUM(Z17:AC17) -> 0 | AI17: =SUM(AE17:AH17) -> 0 | AN17: =SUM(AJ17:AM17) -> 0 | AS17: =SUM(AO17:AR17) -> 0 | AX17: =SUM(AT17:AW17) -> 0 | BC17: =SUM(AY17:BB17) -> 0 | BH17: =SUM(BD17:BG17) -> 0 | BM17: =SUM(BI17:BL17) -> 0 | BR17: =SUM(BN17:BQ17) -> 0
A18: Corporate | F18: -9.536 | G18: -10.403 | H18: -8.446 | I18: =J18-H18-G18-F18 -> -5.095 | J18: -33.48 | K18: -9.36 | L18: -9.688 | M18: -9.16 | N18: =O18-M18-L18-K18 -> -16.128 | O18: -44.336 | P18: -12.616 | Q18: -10.595 | R18: -9.528 | S18: =T18-R18-Q18-P18 -> -12.355 | T18: -45.094 | U18: -11.804 | V18: -10.846 | W18: -13.624 | X18: =Y18-W18-V18-U18 -> -11.158 | Y18: -47.432 | Z18: -12.488 | AA18: -12.866 | AB18: -13.365 | AC18: -15.84 | AD18: =SUM(Z18:AC18) -> -54.559 | AE18: -18.754 | AF18: -16.599 | AG18: -15.713 | AH18: -3.174 | AI18: =SUM(AE18:AH18) -> -54.24 | AJ18: -15.406 | AK18: -14.863 | AL18: -13.768 | AM18: -16.185 | AN18: =SUM(AJ18:AM18) -> -60.222 | AO18: -14.875 | AP18: -15.828 | AQ18: -17.705 | AR18: -17.46 | AS18: =SUM(AO18:AR18) -> -65.868 | AT18: -17.424 | AU18: -14.614 | AV18: -14.39 | AW18: -17.321 | AX18: =SUM(AT18:AW18) -> -63.749 | AY18: -14.447 | AZ18: -13.64 | BA18: -17.579 | BB18: =BB75*-BB11 -> -16.808716 | BC18: =SUM(AY18:BB18) -> -62.474716 | BD18: =BD75*-BD11 -> -13.80775 | BE18: =BE75*-BE11 -> -18.647323 | BF18: =BF75*-BF11 -> -18.956217 | BG18: =BG75*-BG11 -> -19.510928 | BH18: =SUM(BD18:BG18) -> -70.922218 | BI18: =BI75*-BI11 -> -13.439791 | BJ18: =BJ75*-BJ11 -> -18.772302 | BK18: =BK75*-BK11 -> -18.811602 | BL18: =BL75*-BL11 -> -19.898522 | BM18: =SUM(BI18:BL18) -> -70.922218 | BN18: =BN75*-BN11 -> -12.880291 | BO18: =BO75*-BO11 -> -18.650879 | BP18: =BP75*-BP11 -> -19.042277 | BQ18: =BQ75*-BQ11 -> -20.348771 | BR18: =SUM(BN18:BQ18) -> -70.922218
A19: Total Operating Income | F19: =SUM(F14:F18) -> 34.157 | G19: =SUM(G14:G18) -> 55.851 | H19: =SUM(H14:H18) -> 49.96 | I19: =SUM(I14:I18) -> 32.344 | J19: =SUM(J14:J18) -> 172.312 | K19: =SUM(K14:K18) -> 18.513 | L19: =SUM(L14:L18) -> 37.035 | M19: =SUM(M14:M18) -> 62.036 | ... AA19: =SUM(AA14:AA18) -> 65.443 | AB19: =SUM(X14:X18) -> 70.175 | AC19: =SUM(AC14:AC18) -> 64.396 | AD19: =SUM(Z19:AC19) -> 241.511 | AE19: =SUM(AE14:AE18) -> 20.084 | AF19: =SUM(AF14:AF18) -> 30.881 | AG19: =SUM(AG14:AG18) -> 38.974 | AH19: =SUM(AH14:AH18) -> 15.474 | AI19: =SUM(AE19:AH19) -> 105.413 | AJ19: =SUM(AJ14:AJ18) -> 40.122 | AK19: =SUM(AK14:AK18) -> 48.829 | AL19: =SUM(AL14:AL18) -> 60.919 | AM19: =SUM(AM14:AM18) -> 52.05 | AN19: =SUM(AJ19:AM19) -> 201.92 | AO19: =SUM(AO14:AO18) -> 37.017 | AP19: =SUM(AP14:AP18) -> 34.045 | AQ19: =SUM(AQ14:AQ18) -> 49.072 | AR19: =SUM(AR14:AR18) -> 59.343 | AS19: =SUM(AO19:AR19) -> 179.477 | AT19: =SUM(AT14:AT18) -> -0.925 | AU19: =SUM(AU14:AU18) -> 54.815 | AV19: =SUM(AV14:AV18) -> 47.306 | AW19: =SUM(AW14:AW18) -> 90.68 | AX19: =SUM(AT19:AW19) -> 191.876 | AY19: =SUM(AY14:AY18) -> 22.943 | AZ19: =SUM(AZ14:AZ18) -> -341.717 | BA19: =SUM(BA14:BA18) -> 47.943 | BB19: =SUM(BB14:BB18) -> 66.880545 | BC19: =SUM(AY19:BB19) -> -203.95046 | BD19: =SUM(BD14:BD18) -> 72.389698 | BE19: =SUM(BE14:BE18) -> 102.1275 | BF19: =SUM(BF14:BF18) -> 102.8716 | BG19: =SUM(BG14:BG18) -> 103.43182 | BH19: =SUM(BD19:BG19) -> 380.82062 | BI19: =SUM(BI14:BI18) -> 70.335969 | BJ19: =SUM(BJ14:BJ18) -> 103.10989 | BK19: =SUM(BK14:BK18) -> 102.12039 | BL19: =SUM(BL14:BL18) -> 105.25436 | BM19: =SUM(BI19:BL19) -> 380.82062 | BN19: =SUM(BN14:BN18) -> 68.433642 | BO19: =SUM(BO14:BO18) -> 102.08637 | BP19: =SUM(BP14:BP18) -> 103.69945 | BQ19: =SUM(BQ14:BQ18) -> 106.60115 | BR19: =SUM(BN19:BQ19) -> 380.82062
A21: Cost of Operations | F21: 788.942 | G21: 815.464 | H21: 641.136 | I21: =J21-H21-G21-F21 -> 615.82 | J21: 2861.362 | K21: 552.826 | L21: 732.648 | M21: 1046.055 | N21: =O21-M21-L21-K21 -> 989.447 | O21: 3320.976 | P21: 826.375 | Q21: 898.285 | R21: 983.93 | S21: =T21-R21-Q21-P21 -> 987.749 | T21: 3696.339 | U21: 892.571 | V21: 947.11 | W21: 909.531 | X21: =Y21-W21-V21-U21 -> 959.556 | Y21: 3708.768 | Z21: 849.886 | AA21: 954.979 | AB21: 1109.848 | AC21: =(AC11-AC19)-AC22 -> 1137.481 | AD21: =SUM(Z21:AC21) -> 4052.194 | AE21: =(AE11-AE19)-AE22 -> 1046.381 | AF21: =(AF11-AF19)-AF22 -> 1281.557 | AG21: =(AG11-AG19)-AG22 -> 1301.765 | AH21: =(AH11-AH19)-AH22 -> 1185.356 | AI21: =SUM(AE21:AH21) -> 4815.059 | AJ21: =(AJ11-AJ19)-AJ22 -> 1045.247 | AK21: =(AK11-AK19)-AK22 -> 1197.442 | AL21: =(AL11-AL19)-AL22 -> 1272.059 | AM21: =(AM11-AM19)-AM22 -> 1194.549 | AN21: =SUM(AJ21:AM21) -> 4709.297 | AO21: =(AO11-AO19)-AO22 -> 1080.344 | AP21: =(AP11-AP19)-AP22 -> 1213.229 | AQ21: =(AQ11-AQ19)-AQ22 -> 1150.433 | AR21: =(AR11-AR19)-AR22 -> 1133.725 | AS21: =SUM(AO21:AR21) -> 4577.731 | AT21: =(AT11-AT19)-AT22 -> 1029.081 | AU21: =(AU11-AU19)-AU22 -> 1065.27 | AV21: =(AV11-AV19)-AV22 -> 1075.831 | AW21: =(AW11-AW19)-AW22 -> 1092.604 | AX21: =SUM(AT21:AW21) -> 4262.786 | AY21: =(AY11-AY19)-AY22 -> 935.544 | AZ21: =(AZ11-AZ19)-AZ22 -> 1466.992 | BA21: =(BA11-BA19)-BA22 -> 1141.402 | BB21: =(BB11-BB19)-BB22 -> 1299.6817 | BC21: =SUM(AY21:BB21) -> 4843.6197 | BD21: =(BD11-BD19)-BD22 -> 1050.1916 | BE21: =(BE11-BE19)-BE22 -> 1413.915 | BF21: =(BF11-BF19)-BF22 -> 1438.2843 | BG21: =(BG11-BG19)-BG22 -> 1482.8225 | BH21: =SUM(BD21:BG21) -> 5385.2134 | BI21: =(BI11-BI19)-BI22 -> 1022.33 | BJ21: =(BJ11-BJ19)-BJ22 -> 1423.0935 | BK21: =(BK11-BK19)-BK22 -> 1427.2782 | BL21: =(BL11-BL19)-BL22 -> 1512.5117 | BM21: =SUM(BI21:BL21) -> 5385.2134 | BN21: =(BN11-BN19)-BN22 -> 978.74447 | BO21: =(BO11-BO19)-BO22 -> 1414.2453 | BP21: =(BP11-BP19)-BP22 -> 1444.4531 | BQ21: =(BQ11-BQ19)-BQ22 -> 1547.7705 | BR21: =SUM(BN21:BQ21) -> 5385.2134
A23: Goodwill and Intangible Asset Impairment | F23: 0 | G23: 0 | H23: 0 | I23: 0 | J23: 0 | K23: 0 | L23: 0 | M23: 0 | N23: 0 | O23: 0 | P23: 0 | Q23: 376.574 | R23: 0 | S23: 0 | T23: =SUM(P23:S23) -> 376.574 | U23: 0
A24: Income From Construction Operations | F24: =F11-F21-F22 -> 76.133 | G24: =G11-G21-G22 -> 98.912 | H24: =H11-H21-H22 -> 90.67 | I24: =I11-I21-I22 -> 72.133 | J24: =J11-J21-J22 -> 337.848 | K24: =K11-K21-K22 -> 62.463 | L24: =L11-L21-L22 -> 87.21 | M24: =M11-M21-M22 -> 120.355 | ... P24: =P11-P21-P22 -> 86.159 | Q24: =Q11-SUM(Q21:Q23) -> -289.513 | R24: =R11-SUM(R21:R23) -> 115.463 | S24: =S11-SUM(S21:S23) -> 126.449 | T24: =T11-T21-T22-T23 -> 38.558 | U24: =U11-U21-U22 -> 100.357 | V24: =V11-V21-V22 -> 105.955 | W24: =W11-W21-W22 -> 120.857 | X24: =X11-X21-X22 -> 139.735 | Y24: =Y11-Y21-Y22 -> 466.904 | Z24: =Z11-Z21-Z22 -> 105.347 | AA24: =AA11-AA21-AA22 -> 129.531 | AB24: =X11-X21-X22 -> 139.735 | AC24: =AC11-AC21-AC22 -> 64.396 | AD24: =AD11-AD21-AD22 -> 435.422 | AE24: =AE11-AE21-AE22 -> 20.084 | AF24: =AF11-AF21-AF22 -> 30.881 | AG24: =AG11-AG21-AG22 -> 38.974 | AH24: =AH11-AH21-AH22 -> 15.474 | AI24: =AI11-AI21-AI22 -> 105.413 | AJ24: =AJ11-AJ21-AJ22 -> 40.122 | ... BR24: =BR11-BR21-BR22 -> 380.82062
A40: Other Income, net | F40: 0.345 | G40: -1.102 | H40: 0.358 | I40: =J40-H40-G40-F40 -> -1.881 | J40: -2.28 | K40: -0.447 | L40: 1.232 | M40: 5.863 | N40: =O40-M40-L40-K40 -> -2.227 | O40: 4.421 | P40: -2.308 | Q40: 1.082 | R40: 0.545 | S40: =T40-R40-Q40-P40 -> -1.176 | T40: -1.857 | U40: -0.821 | V40: -3.234 | W40: -9.488 | X40: =Y40-W40-V40-U40 -> -5.032 | Y40: -18.575 | Z40: -3.373 | AA40: -6.974 | AB40: -0.441 | AC40: 1.252 | AD40: =SUM(Z40:AC40) -> -9.536 | AE40: -0.754 | AF40: 0.1 | AG40: 5.916 | AH40: 7.192 | AI40: =SUM(AE40:AH40) -> 12.454 | AJ40: 0.682 | AK40: 2.485 | AL40: 2.048 | AM40: 1.763 | AN40: =SUM(AJ40:AM40) -> 6.978 | AO40: 0.417 | AP40: 40.99 | AQ40: 0.967 | AR40: 1.508 | AS40: =SUM(AO40:AR40) -> 43.882 | AT40: 0.78 | AU40: 1.05 | AV40: 1.909 | AW40: 0.517 | AX40: =SUM(AT40:AW40) -> 4.256 | AY40: 0.422 | AZ40: =+(BC40-AY40)/3 -> -0.14066667 | BA40: 1.674 | BB40: =+BC40-BA40-AZ40-AY40 -> -1.9553333 | BC40: 0 | BD40: =+BH40/4 -> 0 | BE40: =+(BH40-BD40)/3 -> 0 | BF40: =+(BH40-BE40-BD40)/2 -> 0 | BG40: =+BH40-BF40-BE40-BD40 -> 0 | BH40: 0 | BI40: =+BM40/4 -> 0 | BJ40: =+(BM40-BI40)/3 -> 0 | BK40: =+(BM40-BJ40-BI40)/2 -> 0 | BL40: =+BM40-BK40-BJ40-BI40 -> 0 | BM40: 0 | BN40: =+BR40/4 -> 0 | BO40: =+(BR40-BN40)/3 -> 0 | BP40: =+(BR40-BO40-BN40)/2 -> 0 | BQ40: =+BR40-BP40-BO40-BN40 -> 0 | BR40: 0
A41: Interest Expense | F41: -1.521 | G41: -3.244 | H41: -1.589 | I41: =J41-H41-G41-F41 -> -4.21 | J41: -10.564 | K41: -7.155 | L41: -7.252 | M41: -11.566 | N41: =O41-M41-L41-K41 -> -9.777 | O41: -35.75 | P41: -11.082 | Q41: -10.603 | R41: -11.039 | S41: =T41-R41-Q41-P41 -> -11.45 | T41: -44.174 | U41: -11.336 | V41: -11.083 | W41: -11.571 | X41: =Y41-W41-V41-U41 -> -11.642 | Y41: -45.632 | Z41: -10.831 | AA41: -10.857 | AB41: -11.297 | AC41: -11.731 | AD41: =SUM(Z41:AC41) -> -44.716 | AE41: -11.125 | AF41: -10.989 | AG41: -10.935 | AH41: -10.979 | AI41: =+SUM(AE41:AH41) -> -44.028 | AJ41: -14.08 | AK41: -15.534 | AL41: -15.041 | AM41: -15.128 | AN41: =SUM(AJ41:AM41) -> -59.783 | AO41: -15.564 | AP41: -22.519 | AQ41: -15.643 | AR41: -15.658 | AS41: =SUM(AO41:AR41) -> -69.384 | AT41: -15.065 | AU41: -15.998 | AV41: -16.411 | AW41: -16.045 | AX41: =SUM(AT41:AW41) -> -63.519 | AY41: -16.425 | AZ41: =+(BC41-AY41)/3 -> -14.525 | BA41: -17.305 | BB41: =+BC41-BA41-AZ41-AY41 -> -11.745 | BC41: -60 | BD41: =+BH41/4 -> -13.75 | BE41: =+(BH41-BD41)/3 -> -13.75 | BF41: =+(BH41-BE41-BD41)/2 -> -13.75 | BG41: =+BH41-BF41-BE41-BD41 -> -13.75 | BH41: -55 | BI41: =+BM41/4 -> -13.75 | BJ41: =+(BM41-BI41)/3 -> -13.75 | BK41: =+(BM41-BJ41-BI41)/2 -> -13.75 | BL41: =+BM41-BK41-BJ41-BI41 -> -13.75 | BM41: -55 | BN41: =+BR41/4 -> -13.75 | BO41: =+(BR41-BN41)/3 -> -13.75 | BP41: =+(BR41-BO41-BN41)/2 -> -13.75 | BQ41: =+BR41-BP41-BO41-BN41 -> -13.75 | BR41: -55
A43: EBITDA | AJ43: =AJ44+CF!AJ8 -> 41.22 | AK43: =AK44+CF!AK8 -> 51.24 | AL43: =AL44+CF!AL8 -> 65.265 | AM43: =AM44+CF!AM8 -> 58.692 | AN43: =AN44+CF!AN8 -> 216.417 | AO43: =AO44+CF!AO8 -> 42.866 | AP43: =AP44+CF!AP8 -> 62.278 | AQ43: =AQ44+CF!AQ8 -> 44.101 | ... BR43: =BR44+CF!BR8 -> 390.82062
A44: Income Before Taxes | F44: =F24+F40+F41 -> 74.957 | G44: =G24+G40+G41 -> 94.566 | H44: =H24+H40+H41 -> 89.439 | I44: =I24+I40+I41 -> 66.042 | J44: =J41+J40+J24 -> 325.004 | K44: =K24+K40+K41 -> 54.861 | L44: =L24+L40+L41 -> 81.19 | M44: =M24+M40+M41 -> 114.652 | N44: =N24+N40+N41 -> 113.309 | O44: =O41+O40+O24 -> 364.012 | P44: =P24+P40+P41 -> 72.769 | Q44: =Q24+Q40+Q41 -> -299.034 | R44: =R24+R40+R41 -> 104.969 | S44: =S24+S40+S41 -> 113.823 | T44: =T41+T40+T24 -> -7.473 | U44: =U24+U40+U41 -> 88.2 | V44: =V24+V40+V41 -> 91.638 | W44: =W24+W40+W41 -> 99.798 | X44: =X24+X40+X41 -> 123.061 | Y44: =Y41+Y40+Y24 -> 402.697 | Z44: =Z19+Z40+Z41 -> 27.293 | AA44: =AA19+AA40+AA41 -> 47.612 | AB44: =X19+X40+X41 -> 53.501 | AC44: =AC19+AC40+AC41 -> 53.917 | AD44: =SUM(Z44:AC44) -> 182.323 | AE44: =AE19+AE40+AE41 -> 8.205 | AF44: =AF19+AF40+AF41 -> 19.992 | AG44: =AG19+AG40+AG41 -> 33.955 | AH44: =AH19+AH40+AH41 -> 11.687 | AI44: =AI41+AI40+AI19 -> 73.839 | AJ44: =AJ19+AJ40+AJ41 -> 26.724 | AK44: =AK19+AK40+AK41 -> 35.78 | AL44: =AL19+AL40+AL41 -> 47.926 | AM44: =AM19+AM40+AM41 -> 38.685 | AN44: =AN41+AN40+AN19 -> 149.115 | AO44: =AO19+AO40+AO41 -> 21.87 | AP44: =AP19+AP40+AP41 -> 52.516 | AQ44: =AQ19+AQ40+AQ41 -> 34.396 | AR44: =AR19+AR40+AR41 -> 45.193 | AS44: =AS41+AS40+AS19 -> 153.975 | AT44: =AT19+AT40+AT41 -> -15.21 | AU44: =AU19+AU40+AU41 -> 39.867 | AV44: =AV19+AV40+AV41 -> 32.804 | AW44: =AW19+AW40+AW41 -> 75.152 | AX44: =AX41+AX40+AX19 -> 132.613 | AY44: =AY19+AY40+AY41 -> 6.94 | AZ44: =AZ19+AZ40+AZ41 -> -356.38267 | BA44: =BA19+BA40+BA41 -> 32.312 | BB44: =BB19+BB40+BB41 -> 53.180212 | BC44: =BC41+BC40+BC19 -> -263.95046 | BD44: =BD19+BD40+BD41 -> 58.639698 | BE44: =BE19+BE40+BE41 -> 88.377503 | BF44: =BF19+BF40+BF41 -> 89.121599 | BG44: =BG19+BG40+BG41 -> 89.681816 | BH44: =BH41+BH40+BH19 -> 325.82062 | BI44: =BI19+BI40+BI41 -> 56.585969 | BJ44: =BJ19+BJ40+BJ41 -> 89.359894 | BK44: =BK19+BK40+BK41 -> 88.370393 | BL44: =BL19+BL40+BL41 -> 91.504359 | BM44: =BM41+BM40+BM19 -> 325.82062 | BN44: =BN19+BN40+BN41 -> 54.683642 | BO44: =BO19+BO40+BO41 -> 88.336375 | BP44: =BP19+BP40+BP41 -> 89.949449 | BQ44: =BQ19+BQ40+BQ41 -> 92.851151 | BR44: =BR41+BR40+BR19 -> 325.82062
A45: Provision for Income Taxes | F45: -12.048 | G45: -18.78 | H45: -17.796 | I45: =J45-H45-G45-F45 -> -7.344 | J45: -55.968 | K45: -3.982 | L45: -11.321 | M45: -20.856 | N45: =O45-M45-L45-K45 -> -14.74 | O45: -50.899 | P45: -4.776 | Q45: 15.272 | R45: -1.591 | S45: =T45-R45-Q45-P45 -> -6.463 | T45: 2.442 | U45: -9.116 | V45: -9.679 | W45: -13.276 | X45: =Y45-W45-V45-U45 -> -20.248 | Y45: -52.319 | Z45: -11.354 | AA45: -19.067 | AB45: -22.886 | AC45: -26.195 | AD45: =SUM(Z45:AC45) -> -79.502 | AE45: -3.079 | AF45: -8.215 | AG45: -14.278 | AH45: -2.975 | AI45: =SUM(AE45:AH45) -> -28.547 | AJ45: -11.324 | AK45: -14.419 | AL45: -19.125 | AM45: -8.425 | AN45: =SUM(AJ45:AM45) -> -53.293 | AO45: -8.106 | AP45: -19.883 | AQ45: -9.096 | AR45: 37.654 | AS45: =SUM(AO45:AR45) -> 0.569 | AT45: 4.268 | AU45: -11.971 | AV45: -7.368 | AW45: -19.761 | AX45: =SUM(AT45:AW45) -> -34.832 | AY45: -2.188 | AZ45: 42.9 | BA45: -5.591 | BB45: =BB44*BB78 -> -15.422261 | BC45: =SUM(AY45:BB45) -> 19.698739 | BD45: =BD44*BD78 -> -17.005512 | BE45: =BE44*BE78 -> -25.629476 | BF45: =BF44*BF78 -> -25.845264 | BG45: =BG44*BG78 -> -26.007727 | BH45: =SUM(BD45:BG45) -> -94.487979 | BI45: =BI44*BI78 -> -16.409931 | BJ45: =BJ44*BJ78 -> -25.914369 | BK45: =BK44*BK78 -> -25.627414 | BL45: =BL44*BL78 -> -26.536264 | BM45: =SUM(BI45:BL45) -> -94.487979 | BN45: =BN44*BN78 -> -15.858256 | BO45: =BO44*BO78 -> -25.617549 | BP45: =BP44*BP78 -> -26.08534 | BQ45: =BQ44*BQ78 -> -26.926834 | BR45: =SUM(BN45:BQ45) -> -94.487979
A47: NCI | AP47: -2.537 | AQ47: -1.716 | AR47: -1.909 | AS47: =+SUM(AO47:AR47) -> -6.162 | AT47: -1.182 | AU47: -3.013 | AV47: -4.164 | AW47: -5.986 | AX47: =+SUM(AT47:AW47) -> -14.345 | AY47: -5.078 | AZ47: -5.091 | BA47: -7.408 | BB47: =BA47 -> -7.408 | BC47: =SUM(AY47:BB47) -> -24.985 | BD47: -4 | BE47: =BD47 -> -4 | BF47: =BE47 -> -4 | BG47: =BF47 -> -4 | BH47: =SUM(BD47:BG47) -> -16 | BI47: -4 | BJ47: =BI47 -> -4 | BK47: =BJ47 -> -4 | BL47: =BK47 -> -4 | BM47: =SUM(BI47:BL47) -> -16 | BN47: -4 | BO47: =BN47 -> -4 | BP47: =BO47 -> -4 | BQ47: =BP47 -> -4 | BR47: =SUM(BN47:BQ47) -> -16
A48: Net Income | F48: =F44+F45 -> 62.909 | G48: =G44+G45 -> 75.786 | H48: =H44+H45 -> 71.643 | I48: =I44+I45 -> 58.698 | J48: =J44+J45 -> 269.036 | K48: =K44+K45 -> 50.879 | L48: =L44+L45 -> 69.869 | M48: =M44+M45 -> 93.796 | ... AA48: =AA44+AA45 -> 28.545 | AB48: =X44+X45 -> 102.813 | AC48: =AC44+AC45 -> 27.722 | AD48: =AD44+AD45 -> 102.821 | AE48: =AE44+AE45 -> 5.126 | AF48: =AF44+AF45 -> 11.777 | AG48: =AG44+AG45 -> 19.677 | AH48: =AH44+AH45 -> 8.712 | AI48: =AI44+AI45 -> 45.292 | AJ48: =AJ44+AJ45 -> 15.4 | ... AO48: =AO44+AO45 -> 13.764 | AP48: =AP44+AP45+AP47 -> 30.096 | AQ48: =AQ44+AQ45+AQ47 -> 23.584 | AR48: =AR44+AR45+AR47 -> 80.938 | AS48: =AS44+AS45+AS47 -> 148.382 | AT48: =AT44+AT45+AT47 -> -12.124 | AU48: =AU44+AU45+AU47 -> 24.883 | AV48: =AV44+AV45+AV47 -> 21.272 | AW48: =AW44+AW45+AW47 -> 49.405 | ... BR48: =BR44+BR45+BR47 -> 215.33264
A50: Basic EPS | F50: =F48/F53 -> 1.2832024 | G50: =G48/G53 -> 1.5466215 | H50: =H48/H53 -> 1.5128281 | I50: =I48/I53 -> 1.2200536 | J50: =J48/J53 -> 5.5919852 | K50: =K48/K53 -> 1.0802335 | L50: =L48/L53 -> 1.4808088 | M50: =M48/M53 -> 1.9833795 | ... AA50: =AA48/AA53 -> 0.58803535 | AB50: =X48/X53 -> 2.1486071 | AC50: =AC48/AC53 -> 0.56957942 | AD50: =AD48/AD53 -> 2.1173794 | AE50: =AE48/AE53 -> 0.10515519 | AF50: =AF48/AF53 -> 0.24020968 | AG50: =AG48/AG53 -> 0.40099857 | AH50: =AH48/AH53 -> 0.17753143 | AI50: =AI48/AI53 -> 0.92468508 | AJ50: =AJ48/AJ53 -> 0.31377982 | ... BR50: =BR48/BR53 -> 4.282755
A51: Diluted EPS | F51: =F48/F54 -> 1.2744419 | G51: =G48/G54 -> 1.5299176 | H51: =H48/H54 -> 1.4958034 | I51: =I48/I54 -> 1.2065613 | J51: =J48/J54 -> 5.5301445 | K51: =K48/K54 -> 1.0630354 | L51: =L48/L54 -> 1.4568486 | M51: =M48/M54 -> 1.9637384 | ... AA51: =AA48/AA54 -> 0.5819216 | AB51: =X48/X54 -> 2.1159728 | AC51: =AC48/AC54 -> 0.56124226 | AD51: =AD48/AD54 -> 2.0935597 | AE51: =AE48/AE54 -> 0.10346568 | AF51: =AF48/AF54 -> 0.23635305 | AG51: =AG48/AG54 -> 0.39531894 | AH51: =AH48/AH54 -> 0.17595734 | AI51: =AI48/AI54 -> 0.9119317 | AJ51: =AJ48/AJ54 -> 0.3124683 | ... BR51: =BR48/BR54 -> 4.2571001
A53: Basic Shares | F53: 49.025 | G53: 49.001 | H53: 47.357 | I53: 48.111 | J53: 48.111 | K53: 47.1 | L53: 47.183 | M53: 47.291 | N53: =O53 -> 47.226 | O53: 47.226 | P53: 47.33 | Q53: 47.434 | R53: 47.556 | S53: 47.47 | T53: 47.47 | U53: 47.559 | V53: 47.684 | W53: 47.959 | X53: =Y53 -> 47.851 | Y53: 47.851 | Z53: 48.44 | AA53: 48.543 | AB53: 48.588 | AC53: 48.671 | AD53: =AVERAGE(Z53:AC53) -> 48.5605 | AE53: 48.747 | AF53: 49.028 | AG53: 49.07 | AH53: 49.073 | AI53: 48.981 | AJ53: 49.079 | AK53: 49.131 | AL53: 49.185 | AM53: 49.202 | AN53: =+AVERAGE(AJ53:AM53) -> 49.14925 | AO53: 49.282 | AP53: 49.735 | AQ53: =AP53 -> 49.735 | AR53: 49.781 | AS53: =+AVERAGE(AO53:AR53) -> 49.63325 | AT53: 49.814 | AU53: 49.946 | AV53: 50.018 | AW53: 49.952 | AX53: =+AVERAGE(AT53:AW53) -> 49.9325 | AY53: 50.098 | AZ53: 50.224 | BA53: 50.279 | BB53: =BA53 -> 50.279 | BC53: =+AVERAGE(AY53:BB53) -> 50.22 | BD53: =BB53 -> 50.279 | BE53: =BD53 -> 50.279 | BF53: =BE53 -> 50.279 | BG53: =BF53 -> 50.279 | BH53: =+AVERAGE(BD53:BG53) -> 50.279 | BI53: =BG53 -> 50.279 | BJ53: =BI53 -> 50.279 | BK53: =BJ53 -> 50.279 | BL53: =BK53 -> 50.279 | BM53: =+AVERAGE(BI53:BL53) -> 50.279 | BN53: =BL53 -> 50.279 | BO53: =BN53 -> 50.279 | BP53: =BO53 -> 50.279 | BQ53: =BP53 -> 50.279 | BR53: =+AVERAGE(BN53:BQ53) -> 50.279
A54: Diluted Shares | F54: 49.362 | G54: 49.536 | H54: 47.896 | I54: =J54 -> 48.649 | J54: 48.649 | K54: 47.862 | L54: 47.959 | M54: 47.764 | N54: =O54 -> 47.89 | O54: 47.89 | P54: 47.33 | Q54: 47.434 | R54: 48.217 | S54: =T54 -> 47.47 | T54: 47.47 | U54: 48.513 | V54: 48.598 | W54: 48.625 | X54: =Y54 -> 48.589 | Y54: 48.589 | Z54: 48.93 | AA54: 49.053 | AB54: 49.075 | AC54: 49.394 | AD54: =AVERAGE(Z54:AC54) -> 49.113 | AE54: 49.543 | AF54: 49.828 | AG54: 49.775 | AH54: 49.512 | AI54: 49.666 | AJ54: 49.285 | AK54: 49.561 | AL54: 50.1 | AM54: 50.507 | AN54: =+AVERAGE(AJ54:AM54) -> 49.86325 | AO54: 50.948 | AP54: 50.755 | AQ54: =AP54 -> 50.755 | AR54: 50.732 | AS54: =+AVERAGE(AO54:AR54) -> 50.7975 | AT54: 49.814 | AU54: 49.946 | AV54: 50.375 | AW54: 50.301 | AX54: =+AVERAGE(AT54:AW54) -> 50.109 | AY54: 50.098 | AZ54: 50.224 | BA54: 50.582 | BB54: =BA54 -> 50.582 | BC54: =+AVERAGE(AY54:BB54) -> 50.3715 | BD54: =BB54 -> 50.582 | BE54: =BD54 -> 50.582 | BF54: =BE54 -> 50.582 | BG54: =BF54 -> 50.582 | BH54: =+AVERAGE(BD54:BG54) -> 50.582 | BI54: =BG54 -> 50.582 | BJ54: =BI54 -> 50.582 | BK54: =BJ54 -> 50.582 | BL54: =BK54 -> 50.582 | BM54: =+AVERAGE(BI54:BL54) -> 50.582 | BN54: =BL54 -> 50.582 | BO54: =BN54 -> 50.582 | BP54: =BO54 -> 50.582 | BQ54: =BP54 -> 50.582 | BR54: =+AVERAGE(BN54:BQ54) -> 50.582
AI55: =0.53+0.28+0.2-0.16 -> 0.85
A57: Drivers
A58: Building | K58: =K6/F6-1 -> -0.3582409 | L58: =L6/G6-1 -> -0.095271557 | M58: =M6/H6-1 -> 0.090277738 | N58: =N6/I6-1 -> -0.24716111 | P58: =P6/K6-1 -> -0.22112531 | Q58: =Q6/L6-1 -> -0.44677213 | R58: =R6/M6-1 -> -0.31029143 | S58: =S6/N6-1 -> 0.19789619 | U58: =U6/P6-1 -> 0.23925851 | V58: =V6/Q6-1 -> 0.27247804 | W58: =W6/R6-1 -> -0.10093198 | X58: =X6/S6-1 -> -0.18028514 | Z58: =Z6/U6-1 -> -0.26769055 | AA58: =AA6/V6-1 -> -0.075794453 | AB58: =X6/W6-1 -> -0.040563843 | AC58: =AC6/X6-1 -> 0.29201976 | AE58: =AE6/Z6-1 -> 0.33646949 | AF58: =AF6/AA6-1 -> 0.20979472 | AG58: =AG6/X6-1 -> 0.49898737 | AH58: =AH6/AC6-1 -> 0.15942149 | AJ58: =AJ6/AE6-1 -> 0.17288488 | AK58: =AK6/AF6-1 -> 0.10857454 | AL58: =AL6/AG6-1 -> 0.10772352 | AM58: =AM6/AH6-1 -> 0.090679628 | AO58: =AO6/AJ6-1 -> 0.055855195 | AP58: =AP6/AK6-1 -> -0.02817843 | AQ58: =AQ6/AL6-1 -> -0.10765966 | AR58: -0.02 | AS58: =AS6/AN6-1 -> -0.064577604 | AT58: =AT6/AO6-1 -> -0.047809708 | AU58: =AU6/AP6-1 -> -0.11949234 | AV58: =AV6/AQ6-1 -> -0.086159626 | AW58: =AW6/AR6-1 -> 0.018389149 | AX58: =AX6/AS6-1 -> -0.060413973 | AY58: =AY6/AT6-1 -> -0.11082779 | AZ58: =AZ6/AU6-1 -> -0.032180367 | ... BR58: =BR6/BM6-1 -> 0.0065517926
A59: Civil | K59: =K7/F7-1 -> 0.033410878 | L59: =L7/G7-1 -> -0.28358768 | M59: =M7/H7-1 -> 0.65619849 | N59: =N7/I7-1 -> 0.96476473 | P59: =P7/K7-1 -> 0.94518921 | Q59: =Q7/L7-1 -> 1.3124107 | R59: =R7/M7-1 -> 0.24590642 | S59: =S7/N7-1 -> 0.04962146 | U59: =U7/P7-1 -> 0.13323011 | V59: =V7/Q7-1 -> 0.015748826 | W59: =W7/R7-1 -> 0.083365189 | X59: =X7/S7-1 -> 0.18046561 | Z59: =Z7/U7-1 -> 0.32544062 | AA59: =AA7/V7-1 -> 0.19836074 | AB59: =X7/W7-1 -> 0.12650982 | AC59: =AC7/X7-1 -> 0.07480441 | AE59: =AE7/Z7-1 -> 0.043794767 | AF59: =AF7/AA7-1 -> 0.44015794 | AG59: =AG7/X7-1 -> 0.41258599 | AH59: =AH7/AC7-1 -> -0.054742057 | AJ59: =AJ7/AE7-1 -> -0.064587809 | AK59: =AK7/AF7-1 -> -0.18775813 | AL59: =AL7/AG7-1 -> -0.16252563 | AM59: =AM7/AH7-1 -> 0.040693447 | AO59: =AO7/AJ7-1 -> -0.079980735 | AP59: =AP7/AK7-1 -> 0.15641809 | AQ59: =AQ7/AL7-1 -> -0.094078245 | AR59: =AR7/AM7-1 -> 0.088402859 | AS59: =AS7/AN7-1 -> 0.01999626 | AT59: =AT7/AO7-1 -> -0.037585624 | AU59: =AU7/AP7-1 -> -0.14286086 | AV59: =AV7/AQ7-1 -> 0.046007848 | ... BR59: =BR7/BM7-1 -> 0.21724215
A60: Specialty Contractors | K60: =K8/F8-1 -> #DIV/0! | L60: =L8/G8-1 -> #DIV/0! | M60: =M8/H8-1 -> #DIV/0! | N60: =N8/I8-1 -> #DIV/0! | P60: =P8/K8-1 -> #DIV/0! | Q60: =Q8/L8-1 -> #DIV/0! | R60: =R8/M8-1 -> -0.061475764 | S60: =S8/N8-1 -> -0.30432863 | U60: =U8/P8-1 -> 0.12751741 | V60: =V8/Q8-1 -> 0.029481483 | W60: =W8/R8-1 -> -0.08766137 | X60: =X8/S8-1 -> -0.047170451 | Z60: =Z8/U8-1 -> -0.032238296 | AA60: =AA8/V8-1 -> 0.13351477 | AB60: =X8/W8-1 -> 0.075321677 | AC60: =AC8/X8-1 -> 0.071109416 | AE60: =AE8/Z8-1 -> 0.0029848192 | AF60: =AF8/AA8-1 -> 0.015029864 | AG60: =AG8/X8-1 -> 0.051946666 | AH60: =AH8/AC8-1 -> -0.14622448 | AJ60: =AJ8/AE8-1 -> -0.0383732 | AK60: =AK8/AF8-1 -> -0.024161715 | AL60: =AL8/AG8-1 -> 0.019203049 | AM60: =AM8/AH8-1 -> 0.067647402 | AO60: =AO8/AJ8-1 -> 0.12039124 | AP60: =AP8/AK8-1 -> -0.11616421 | AQ60: -0.05 | AR60: =AR8/AM8-1 -> 0.013361679 | AS60: =AS8/AN8-1 -> -0.016660037 | AT60: =AT8/AO8-1 -> -0.12953918 | AU60: =AU8/AP8-1 -> -0.039821612 | AV60: =AV8/AQ8-1 -> -0.23853974 | AW60: =AW8/AR8-1 -> -0.26383742 | AX60: =AX8/AS8-1 -> -0.17041826 | AY60: =AY8/AT8-1 -> -0.30303383 | ... BR60: =BR8/BM8-1 -> 0.0012304342
A61: Management Services | K61: =K9/F9-1 -> -0.1495631 | L61: =L9/G9-1 -> 0.45829925 | M61: =M9/H9-1 -> 1.0720398 | N61: =N9/I9-1 -> 0.1927121 | P61: =P9/K9-1 -> 0.47956989 | Q61: =Q9/L9-1 -> -0.17422456 | R61: =R9/M9-1 -> -0.39467958 | S61: =S9/N9-1 -> -0.13882367 | U61: =U9/P9-1 -> -0.30454252 | V61: =V9/Q9-1 -> -0.29377982 | W61: =W9/R9-1 -> -0.28434215 | X61: =X9/S9-1 -> -0.10416154 | Z61: =Z9/U9-1 -> -1 | AA61: =AA9/V9-1 -> -1 | AB61: =X9/W9-1 -> 0.37538819 | AC61: =AC9/X9-1 -> -1 | AE61: =AE9/Z9-1 -> #DIV/0! | AF61: =AF9/AA9-1 -> #DIV/0! | AG61: =AG9/X9-1 -> -1 | AH61: =AH9/AC9-1 -> #DIV/0! | AJ61: =AJ9/AE9-1 -> #DIV/0! | AK61: =AK9/AF9-1 -> #DIV/0! | AL61: =AL9/AG9-1 -> #DIV/0! | AM61: =AM9/AH9-1 -> #DIV/0! | AO61: =AO9/AJ9-1 -> #DIV/0! | AP61: =AP9/AK9-1 -> #DIV/0! | AQ61: =AQ9/AL9-1 -> #DIV/0! | AR61: =AR9/AM9-1 -> #DIV/0! | AS61: =AS9/AN9-1 -> #DIV/0! | AT61: =AT9/AO9-1 -> #DIV/0! | AU61: =AU9/AP9-1 -> #DIV/0! | AV61: =AV9/AQ9-1 -> #DIV/0! | ... BR61: =BR9/BM9-1 -> #DIV/0!
A62: Eliminations (% of construction revenue) | M62: =-M10/SUM(M6:M9) -> 0.08188068 | N62: =-N10/SUM(N6:N9) -> 0.087649517 | P62: =-P10/SUM(P6:P9) -> 0.018227474 | Q62: =-Q10/SUM(Q6:Q9) -> 0.014329714 | R62: =-R10/SUM(R6:R9) -> 0.0087405226 | S62: =-S10/SUM(S6:S9) -> 0.036065006 | U62: =-U10/SUM(U6:U9) -> 0.061801792 | V62: =-V10/SUM(V6:V9) -> 0.028868402 | W62: =-W10/SUM(W6:W9) -> 0.024662026 | X62: =-X10/SUM(X6:X9) -> 0.023523392 | Z62: =-Z10/SUM(Z6:Z9) -> 0.025125223 | AA62: =-AA10/SUM(AA6:AA9) -> 0.023346706 | AB62: =-X10/SUM(X6:X9) -> 0.023523392 | AC62: =-AC10/SUM(AC6:AC9) -> 0.020843822 | AE62: =-AE10/SUM(AE6:AE9) -> 0.032207275 | AF62: =-AF10/SUM(AF6:AF9) -> 0.043694828 | AG62: =-AG10/SUM(AG6:AG9) -> 0.066299381 | AH62: =-AH10/SUM(AH6:AH9) -> 0.018459016 | AJ62: =-AJ10/SUM(AJ6:AJ9) -> 0.045634802 | AK62: =-AK10/SUM(AK6:AK9) -> 0.047288114 | AL62: =-AL10/SUM(AL6:AL9) -> 0.046857079 | AM62: =-AM10/SUM(AM6:AM9) -> 0.045564274 | AO62: =-AO10/SUM(AO6:AO9) -> 0.044218621 | AP62: =-AP10/SUM(AP6:AP9) -> 0.061620039 | AQ62: =-AQ10/SUM(AQ6:AQ9) -> 0.054796366 | AR62: =-AR10/SUM(AR6:AR9) -> 0.053746214 | AS62: =-AS10/SUM(AS6:AS9) -> 0.053877501 | AT62: =-AT10/SUM(AT6:AT9) -> 0.057444963 | AU62: =-AU10/SUM(AU6:AU9) -> 0.050953973 | AV62: =-AV10/SUM(AV6:AV9) -> 0.042543234 | ... BR62: =-BR10/SUM(BR6:BR9) -> 0.034803042
A63: Revenue | K63: =K11/F11-1 -> -0.28874491 | L63: =L11/G11-1 -> -0.10336885 | M63: =M11/H11-1 -> 0.59387871 | N63: =N11/I11-1 -> 0.62040139 | P63: =P11/K11-1 -> 0.48309819 | Q63: =Q11/L11-1 -> 0.20184959 | R63: =R11/M11-1 -> -0.057455783 | S63: =S11/N11-1 -> -0.00050414439 | U63: =U11/P11-1 -> 0.088099731 | V63: =V11/Q11-1 -> 0.068726112 | W63: =W11/R11-1 -> -0.062766454 | X63: =X11/S11-1 -> -0.01337913 | Z63: =Z11/U11-1 -> -0.037963478 | AA63: =AA11/V11-1 -> 0.029860455 | AB63: =X11/W11-1 -> 0.066870926 | AC63: =AC11/X11-1 -> 0.093320149 | AE63: =AE11/Z11-1 -> 0.11644489 | AF63: =AF11/AA11-1 -> 0.2101668 | AG63: =AG11/X11-1 -> 0.21963975 | AH63: =AH11/AC11-1 -> -0.0008711374 | AJ63: =AJ11/AE11-1 -> 0.017725851 | AK63: =AK11/AF11-1 -> -0.050415334 | AL63: =AL11/AG11-1 -> -0.0057885987 | AM63: =AM11/AH11-1 -> 0.038114471 | AN63: =+AN11/AI11-1 -> -0.0018809171 | AO63: =AO11/AJ11-1 -> 0.02947569 | AP63: =AP11/AK11-1 -> 0.00080480088 | AQ63: =AQ11/AL11-1 -> -0.10013144 | AR63: =AR11/AM11-1 -> -0.042941636 | AS63: =AS11/AN11-1 -> -0.031358623 | AT63: =AT11/AO11-1 -> -0.079835434 | AU63: =AU11/AP11-1 -> -0.10197358 | AV63: =AV11/AQ11-1 -> -0.063666262 | ... BR63: =BR11/BM11-1 -> 0
A64: % of revenue
A65: Building | U65: =U6/U$11 -> 0.42814182 | V65: =V6/V$11 -> 0.40108255 | W65: =W6/W$11 -> 0.3416315 | X65: =X6/X$11 -> 0.30722893 | Z65: =Z6/Z$11 -> 0.32590478 | AA65: =AA6/AA$11 -> 0.3599349 | AB65: =X6/X$11 -> 0.30722893 | AC65: =AC6/AC$11 -> 0.36306461 | AE65: =AE6/AE$11 -> 0.39013282 | AF65: =AF6/AF$11 -> 0.35982424 | AG65: =AG6/AG$11 -> 0.37759698 | AH65: =AH6/AH$11 -> 0.42131193 | AJ65: =AJ6/AJ$11 -> 0.44961115 | AK65: =AK6/AK$11 -> 0.42006995 | AL65: =AL6/AL$11 -> 0.42070837 | AM65: =AM6/AM$11 -> 0.44264515 | AO65: =AO6/AO$11 -> 0.46113208 | AP65: =AP6/AP$11 -> 0.40790476 | AQ65: =AQ6/AQ$11 -> 0.41718876 | AR65: =AR6/AR$11 -> 0.38765686 | AT65: =AT6/AT$11 -> 0.47718148 | AU65: =AU6/AU$11 -> 0.39994733 | AV65: =AV6/AV$11 -> 0.40716671 | AW65: =AW6/AW$11 -> 0.39804983 | AY65: =AY6/AY$11 -> 0.45513711 | AZ65: =AZ6/AZ$11 -> 0.3852916 | BA65: =BA6/BA$11 -> 0.35417898 | BB65: =BB6/BB$11 -> 0.37838266 | BD65: =BD6/BD$11 -> 0.34642657 | BE65: =BE6/BE$11 -> 0.30150239 | BF65: =BF6/BF$11 -> 0.30288718 | BG65: =BG6/BG$11 -> 0.32131006 | BI65: =BI6/BI$11 -> 0.3490929 | BJ65: =BJ6/BJ$11 -> 0.30079188 | BK65: =BK6/BK$11 -> 0.30286862 | BL65: =BL6/BL$11 -> 0.32065199 | BN65: =BN6/BN$11 -> 0.34249477 | BO65: =BO6/BO$11 -> 0.30149997 | BP65: =BP6/BP$11 -> 0.29987998 | BQ65: =BQ6/BQ$11 -> 0.32784127
A66: Civil | U66: =U7/U$11 -> 0.28599757 | V66: =V7/V$11 -> 0.31548195 | W66: =W7/W$11 -> 0.36856505 | X66: =X7/X$11 -> 0.38916811 | Z66: =Z7/Z$11 -> 0.39403161 | AA66: =AA7/AA$11 -> 0.36709943 | AB66: =X7/X$11 -> 0.38916811 | AC66: =AC7/AC$11 -> 0.38257742 | AE66: =AE7/AE$11 -> 0.3683909 | AF66: =AF7/AF$11 -> 0.43686635 | AG66: =AG7/AG$11 -> 0.45073426 | AH66: =AH7/AH$11 -> 0.36194965 | AJ66: =AJ7/AJ$11 -> 0.33859545 | AK66: =AK7/AK$11 -> 0.37368036 | AL66: =AL7/AL$11 -> 0.37967618 | AM66: =AM7/AM$11 -> 0.36284884 | AO66: =AO7/AO$11 -> 0.30259513 | AP66: =AP7/AP$11 -> 0.43178323 | AQ66: =AQ7/AQ$11 -> 0.38223017 | AR66: =AR7/AR$11 -> 0.41264538 | AT66: =AT7/AT$11 -> 0.31648894 | AU66: =AU7/AU$11 -> 0.41212408 | AV66: =AV7/AV$11 -> 0.42700134 | AW66: =AW7/AW$11 -> 0.4594307 | AY66: =AY7/AY$11 -> 0.40023704 | AZ66: =AZ7/AZ$11 -> 0.48087534 | BA66: =BA7/BA$11 -> 0.49765543 | BB66: =BB7/BB$11 -> 0.34347038 | BD66: =BD7/BD$11 -> 0.48722615 | BE66: =BE7/BE$11 -> 0.54770116 | BF66: =BF7/BF$11 -> 0.53753028 | BG66: =BG7/BG$11 -> 0.51409643 | BI66: =BI7/BI$11 -> 0.48391869 | BJ66: =BJ7/BJ$11 -> 0.55143039 | BK66: =BK7/BK$11 -> 0.53757478 | BL66: =BL7/BL$11 -> 0.51223249 | BN66: =BN7/BN$11 -> 0.49772826 | BO66: =BO7/BO$11 -> 0.54698288 | BP66: =BP7/BP$11 -> 0.54142768 | BQ66: =BQ7/BQ$11 -> 0.50313035
A67: Specialty Contractors | U67: =U8/U$11 -> 0.30402708 | V67: =V8/V$11 -> 0.26972314 | W67: =W8/W$11 -> 0.27915018 | X67: =X8/X$11 -> 0.28136135 | Z67: =Z8/Z$11 -> 0.30583638 | AA67: =AA8/AA$11 -> 0.29687048 | AB67: =X8/X$11 -> 0.28136135 | AC67: =AC8/AC$11 -> 0.27564551 | AE67: =AE8/AE$11 -> 0.27475538 | AF67: =AF8/AF$11 -> 0.24900071 | AG67: =AG8/AG$11 -> 0.24267587 | AH67: =AH8/AH$11 -> 0.23554458 | AJ67: =AJ8/AJ$11 -> 0.25961033 | AK67: =AK8/AK$11 -> 0.25588496 | AL67: =AL8/AL$11 -> 0.24877605 | AM67: =AM8/AM$11 -> 0.2422455 | AO67: =AO8/AO$11 -> 0.28253716 | AP67: =AP8/AP$11 -> 0.22597841 | AQ67: =AQ8/AQ$11 -> 0.25855415 | AR67: =AR8/AR$11 -> 0.2564967 | AT67: =AT8/AT$11 -> 0.26727559 | AU67: =AU8/AU$11 -> 0.24161827 | AV67: =AV8/AV$11 -> 0.21026553 | AW67: =AW8/AW$11 -> 0.19038456 | AY67: =AY8/AY$11 -> 0.19982222 | AZ67: =AZ8/AZ$11 -> 0.19843949 | BA67: =BA8/BA$11 -> 0.20973981 | BB67: =BB8/BB$11 -> 0.35217359 | BD67: =BD8/BD$11 -> 0.2353846 | BE67: =BE8/BE$11 -> 0.20191639 | BF67: =BF8/BF$11 -> 0.20986947 | BG67: =BG8/BG$11 -> 0.21345074 | BI67: =BI8/BI$11 -> 0.23791585 | BJ67: =BJ8/BJ$11 -> 0.19855733 | BK67: =BK8/BK$11 -> 0.21023012 | BL67: =BL8/BL$11 -> 0.21502109 | BN67: =BN8/BN$11 -> 0.23378539 | BO67: =BO8/BO$11 -> 0.20262734 | BP67: =BP8/BP$11 -> 0.208752 | BQ67: =BQ8/BQ$11 -> 0.21587396
A68: Eliminations (#) | X68: =X10 -> -26.482 | Z68: =Z10 -> -24.619 | AA68: =AA10 -> -25.925 | AB68: =X10 -> -26.482 | AC68: =AC10 -> -25.585 | AD68: =SUM(Z68:AC68) -> -102.611 | AE68: =AE10 -> -35.491 | AF68: =AF10 -> -59.967 | AG68: =AG10 -> -95.202 | AH68: =AH10 -> -22.583 | AI68: =SUM(AE68:AH68) -> -213.243 | AJ68: =AJ10 -> -51.899 | AK68: =AK10 -> -61.859 | AL68: =AL10 -> -65.53 | AM68: =AM10 -> -59.512 | AN68: =SUM(AJ68:AM68) -> -238.8 | AO68: =AO10 -> -51.694
A70: Margins | AD70: =+AD51-0.33 -> 1.7635597 | AI70: =+AI55+AI51 -> 1.7619317
A71: Building | F71: =F14/F6 -> 0.047079635 | G71: =G14/G6 -> 0.044764664 | H71: =H14/H6 -> 0.054110945 | I71: =I14/I6 -> 0.012447797 | J71: =J14/J6 -> 0.041193736 | K71: =K14/K6 -> 0.029784596 | L71: =L14/L6 -> 0.041536592 | M71: =M14/M6 -> 0.01563568 | ... AA71: =AA14/AA6 -> 0.019659129 | AB71: =X14/X6 -> 0.0089064175 | AC71: =AC14/AC6 -> -0.0090728047 | AD71: =AD14/AD6 -> 0.015847349 | AE71: =AE14/AE6 -> -0.0054775359 | AF71: =AF14/AF6 -> -0.026664013 | AG71: =AG14/AG6 -> 0.013358775 | AH71: =AH14/AH6 -> 0.013573185 | AI71: =AI14/AI6 -> -0.00065298846 | AJ71: =AJ14/AJ6 -> 0.025512609 | ... AT71: =AT14/AT6 -> 0.013095755 | AU71: 0.015 | AV71: 0.015 | AW71: 0.015 | AX71: =AX14/AX6 -> 0.023535783 | AY71: 0.02 | AZ71: 0.02 | BA71: 0.02 | BB71: 0.02 | BC71: =BC14/BC6 -> 0.0094623125 | BD71: 0.04 | BE71: 0.04 | BF71: 0.04 | BG71: 0.04 | BH71: =BH14/BH6 -> 0.036663873 | BI71: 0.04 | BJ71: 0.04 | BK71: 0.04 | BL71: 0.04 | BM71: =BM14/BM6 -> 0.035726566 | BN71: 0.04 | BO71: 0.04 | BP71: 0.04 | BQ71: 0.04 | BR71: =BR14/BR6 -> 0.035494017
A72: Civil | F72: =F15/F7 -> 0.066500882 | G72: =G15/G7 -> 0.1505336 | H72: =H15/H7 -> 0.1606899 | I72: =I15/I7 -> 0.12788719 | J72: =J15/J7 -> 0.13146844 | K72: =K15/K7 -> 0.094034543 | L72: =L15/L7 -> 0.10805136 | M72: =M15/M7 -> 0.084608413 | ... AA72: =AA15/AA7 -> 0.14568864 | AB72: =X15/X7 -> 0.16264969 | AC72: =AC15/AC7 -> 0.14032505 | AD72: =AD15/AD7 -> 0.12745338 | AE72: =AE15/AE7 -> 0.077869353 | AF72: =AF15/AF7 -> 0.080802637 | AG72: =AG15/AG7 -> 0.07145753 | AH72: =AH15/AH7 -> 0.057765047 | AI72: =AI15/AI7 -> 0.072417967 | AJ72: =AJ15/AJ7 -> 0.091605193 | ... AT72: =AT15/AT7 -> 0.0087246466 | AU72: =AT72 -> 0.0087246466 | AV72: =AU72 -> 0.0087246466 | AW72: =AV72 -> 0.0087246466 | AX72: =AX15/AX7 -> 0.092947202 | AY72: 0.105 | AZ72: =AY72 -> 0.105 | BA72: =AZ72 -> 0.105 | BB72: =BA72 -> 0.105 | BC72: =BC15/BC7 -> -0.0075293937 | BD72: 0.105 | BE72: =BD72 -> 0.105 | BF72: =BE72 -> 0.105 | BG72: =BF72 -> 0.105 | BH72: =BH15/BH7 -> 0.089224824 | BI72: 0.105 | BJ72: =BI72 -> 0.105 | BK72: =BJ72 -> 0.105 | BL72: =BK72 -> 0.105 | BM72: =BM15/BM7 -> 0.069171414 | BN72: 0.105 | BO72: =BN72 -> 0.105 | BP72: =BO72 -> 0.105 | BQ72: =BP72 -> 0.105 | BR72: =BR15/BR7 -> 0.056826338
A73: Specialty Contractors | F73: =F16/F8 -> #DIV/0! | G73: =G16/G8 -> #DIV/0! | H73: =H16/H8 -> #DIV/0! | I73: =I16/I8 -> #DIV/0! | K73: =K16/K8 -> #DIV/0! | L73: =L16/L8 -> #DIV/0! | M73: =M16/M8 -> 0.098630333 | N73: =N16/N8 -> 0.069543563 | O73: =O16/O8 -> 0.081718554 | P73: =P16/P8 -> 0.073759226 | Q73: =Q16/Q8 -> 0.030369479 | R73: =R16/R8 -> 0.045154947 | ... AA73: =AA16/AA8 -> 0.039237915 | AB73: =X16/X8 -> 0.014306591 | AC73: =AC16/AC8 -> 0.059379641 | AD73: =AD16/AD8 -> 0.039189197 | AE73: =AE16/AE8 -> 0.035916005 | AF73: =AF16/AF8 -> 0.042053501 | AG73: =AG16/AG8 -> 0.014571328 | AH73: =AH16/AH8 -> -0.047113478 | AI73: =AI16/AI8 -> 0.012770057 | AJ73: =AJ16/AJ8 -> 0.033406324 | ... AT73: =AT16/AT8 -> 0.026328143 | AU73: 0.04 | AV73: 0.04 | AW73: 0.04 | AX73: =AX16/AX8 -> 0.043133672 | AY73: 0.05 | AZ73: 0.05 | BA73: 0.05 | BB73: 0.05 | BC73: 0.04 | BD73: 0.05 | BE73: 0.05 | BF73: 0.05 | BG73: 0.05 | BH73: 0.04 | BI73: 0.05 | BJ73: 0.05 | BK73: 0.05 | BL73: 0.05 | BM73: 0.04 | BN73: 0.05 | BO73: 0.05 | BP73: 0.05 | BQ73: 0.05 | BR73: 0.04
A74: Management Services | F74: =F17/F9 -> 0.057139162 | G74: =G17/G9 -> 0.12731464 | H74: =H17/H9 -> 0.071118652 | I74: =I17/I9 -> 0.16761815 | J74: =J17/J9 -> 0.10831386 | K74: =K17/K9 -> 0.057369393 | L74: =L17/L9 -> 0.083109168 | M74: =M17/M9 -> 0.062972322 | ... AA74: =AA17/AA9 -> #DIV/0! | AB74: =X17/X9 -> 0.084760072 | AC74: =AC17/AC9 -> #DIV/0! | AD74: =AD17/AD9 -> #DIV/0! | AE74: =AE17/AE9 -> #DIV/0! | AF74: =AF17/AF9 -> #DIV/0! | AG74: =AG17/AG9 -> #DIV/0! | AH74: =AH17/AH9 -> #DIV/0! | AI74: =AI17/AI9 -> #DIV/0! | AJ74: =AJ17/AJ9 -> #DIV/0! | ... AT74: =AT17/AT9 -> #DIV/0! | AU74: =+AT74 -> #DIV/0! | AV74: =+AU74 -> #DIV/0! | AW74: =+AV74 -> #DIV/0! | AX74: =AX17/AX9 -> #DIV/0! | AZ74: =+AY74 -> 0 | BA74: =+AZ74 -> 0 | BB74: =+BA74 -> 0 | BC74: =BC17/BC9 -> #DIV/0! | BE74: =+BD74 -> 0 | BF74: =+BE74 -> 0 | BG74: =+BF74 -> 0 | BH74: =BH17/BH9 -> #DIV/0! | BJ74: =+BI74 -> 0 | BK74: =+BJ74 -> 0 | BL74: =+BK74 -> 0 | BM74: =BM17/BM9 -> #DIV/0! | BO74: =+BN74 -> 0 | BP74: =+BO74 -> 0 | BQ74: =+BP74 -> 0 | BR74: =BR17/BR9 -> #DIV/0!
A75: Corporate (% of sales) | F75: =-F18/F11 -> 0.011023322 | G75: =-G18/G11 -> 0.011377158 | H75: =-H18/H11 -> 0.01154131 | I75: =-I18/I11 -> 0.0074060292 | J75: =-J18/J11 -> 0.010465084 | K75: =-K18/K11 -> 0.015212364 | L75: =-L18/L11 -> 0.01181668 | M75: =-M18/M11 -> 0.0078531563 | ... AA75: =-AA18/AA11 -> 0.011863422 | AB75: =-X18/X11 -> 0.010150179 | AC75: =-AC18/AC11 -> 0.013179385 | AD75: =-AD18/AD11 -> 0.01215768 | AE75: =-AE18/AE11 -> 0.0175852 | AF75: =-AF18/AF11 -> 0.012647455 | AG75: =-AG18/AG11 -> 0.011719656 | AH75: =-AH18/AH11 -> 0.0026431718 | AI75: =-AI18/AI11 -> 0.011023333 | AJ75: =-AJ18/AJ11 -> 0.014194251 | ... AT75: =-AT18/AT11 -> 0.016946845 | AU75: =+AT75 -> 0.016946845 | AV75: =+AU75 -> 0.016946845 | AW75: =+AV75 -> 0.016946845 | AX75: =-AX18/AX11 -> 0.014310626 | AY75: 0.0123 | AZ75: =+AY75 -> 0.0123 | BA75: =+AZ75 -> 0.0123 | BB75: =+BA75 -> 0.0123 | BC75: =-BC18/BC11 -> 0.013465338 | BD75: 0.0123 | BE75: =+BD75 -> 0.0123 | BF75: =+BE75 -> 0.0123 | BG75: =+BF75 -> 0.0123 | BH75: =-BH18/BH11 -> 0.0123 | BI75: 0.0123 | BJ75: =+BI75 -> 0.0123 | BK75: =+BJ75 -> 0.0123 | BL75: =+BK75 -> 0.0123 | BM75: =-BM18/BM11 -> 0.0123 | BN75: 0.0123 | BO75: =+BN75 -> 0.0123 | BP75: =+BO75 -> 0.0123 | BQ75: =+BP75 -> 0.0123 | BR75: =-BR18/BR11 -> 0.0123
A76: Operating Margin | F76: =+F19/F11 -> 0.039484438 | G76: =+G19/G11 -> 0.061081 | H76: =+H19/H11 -> 0.068269459 | I76: =+I19/I11 -> 0.04701484 | J76: =+J19/J11 -> 0.053860797 | K76: =+K19/K11 -> 0.0300883 | L76: =+L19/L11 -> 0.045172457 | M76: =+M19/M11 -> 0.053185415 | ... AA76: =+AA19/AA11 -> 0.060343381 | AB76: =+X19/X11 -> 0.0638366 | AC76: =+AC19/AC11 -> 0.053579526 | AD76: =+AD19/AD11 -> 0.053817216 | AE76: =+AE19/AE11 -> 0.01883231 | AF76: =+AF19/AF11 -> 0.023529492 | AG76: =+AG19/AG11 -> 0.029069043 | AH76: =+AH19/AH11 -> 0.012886087 | AI76: =+AI19/AI11 -> 0.021423351 | AJ76: =+AJ19/AJ11 -> 0.03696623 | ... BR76: =+BR19/BR11 -> 0.066045503
A77: G&A (% of sales) | F77: =F22/F11 -> 0 | G77: =G22/G11 -> 0 | H77: =H22/H11 -> 0 | I77: =I22/I11 -> 0 | K77: =K22/K11 -> 0 | L77: =L22/L11 -> 0 | M77: =M22/M11 -> 0 | N77: =N22/N11 -> 0 | P77: =P22/P11 -> 0 | Q77: =Q22/Q11 -> 0 | R77: =R22/R11 -> 0 | S77: =S22/S11 -> 0 | U77: =U22/U11 -> 0 | V77: =V22/V11 -> 0 | W77: =W22/W11 -> 0 | X77: =X22/X11 -> 0 | Z77: =Z22/Z11 -> 0 | AA77: =AA22/AA11 -> 0 | AB77: =X22/X11 -> 0 | AE77: =AE22/AE11 -> 0 | AF77: =AF22/AF11 -> 0 | AG77: =AG22/AG11 -> 0 | AH77: =AH22/AH11 -> 0 | AJ77: =AJ22/AJ11 -> 0 | AK77: =AK22/AK11 -> 0 | AL77: =AL22/AL11 -> 0 | AM77: =AM22/AM11 -> 0 | AO77: =AO22/AO11 -> 0 | AP77: =AP22/AP11 -> 0 | AQ77: =AQ22/AQ11 -> 0 | AR77: =AR22/AR11 -> 0 | AT77: 0.06 | AU77: 0.06 | AV77: 0.06 | AW77: 0.06 | AY77: 0.06 | AZ77: 0.06 | BA77: 0.06 | BB77: 0.06 | BD77: 0.06 | BE77: 0.06 | BF77: 0.06 | BG77: 0.06 | BI77: 0.06 | BJ77: 0.06 | BK77: 0.06 | BL77: 0.06 | BN77: 0.06 | BO77: 0.06 | BP77: 0.06 | BQ77: 0.06
A78: Tax rate | F78: =F45/F44 -> -0.16073215 | G78: =G45/G44 -> -0.19859146 | H78: =H45/H44 -> -0.1989736 | I78: =I45/I44 -> -0.11120196 | K78: =K45/K44 -> -0.072583438 | L78: =L45/L44 -> -0.13943835 | M78: =M45/M44 -> -0.18190699 | N78: =N45/N44 -> -0.13008675 | P78: =P45/P44 -> -0.065632343 | Q78: =Q45/Q44 -> -0.051071116 | R78: =R45/R44 -> -0.015156856 | S78: =S45/S44 -> -0.056781143 | U78: =U45/U44 -> -0.10335601 | V78: =V45/V44 -> -0.10562212 | W78: =W45/W44 -> -0.13302872 | X78: =X45/X44 -> -0.16453629 | Y78: =Y45/Y44 -> -0.1299215 | Z78: =Z45/Z44 -> -0.4160041 | AA78: =AA45/AA44 -> -0.40046627 | AB78: =X45/X44 -> -0.16453629 | AC78: =AC45/AC44 -> -0.48583935 | AD78: =AD45/AD44 -> -0.43605031 | AE78: =AE45/AE44 -> -0.37525899 | AF78: =AF45/AF44 -> -0.41091437 | AG78: =AG45/AG44 -> -0.42049772 | AH78: =AH45/AH44 -> -0.25455634 | AI78: =AI45/AI44 -> -0.38661141 | AJ78: =AJ45/AJ44 -> -0.42373896 | ... AS78: =AS45/AS44 -> 0.0036954051 | AT78: -0.29 | AU78: -0.29 | AV78: -0.29 | AW78: -0.29 | AX78: =AX45/AX44 -> -0.26265902 | AY78: -0.29 | AZ78: -0.29 | BA78: -0.29 | BB78: -0.29 | BC78: =BC45/BC44 -> -0.07463044 | BD78: -0.29 | BE78: -0.29 | BF78: -0.29 | BG78: -0.29 | BH78: =BH45/BH44 -> -0.29 | BI78: -0.29 | BJ78: -0.29 | BK78: -0.29 | BL78: -0.29 | BM78: =BM45/BM44 -> -0.29 | BN78: -0.29 | BO78: -0.29 | BP78: -0.29 | BQ78: -0.29 | BR78: =BR45/BR44 -> -0.29
A80: Seasonality
A81: Building | F81: =F6/J6 -> 0.29492475 | G81: =G6/J6 -> 0.28498612 | H81: =H6/J6 -> 0.22375396 | I81: =I6/J6 -> 0.19633516 | K81: =K6/O6 -> 0.22562614 | L81: =L6/O6 -> 0.30736054 | M81: =M6/O6 -> 0.29081315 | N81: =N6/O6 -> 0.17620016 | P81: =P6/T6 -> 0.23201701 | Q81: =Q6/T6 -> 0.22449929 | R81: =R6/T6 -> 0.26481494 | S81: =S6/T6 -> 0.27866877 | U81: =U6/Y6 -> 0.27654601 | V81: =V6/Y6 -> 0.27475838 | W81: =W6/Y6 -> 0.2289922 | X81: =X6/Y6 -> 0.2197034 | Z81: =Z6/AD6 -> 0.19976181 | AA81: =AA6/AD6 -> 0.25047821 | AB81: =X6/AD6 -> 0.21671412 | AC81: =AC6/AD6 -> 0.27999892 | AD81: 1 | AE81: =AE6/AI6 -> 0.21892372 | AF81: =AF6/$AI6 -> 0.24848658 | AG81: =AG6/$AI6 -> 0.26638299 | AH81: =AH6/AI6 -> 0.26620672 | AI81: 1 | AJ81: =AJ6/AN6 -> 0.22974035 | AK81: =AK6/AN6 -> 0.24646593 | AL81: =AL6/$AN6 -> 0.26401398 | AM81: =AM6/$AN6 -> 0.25977974 | AN81: 1 | AO81: =AO6/$AS6 -> 0.25931872 | AP81: =AP6/$AS6 -> 0.25605642 | AQ81: =AQ6/$AS6 -> 0.25185448 | AR81: =AR6/$AS6 -> 0.23277037 | AS81: 1 | AT81: 0.15 | AU81: =+AVERAGE(AA81,AF81,AK81,AP81) -> 0.25037178 | AV81: =+AVERAGE(X81,AG81,AL81,AQ81) -> 0.25048871 | AW81: =AX81-SUM(AT81:AV81) -> 0.3491395 | AX81: 1 | AY81: =+AVERAGE(AE81,AJ81,AO81,AT81) -> 0.2144957 | AZ81: =+AVERAGE(AF81,AK81,AP81,AU81) -> 0.25034518 | BA81: =+AVERAGE(AG81,AL81,AQ81,AV81) -> 0.25818504 | BB81: =BC81-SUM(AY81:BA81) -> 0.27697408 | BC81: 1 | BD81: =+AVERAGE(AJ81,AO81,AT81,AY81) -> 0.21338869 | BE81: =+AVERAGE(AK81,AP81,AU81,AZ81) -> 0.25080983 | BF81: =+AVERAGE(AL81,AQ81,AV81,BA81) -> 0.25613555 | BG81: =BH81-SUM(BD81:BF81) -> 0.27966592 | BH81: 1 | BI81: =+AVERAGE(AO81,AT81,AY81,BD81) -> 0.20930078 | BJ81: =+AVERAGE(AP81,AU81,AZ81,BE81) -> 0.2518958 | BK81: =+AVERAGE(AQ81,AV81,BA81,BF81) -> 0.25416595 | BL81: =BM81-SUM(BI81:BK81) -> 0.28463747 | BM81: 1 | BN81: =+AVERAGE(AT81,AY81,BD81,BI81) -> 0.19679629 | BO81: =+AVERAGE(AU81,AZ81,BE81,BJ81) -> 0.25085565 | BP81: =+AVERAGE(AV81,BA81,BF81,BK81) -> 0.25474381 | BQ81: =BR81-SUM(BN81:BP81) -> 0.29760425 | BR81: 1
A82: Civil | F82: =F7/J7 -> 0.1866995 | G82: =G7/J7 -> 0.29568641 | H82: =H7/J7 -> 0.25442412 | I82: =I7/J7 -> 0.26318998 | K82: =K7/O7 -> 0.14363427 | L82: =L7/O7 -> 0.15770167 | M82: =M7/O7 -> 0.31369858 | N82: =N7/O7 -> 0.38496548 | P82: =P7/T7 -> 0.19416323 | Q82: =Q7/T7 -> 0.25342435 | R82: =R7/T7 -> 0.27160955 | S82: =S7/T7 -> 0.28080288 | U82: =U7/Y7 -> 0.19945258 | V82: =V7/Y7 -> 0.23334003 | W82: =W7/Y7 -> 0.26673161 | X82: =X7/Y7 -> 0.30047578 | Z82: =Z7/AD7 -> 0.21750879 | AA82: =AA7/AD7 -> 0.23006666 | AB82: =X7/AD7 -> 0.24722156 | AC82: =AC7/AD7 -> 0.26571482 | AD82: 1 | AE82: =AE7/AI7 -> 0.19592927 | AF82: =AF7/$AI7 -> 0.28593756 | AG82: =AG7/$AI7 -> 0.30137598 | AH82: =AH7/AI7 -> 0.21675719 | AI82: 1 | AJ82: =AJ7/AN7 -> 0.20512046 | AK82: =AK7/AN7 -> 0.25993408 | AL82: =AL7/$AN7 -> 0.28247941 | AM82: =AM7/$AN7 -> 0.25246604 | AN82: 1 | AO82: =AO7/$AS7 -> 0.18501517 | AP82: =AP7/$AS7 -> 0.29469959 | AQ82: =AQ7/$AS7 -> 0.25088743 | AR82: =AR7/$AS7 -> 0.26939781 | AS82: 1 | AT82: 0.15 | AU82: =+AVERAGE(AA82,AF82,AK82,AP82) -> 0.26765947 | AV82: =+AVERAGE(X82,AG82,AL82,AQ82) -> 0.28380465 | AW82: =AX82-SUM(AT82:AV82) -> 0.29853588 | AX82: 1 | AY82: =+AVERAGE(AE82,AJ82,AO82,AT82) -> 0.18401622 | AZ82: =+AVERAGE(AF82,AK82,AP82,AU82) -> 0.27705768 | BA82: =+AVERAGE(AG82,AL82,AQ82,AV82) -> 0.27963687 | BB82: =BC82-SUM(AY82:BA82) -> 0.25928923 | BC82: 1 | BD82: =+AVERAGE(AJ82,AO82,AT82,AY82) -> 0.18103796 | BE82: =+AVERAGE(AK82,AP82,AU82,AZ82) -> 0.2748377 | BF82: =+AVERAGE(AL82,AQ82,AV82,BA82) -> 0.27420209 | BG82: =BH82-SUM(BD82:BF82) -> 0.26992224 | BH82: 1 | BI82: =+AVERAGE(AO82,AT82,AY82,BD82) -> 0.17501734 | BJ82: =+AVERAGE(AP82,AU82,AZ82,BE82) -> 0.27856361 | BK82: =+AVERAGE(AQ82,AV82,BA82,BF82) -> 0.27213276 | BL82: =BM82-SUM(BI82:BK82) -> 0.27428629 | BM82: 1 | BN82: =+AVERAGE(AT82,AY82,BD82,BI82) -> 0.17251788 | BO82: =+AVERAGE(AU82,AZ82,BE82,BJ82) -> 0.27452962 | BP82: =+AVERAGE(AV82,BA82,BF82,BK82) -> 0.27744409 | BQ82: =BR82-SUM(BN82:BP82) -> 0.27550841 | BR82: 1
A83: Specialty Contractors | F83: =F8/J8 -> #DIV/0! | G83: =G8/J8 -> #DIV/0! | H83: =H8/J8 -> #DIV/0! | I83: =I8/J8 -> #DIV/0! | K83: =K8/O8 -> 0 | L83: =L8/O8 -> 0 | M83: =M8/O8 -> 0.41857489 | N83: =N8/O8 -> 0.58142511 | P83: =P8/T8 -> 0.22622047 | Q83: =Q8/T8 -> 0.23312024 | R83: =R8/T8 -> 0.26638378 | S83: =S8/T8 -> 0.27427551 | U83: =U8/Y8 -> 0.25521286 | V83: =V8/Y8 -> 0.24012972 | W83: =W8/Y8 -> 0.2431707 | X83: =X8/Y8 -> 0.26148672 | Z83: =Z8/AD8 -> 0.22449759 | AA83: =AA8/AD8 -> 0.24740803 | AB83: =X8/AD8 -> 0.23767874 | AC83: =AC8/AD8 -> 0.25457994 | AD83: 1 | AE83: =AE8/AI8 -> 0.23860756 | AF83: =AF8/$AI8 -> 0.26611587 | AG83: =AG8/$AI8 -> 0.26494895 | AH83: =AH8/AI8 -> 0.23032762 | AI83: 1 | AJ83: =AJ8/AN8 -> 0.22829103 | AK83: =AK8/AN8 -> 0.25837276 | AL83: =AL8/$AN8 -> 0.26867114 | AM83: =AM8/$AN8 -> 0.24466507 | AN83: 1 | AO83: =AO8/$AS8 -> 0.26010869 | AP83: =AP8/$AS8 -> 0.23222802 | AQ83: =AQ8/$AS8 -> 0.25552851 | AR83: =AR8/$AS8 -> 0.25213478 | AS83: 1 | AT83: 0.15 | AU83: =+AVERAGE(AA83,AF83,AK83,AP83) -> 0.25103117 | AV83: =+AVERAGE(X83,AG83,AL83,AQ83) -> 0.26265883 | AW83: =AX83-SUM(AT83:AV83) -> 0.33631 | AX83: 1 | AY83: =+AVERAGE(AE83,AJ83,AO83,AT83) -> 0.21925182 | AZ83: =+AVERAGE(AF83,AK83,AP83,AU83) -> 0.25193695 | BA83: =+AVERAGE(AG83,AL83,AQ83,AV83) -> 0.26295186 | BB83: =BC83-SUM(AY83:BA83) -> 0.26585937 | BC83: 1 | BD83: =+AVERAGE(AJ83,AO83,AT83,AY83) -> 0.21441289 | BE83: =+AVERAGE(AK83,AP83,AU83,AZ83) -> 0.24839222 | BF83: =+AVERAGE(AL83,AQ83,AV83,BA83) -> 0.26245259 | BG83: =BH83-SUM(BD83:BF83) -> 0.2747423 | BH83: 1 | BI83: =+AVERAGE(AO83,AT83,AY83,BD83) -> 0.21094335 | BJ83: =+AVERAGE(AP83,AU83,AZ83,BE83) -> 0.24589709 | BK83: =+AVERAGE(AQ83,AV83,BA83,BF83) -> 0.26089795 | BL83: =BM83-SUM(BI83:BK83) -> 0.28226161 | BM83: 1 | BN83: =+AVERAGE(AT83,AY83,BD83,BI83) -> 0.19865201 | BO83: =+AVERAGE(AU83,AZ83,BE83,BJ83) -> 0.24931436 | BP83: =+AVERAGE(AV83,BA83,BF83,BK83) -> 0.26224031 | BQ83: =BR83-SUM(BN83:BP83) -> 0.28979332 | BR83: 1

Sheet BS
A1: Tutor Perini | AC1: =CF!AC17 -> -8.35 | AD1: =CF!AD17 -> 51.71 | AE1: =CF!AE17 -> -33.254 | AF1: =CF!AF17 -> -22.642 | AG1: =CF!AG17 -> 23.165 | AH1: =CF!AH17 -> 1.746 | AI1: =CF!AI17 -> -30.985 | AJ1: =CF!AJ17 -> -2.729 | ... AS1: =CF!AS17 -> 125.757 | AT1: =CF!BD17 -> 9.8456573 | AU1: =CF!BE17 -> 23.446052 | AV1: =CF!BF17 -> 21.108651 | AW1: =CF!BG17 -> 13.181523 | AX1: =CF!BH17 -> 67.581884 | AY1: =CF!BI17 -> -1.7949194 | AZ1: =CF!BJ17 -> 0.60965244 | BA1: =CF!BK17 -> -0.70543694 | ... BC1: =CF!BM17 -> 0
A2: Balance Sheet | F2: 40268 | G2: =+EOMONTH(F2,3) -> 40359 | H2: =+EOMONTH(G2,3) -> 40451 | I2: =+EOMONTH(H2,3) -> 40543 | K2: =+EOMONTH(F2,12) -> 40633 | L2: =+EOMONTH(G2,12) -> 40724 | M2: =+EOMONTH(H2,12) -> 40816 | N2: =+EOMONTH(I2,12) -> 40908 | P2: =EOMONTH(K2,12) -> 40999 | Q2: =EOMONTH(L2,12) -> 41090 | R2: =EOMONTH(M2,12) -> 41182 | S2: =EOMONTH(N2,12) -> 41274 | U2: =EOMONTH(P2,12) -> 41364 | V2: =EOMONTH(Q2,12) -> 41455 | W2: =EOMONTH(R2,12) -> 41547 | X2: =EOMONTH(S2,12) -> 41639 | Z2: =EOMONTH(U2,12) -> 41729 | AA2: =EOMONTH(V2,12) -> 41820 | AB2: =EOMONTH(W2,12) -> 41912 | AC2: =EOMONTH(X2,12) -> 42004 | AE2: =EOMONTH(Z2,12) -> 42094 | AF2: =EOMONTH(AA2,12) -> 42185 | AG2: =EOMONTH(AB2,12) -> 42277 | AH2: =EOMONTH(AC2,12) -> 42369 | AJ2: =EOMONTH(AE2,12) -> 42460 | AK2: =EOMONTH(AF2,12) -> 42551 | AL2: =EOMONTH(AG2,12) -> 42643 | AM2: =EOMONTH(AH2,12) -> 42735 | AO2: =EOMONTH(AJ2,12) -> 42825 | AP2: =EOMONTH(AK2,12) -> 42916 | AQ2: =EOMONTH(AL2,12) -> 43008 | AR2: =EOMONTH(AM2,12) -> 43100 | AT2: =EOMONTH(AO2,12) -> 43190 | AU2: =EOMONTH(AP2,12) -> 43281 | AV2: =EOMONTH(AQ2,12) -> 43373 | AW2: =EOMONTH(AR2,12) -> 43465 | AY2: =EOMONTH(AT2,12) -> 43555 | AZ2: =EOMONTH(AU2,12) -> 43646 | BA2: =EOMONTH(AV2,12) -> 43738 | BB2: =EOMONTH(AW2,12) -> 43830 | BD2: =EOMONTH(AY2,12) -> 43921 | BE2: =EOMONTH(AZ2,12) -> 44012 | BF2: =EOMONTH(BA2,12) -> 44104 | BG2: =EOMONTH(BB2,12) -> 44196 | BI2: =EOMONTH(BD2,12) -> 44286 | BJ2: =EOMONTH(BE2,12) -> 44377 | BK2: =EOMONTH(BF2,12) -> 44469 | BL2: =EOMONTH(BG2,12) -> 44561 | BN2: =EOMONTH(BI2,12) -> 44651 | BO2: =EOMONTH(BJ2,12) -> 44742 | BP2: =EOMONTH(BK2,12) -> 44834 | BQ2: =EOMONTH(BL2,12) -> 44926
A3: TPC | F3: 2010 | J3: =+F3 -> 2010 | K3: 2011 | O3: =+K3 -> 2011 | P3: 2012 | T3: =+P3 -> 2012 | U3: 2013 | Y3: =+U3 -> 2013 | Z3: 2014 | AD3: =+Z3 -> 2014 | AE3: 2015 | AI3: =+AE3 -> 2015 | AJ3: 2016 | AN3: =+AJ3 -> 2016 | AO3: 2017 | AS3: =+AO3 -> 2017 | AT3: 2018 | AX3: =+AT3 -> 2018 | AY3: 2019E | BC3: =+AY3 -> 2019E | BD3: 2020E | BH3: =+BD3 -> 2020E | BI3: 2021E | BM3: =+BI3 -> 2021E | BN3: 2022E | BR3: =+BN3 -> 2022E
A4: Fiscal YE December | F4: 1Q | G4: 2Q | H4: 3Q | I4: 4Q | J4: Year | K4: 1Q | L4: 2Q | M4: 3Q | N4: 4Q | O4: Year | P4: 1Q | Q4: 2Q | R4: 3Q | S4: 4Q | T4: Year | U4: 1Q | V4: 2QE | W4: 3QE | X4: 4QE | Y4: Year | Z4: 1Q | AA4: 2Q | AB4: 3Q | AC4: 4Q | AD4: Year | AE4: 1Q | AF4: 2Q | AG4: 3Q | AH4: 4Q | AI4: Year | AJ4: 1Q | AK4: 2Q | AL4: 3Q | AM4: 4Q | AN4: Year | AO4: 1Q | AP4: 2Q | AQ4: 3Q | AR4: 4Q | AS4: Year | AT4: 1Q | AU4: 2Q | AV4: 3Q | AW4: 4Q | AX4: Year | AY4: 1Q | AZ4: 2Q | BA4: 3Q | BB4: 4QE | BC4: Year | BD4: 1QE | BE4: 2QE | BF4: 3QE | BG4: 4QE | BH4: Year | BI4: 1QE | BJ4: 2QE | BK4: 3QE | BL4: 4QE | BM4: Year | BN4: 1QE | BO4: 2QE | BP4: 3QE | BQ4: 4QE | BR4: Year
A5: ASSETS
A6: Current assets
B7: Cash and cash equivalents | F7: 256.927 | G7: 303.212 | H7: 213.077 | I7: =J7 -> 471.378 | J7: 471.378 | K7: 367.106 | L7: 420.978 | M7: 273.321 | N7: =O7 -> 204.24 | O7: 204.24 | P7: 190.414 | Q7: 185.386 | R7: 180.777 | S7: =T7 -> 168.056 | T7: 168.056 | U7: 132.318 | V7: 142.678 | W7: 127.902 | X7: =Y7 -> 119.923 | Y7: 119.923 | Z7: 133.064 | AA7: 139.858 | AB7: 137.228 | AC7: 135.583 | AD7: =AC7 -> 135.583 | AE7: 145.958 | AF7: 106.917 | AG7: 96.894 | AH7: 75.452 | AI7: =AH7 -> 75.452 | AJ7: 90.582 | AK7: 93.622 | AL7: 170.744 | AM7: 146.103 | AN7: =AM7 -> 146.103 | AO7: 104.817 | AP7: 172.927 | AQ7: 221.878 | AR7: 192.868 | AS7: =AR7 -> 192.868 | AT7: 174.34 | AU7: 138.569 | AV7: 118.258 | AW7: 116.075 | AX7: =AW7 -> 116.075 | AY7: 101.482 | AZ7: 149.881 | BA7: 207.13 | BB7: =CF!BB41 -> 362.24289 | BC7: =BB7 -> 362.24289 | BD7: =CF!BD41 -> 426.76477 | BE7: =CF!BE41 -> 527.27732 | BF7: =CF!BF41 -> 617.77956 | BG7: =CF!BG41 -> 683.3337 | BH7: =BG7 -> 683.3337 | BI7: =CF!BI41 -> 711.88308 | BJ7: =CF!BJ41 -> 741.59167 | BK7: =CF!BK41 -> 767.09412 | BL7: =CF!BL41 -> 801.43883 | BM7: =BL7 -> 801.43883 | BN7: =CF!BN41 -> 826.74709 | BO7: =CF!BO41 -> 852.74543 | BP7: =CF!BP41 -> 884.00147 | BQ7: =CF!BQ41 -> 919.54395 | BR7: =BQ7 -> 919.54395
B8: Restricted Cash | F8: 23.523 | G8: 23.523 | H8: 23.541 | I8: =J8 -> 23.55 | J8: 23.55 | K8: 28.008 | L8: 32.443 | M8: 35.817 | N8: =O8 -> 35.437 | O8: 35.437 | P8: 35.45 | Q8: 38.684 | R8: 38.7 | S8: =T8 -> 38.717 | T8: 38.717 | U8: 45.231 | V8: 47.019 | W8: 47.466 | X8: =Y8 -> 42.594 | Y8: 42.594 | Z8: 43.269 | AA8: 42.627 | AB8: 46.988 | AC8: 44.37 | AD8: =AC8 -> 44.37 | AE8: 44.093 | AF8: 39.493 | AG8: 38.572 | AH8: 45.853 | AI8: =AH8 -> 45.853 | AJ8: 49.158 | AK8: 49.452 | AL8: 48.725 | AM8: 50.504 | AN8: =AM8 -> 50.504 | AO8: 60.158 | AP8: 52.051 | AQ8: =17.424+48.775 -> 66.199 | AR8: =4.78+53.014 -> 57.794 | AS8: =AR8 -> 57.794 | AT8: 57.251 | AU8: 56.334 | AV8: 56.552 | AW8: 61.93 | AX8: =AW8 -> 61.93 | AY8: 69.032 | AZ8: =4.742+65.287 -> 70.029 | BA8: =6.261+67.728 -> 73.989 | BB8: =BA8 -> 73.989 | BC8: =BB8 -> 73.989 | BD8: =BB8 -> 73.989 | BE8: =BD8 -> 73.989 | BF8: =BE8 -> 73.989 | BG8: =BF8 -> 73.989 | BH8: =BG8 -> 73.989 | BI8: =BG8 -> 73.989 | BJ8: =BI8 -> 73.989 | BK8: =BJ8 -> 73.989 | BL8: =BK8 -> 73.989 | BM8: =BL8 -> 73.989 | BN8: =BL8 -> 73.989 | BO8: =BN8 -> 73.989 | BP8: =BO8 -> 73.989 | BQ8: =BP8 -> 73.989 | BR8: =BQ8 -> 73.989
B9: Accounts Receivable, including retainage | F9: 1115.997 | G9: 1193.315 | H9: 1121.657 | I9: =J9 -> 880.614 | J9: 880.614 | K9: 911.172 | L9: 1021.27 | M9: 1312.36 | N9: =O9 -> 1275.031 | O9: 1275.031 | P9: 1184.213 | Q9: 1198.764 | R9: 1249.787 | S9: =T9 -> 1224.613 | T9: 1224.613 | U9: 1331.555 | V9: 1389.511 | W9: 1397.857 | X9: =Y9 -> 1291.246 | Y9: 1291.246 | Z9: 1263.39 | AA9: 1454.045 | AB9: 1580.594 | AC9: 1479.504 | AD9: =AC9 -> 1479.504 | AE9: 1394.12 | AF9: 1553.514 | AG9: 1550.865 | AH9: 1473.615 | AI9: =AH9 -> 1473.615 | AJ9: 1615.661 | AK9: 1739.343 | AL9: 1718.685 | AM9: 1743.3 | AN9: =AM9 -> 1743.3 | AO9: 1749.602 | AP9: 1838.359 | AQ9: 1857.87 | AR9: 1801.656 | AS9: =AR9 -> 1801.656 | AT9: 1767.715 | AU9: 1763.683 | AV9: 1818.402 | AW9: =1261.072+478.744 -> 1739.816 | AX9: =AW9 -> 1739.816 | AY9: 1838.013 | AZ9: =1469.213+508.423 -> 1977.636 | BA9: =1460.45+542.274 -> 2002.724 | BB9: =BB60*BB$50 -> 2082.7703 | BC9: =BB9 -> 2082.7703 | BD9: =BD60*BD$50 -> 2154.0312 | BE9: =BE60*BE$50 -> 2326.656 | BF9: =BF60*BF$50 -> 2481.4606 | BG9: =BG60*BG$50 -> 2576.8689 | BH9: =BG9 -> 2576.8689 | BI9: =BI60*BI$50 -> 2560.6315 | BJ9: =BJ60*BJ$50 -> 2562.2943 | BK9: =BK60*BK$50 -> 2554.1844 | BL9: =BL60*BL$50 -> 2565.3368 | BM9: =BL9 -> 2565.3368 | BN9: =BN60*BN$50 -> 2542.2388 | BO9: =BO60*BO$50 -> 2534.9964 | BP9: =BP60*BP$50 -> 2540.4567 | BQ9: =BQ60*BQ$50 -> 2553.8048 | BR9: =BQ9 -> 2553.8048
B10: Costs and Estimated Earnings in Excess of Billings | F10: 134.825 | G10: 120.28 | H10: 123.497 | I10: =J10 -> 139.449 | J10: 139.449 | K10: 172.54 | L10: 215.117 | M10: 374.325 | N10: =O10 -> 358.398 | O10: 358.398 | P10: 377.599 | Q10: 374.936 | R10: 411.662 | S10: =T10 -> 465.002 | T10: 465.002 | U10: 479.361 | V10: 504.911 | W10: 538.421 | X10: =Y10 -> 573.248 | Y10: 573.248 | Z10: 698.423 | AA10: 660.952 | AB10: 720.177 | AC10: 726.402 | AD10: =AC10 -> 726.402 | AE10: 795.51 | AF10: 816.48 | AG10: 883.809 | AH10: 905.175 | AI10: =AH10 -> 905.175 | AJ10: 858.356 | AK10: 811.406 | AL10: 820.243 | AM10: 831.826 | AN10: =AM10 -> 831.826 | AO10: 840.76 | AP10: 850.634 | AQ10: 902.312 | AR10: 932.758 | AS10: =AR10 -> 932.758 | AT10: 980.896 | AU10: 1044.233 | AV10: 1085.651 | AW10: 1142.295 | AX10: =AW10 -> 1142.295 | AY10: 1168.675 | AZ10: 1165.408 | BA10: 1159.333 | BB10: =BB61*BB$50 -> 556.76031 | BC10: =BB10 -> 556.76031 | BD10: =BD61*BD$50 -> 576.45163 | BE10: =BE61*BE$50 -> 623.34373 | BF10: =BF61*BF$50 -> 665.56103 | BG10: =BG61*BG$50 -> 691.92408 | BH10: =BG10 -> 691.92408 | BI10: =BI61*BI$50 -> 688.33424 | BJ10: =BJ61*BJ$50 -> 689.55355 | BK10: =BK61*BK$50 -> 688.14267 | BL10: =BL61*BL$50 -> 691.92408 | BM10: =BL10 -> 691.92408 | BN10: =BN61*BN$50 -> 686.46554 | BO10: =BO61*BO$50 -> 685.28093 | BP10: =BP61*BP$50 -> 687.53141 | BQ10: =BQ61*BQ$50 -> 691.92408 | BR10: =BQ10 -> 691.92408
B11: Deferred Income taxes | F11: 1.393 | G11: 1.369 | H11: 1.41 | I11: =J11 -> 3.737 | J11: 3.737 | K11: 3.782 | L11: 11.44 | M11: 18.559 | N11: =O11 -> 0 | O11: 0 | P11: 1.958 | Q11: 2.931 | R11: 3.246 | S11: =T11 -> 10.071 | T11: 10.071 | U11: 9.721 | V11: 9.452 | W11: 9.631 | X11: =Y11 -> 8.24 | Y11: 8.24 | Z11: 8.195 | AA11: 7.982 | AB11: 7.951 | AC11: 17.962 | AD11: =AC11 -> 17.962 | AE11: 17.962 | AF11: 17.952 | AG11: 18.873 | AH11: 26.306 | AI11: =AH11 -> 26.306 | AJ11: 26.55 | AK11: 19.098 | AL11: 26.029 | AM11: 0 | AN11: =AM11 -> 0 | AO11: 0 | AP11: 0 | AQ11: 0 | AS11: =AR11 -> 0
B12: Other Current Assets | F12: 33.527 | G12: 37.345 | H12: 44.867 | I12: =J12 -> 42.314 | J12: 42.314 | K12: 35.372 | L12: 52.86 | M12: 93.767 | N12: =O12 -> 76.928 | O12: 76.928 | P12: 87.862 | Q12: 101.684 | R12: 76.021 | S12: =T12 -> 75.388 | T12: 75.388 | U12: 74.5 | V12: 53.814 | W12: 48.36 | X12: =Y12 -> 50.669 | Y12: 50.669 | Z12: 54.858 | AA12: 52.42 | AB12: 69.318 | AC12: 68.735 | AD12: =AC12 -> 68.735 | AE12: 74.367 | AF12: 103.243 | AG12: 86.734 | AH12: 108.844 | AI12: =AH12 -> 108.844 | AJ12: 91.99 | AK12: 76.96 | AL12: 65.511 | AM12: 66.023 | AN12: =AM12 -> 66.023 | AO12: 58.482 | AP12: 77.736 | AQ12: 70.781 | AR12: 89.316 | AS12: =AR12 -> 89.316 | AT12: 132.298 | AU12: 141.472 | AV12: 130.023 | AW12: 115.527 | AX12: =AW12 -> 115.527 | AY12: 124.303 | AZ12: 165.688 | BA12: 162.406 | BB12: =BB63*BB$50 -> 73.264895 | BC12: =BB12 -> 73.264895 | BD12: =BD63*BD$50 -> 75.856103 | BE12: =BE63*BE$50 -> 82.026703 | BF12: =BF63*BF$50 -> 87.582139 | BG12: =BG63*BG$50 -> 91.051291 | BH12: =BG12 -> 91.051291 | BI12: =BI63*BI$50 -> 90.578899 | BJ12: =BJ63*BJ$50 -> 90.739349 | BK12: =BK63*BK$50 -> 90.55369 | BL12: =BL63*BL$50 -> 91.051291 | BM12: =BL12 -> 91.051291 | BN12: =BN63*BN$50 -> 90.332993 | BO12: =BO63*BO$50 -> 90.177109 | BP12: =BP63*BP$50 -> 90.473253 | BQ12: =BQ63*BQ$50 -> 91.051291 | BR12: =BQ12 -> 91.051291
D13: Total Current Assets | F13: =SUM(F7:F12) -> 1566.192 | G13: =SUM(G7:G12) -> 1679.044 | H13: =SUM(H7:H12) -> 1528.049 | I13: =SUM(I7:I12) -> 1561.042 | J13: =SUM(J7:J12) -> 1561.042 | K13: =SUM(K7:K12) -> 1517.98 | L13: =SUM(L7:L12) -> 1754.108 | M13: =SUM(M7:M12) -> 2108.149 | ... BR13: =SUM(BR7:BR12) -> 4330.3131
A14: Long-term assets
B15: Long-term Investments | F15: 100.826 | G15: 100.316 | H15: 94.023 | I15: =J15 -> 88.129 | J15: 88.129 | K15: 88.129 | L15: 88.129 | M15: 67.061 | N15: =O15 -> 62.311 | O15: 62.311 | P15: 46.283 | Q15: 46.283 | R15: 46.283 | S15: =T15 -> 46.283 | T15: 46.283 | U15: 46.283 | V15: 46.283 | W15: 46.283 | X15: =Y15 -> 46.283 | Y15: 46.283 | Z15: 46.283 | AA15: 0 | AB15: 0 | AC15: 0 | AD15: =AC15 -> 0 | AE15: 0 | AF15: 0 | AG15: 0 | AH15: 0 | AI15: =AH15 -> 0
C16: Accumulated depreciation | I16: =J16 -> 0 | N16: =O16 -> 0 | S16: =T16 -> 0 | X16: =Y16 -> 0 | AD16: =AC16 -> 0 | AI16: =AH16 -> 0 | AN16: =AM16 -> 0 | AS16: =AR16 -> 0 | AX16: =AW16 -> 0 | BC16: =BB16 -> 0 | BH16: =BG16 -> 0 | BM16: =BL16 -> 0 | BR16: =BQ16 -> 0
C17: Property, plant and equipment, gross | I17: =J17 -> 0 | N17: =O17 -> 0 | S17: =T17 -> 0 | X17: =Y17 -> 0 | AD17: =AC17 -> 0 | AI17: =AH17 -> 0 | AN17: =AM17 -> 0 | AS17: =AR17 -> 0 | AX17: =AW17 -> 0 | BC17: =BB17 -> 0 | BH17: =BG17 -> 0 | BM17: =BL17 -> 0 | BR17: =BQ17 -> 0
B18: Property, Plant and Equipment (less Accumulated Depreciation) | F18: 351.398 | G18: 353.506 | H18: 354.995 | I18: =J18 -> 362.437 | J18: 362.437 | K18: 373.45 | L18: 424.869 | M18: 472.528 | N18: =O18 -> 491.377 | O18: 491.377 | P18: 490.011 | Q18: 488.491 | R18: 488.114 | S18: =T18 -> 485.095 | T18: 485.095 | U18: 487.385 | V18: 491.457 | W18: 493.326 | X18: =Y18 -> 498.125 | Y18: 498.125 | Z18: 516.683 | AA18: 529.545 | AB18: 526.981 | AC18: 527.602 | AD18: =AC18 -> 527.602 | AE18: 523.622 | AF18: 537.833 | AG18: 531.438 | AH18: 523.525 | AI18: =AH18 -> 523.525 | AJ18: 519.89 | AK18: 507.395 | AL18: 492.328 | AM18: 477.626 | AN18: =AM18 -> 477.626 | AO18: 462.695 | AP18: 456.001 | AQ18: 447.588 | AR18: 467.499 | AS18: =AR18 -> 467.499 | AT18: 473.178 | AU18: 490.614 | AV18: 494.498 | AW18: 490.669 | AX18: =AW18 -> 490.669 | AY18: 492.929 | AZ18: 502.675 | BA18: 509.986 | BB18: =BA18-CF!BL22-CF!BL8 -> 499.986 | BC18: =BB18 -> 499.986 | BD18: =BC18-CF!BN22-CF!BN8 -> 489.986 | BE18: =BD18-CF!BO22-CF!BO8 -> 479.986 | BF18: =BE18-CF!BP22-CF!BP8 -> 469.986 | BG18: =BF18-CF!BQ22-CF!BQ8 -> 459.986 | BH18: =BG18 -> 459.986 | BI18: =BH18-CF!BS22-CF!BS8 -> 459.986 | BJ18: =BI18-CF!BT22-CF!BT8 -> 459.986 | BK18: =BJ18-CF!BU22-CF!BU8 -> 459.986 | BL18: =BK18-CF!BV22-CF!BV8 -> 459.986 | BM18: =BL18 -> 459.986 | BN18: =BM18-CF!BX22-CF!BX8 -> 459.986 | BO18: =BN18-CF!BY22-CF!BY8 -> 459.986 | BP18: =BO18-CF!BZ22-CF!BZ8 -> 459.986 | BQ18: =BP18-CF!CA22-CF!CA8 -> 459.986 | BR18: =BQ18 -> 459.986
B19: Goodwill | F19: 602.471 | G19: 602.471 | H19: 602.471 | I19: =J19 -> 621.92 | J19: 621.92 | K19: 651.429 | L19: 691.077 | M19: 881.538 | N19: =O19 -> 892.602 | O19: 892.602 | P19: 893.79 | Q19: 570.646 | R19: 570.646 | S19: =T19 -> 570.646 | T19: 570.646 | U19: 570.646 | V19: 570.646 | W19: 571.932 | X19: =Y19 -> 577.756 | Y19: 577.756 | Z19: 577.756 | AA19: 585.006 | AB19: 585.006 | AC19: 585.006 | AD19: =AC19 -> 585.006 | AE19: 585.006 | AF19: 585.006 | AG19: 585.006 | AH19: 585.006 | AI19: =AH19 -> 585.006 | AJ19: 585.006 | AK19: 585.006 | AL19: 585.006 | AM19: 585.006 | AN19: =AM19 -> 585.006 | AO19: 585.006 | AP19: 585.006 | AQ19: 585.006 | AR19: 585.006 | AS19: =AR19 -> 585.006 | AT19: 585.006 | AU19: 585.006 | AV19: 585.006 | AW19: 585.006 | AX19: =AW19 -> 585.006 | AY19: 585.006 | AZ19: 205.143 | BA19: 205.143 | BB19: =BA19 -> 205.143 | BC19: =BB19 -> 205.143 | BD19: =BB19 -> 205.143 | BE19: =BD19 -> 205.143 | BF19: =BE19 -> 205.143 | BG19: =BF19 -> 205.143 | BH19: =BG19 -> 205.143 | BI19: =BG19 -> 205.143 | BJ19: =BI19 -> 205.143 | BK19: =BJ19 -> 205.143 | BL19: =BK19 -> 205.143 | BM19: =BL19 -> 205.143 | BN19: =BL19 -> 205.143 | BO19: =BN19 -> 205.143 | BP19: =BO19 -> 205.143 | BQ19: =BP19 -> 205.143 | BR19: =BQ19 -> 205.143
B20: Intangible Assets, net | F20: 132.089 | G20: 130.051 | H20: 128.105 | I20: =J20 -> 132.551 | J20: 132.551 | K20: 151.081 | L20: 160.206 | M20: 203.075 | N20: =O20 -> 197.999 | O20: 197.999 | P20: 192.96 | Q20: 133.715 | R20: 130.092 | S20: =T20 -> 126.821 | T20: 126.821 | U20: 123.551 | V20: 120.281 | W20: 117.01 | X20: =Y20 -> 113.74 | Y20: 113.74 | Z20: 110.071 | AA20: 106.403 | AB20: 103.329 | AC20: 100.254 | AD20: =AC20 -> 100.254 | AE20: 99.311 | AF20: 98.368 | AG20: 97.425 | AH20: 96.54 | AI20: =AH20 -> 96.54 | AJ20: 95.654 | AK20: 94.768 | AL20: 93.883 | AM20: 92.997 | AN20: =AM20 -> 92.997 | AO20: 92.111 | AP20: 91.226 | AQ20: 90.34 | AR20: 89.454 | AS20: =AR20 -> 89.454 | AT20: 88.568 | AU20: 87.683 | AV20: 86.797 | AW20: 85.911 | AX20: =AW20 -> 85.911 | AY20: 85.026 | AZ20: 84.14 | BA20: 83.254 | BB20: =BA20 -> 83.254 | BC20: =BB20 -> 83.254 | BD20: =BB20 -> 83.254 | BE20: =BD20 -> 83.254 | BF20: =BE20 -> 83.254 | BG20: =BF20 -> 83.254 | BH20: =BG20 -> 83.254 | BI20: =BG20 -> 83.254 | BJ20: =BI20 -> 83.254 | BK20: =BJ20 -> 83.254 | BL20: =BK20 -> 83.254 | BM20: =BL20 -> 83.254 | BN20: =BL20 -> 83.254 | BO20: =BN20 -> 83.254 | BP20: =BO20 -> 83.254 | BQ20: =BP20 -> 83.254 | BR20: =BQ20 -> 83.254
B21: Other assets | F21: 20.209 | G21: 17.303 | H21: 18.306 | I21: =J21 -> 13.141 | J21: 13.141 | K21: 15.644 | L21: 20.968 | M21: 21.386 | N21: =O21 -> 18.804 | O21: 18.804 | P21: 18.04 | Q21: 35.052 | R21: 40.13 | S21: =T21 -> 85.718 | T21: 85.718 | U21: 86.887 | V21: 81.432 | W21: 80.759 | X21: =Y21 -> 75.614 | Y21: 75.614 | Z21: 73.357 | AA21: 75.685 | AB21: 57.948 | AC21: 87.897 | AD21: =AC21 -> 87.897 | AE21: 86.531 | AF21: 84.83 | AG21: 80.639 | AH21: 202.125 | AI21: =AH21 -> 202.125 | AJ21: 198.635 | AK21: 218.535 | AL21: 199.812 | AM21: 45.235 | AN21: =AM21 -> 45.235 | AO21: 44.852 | AP21: 40.926 | AQ21: 40.811 | AR21: 47.772 | AS21: =AR21 -> 47.772 | AT21: 48.877 | AU21: 50.171 | AV21: 49.981 | AW21: 50.523 | AX21: =AW21 -> 50.523 | AY21: 91.804 | AZ21: 92.896 | BA21: 90.943 | BB21: =+BA21 -> 90.943 | BC21: =BB21 -> 90.943 | BD21: =+BB21 -> 90.943 | BE21: =+BD21 -> 90.943 | BF21: =+BE21 -> 90.943 | BG21: =+BF21 -> 90.943 | BH21: =BG21 -> 90.943 | BI21: =+BG21 -> 90.943 | BJ21: =+BI21 -> 90.943 | BK21: =+BJ21 -> 90.943 | BL21: =+BK21 -> 90.943 | BM21: =BL21 -> 90.943 | BN21: =+BL21 -> 90.943 | BO21: =+BN21 -> 90.943 | BP21: =+BO21 -> 90.943 | BQ21: =+BP21 -> 90.943 | BR21: =BQ21 -> 90.943
A22: Total assets | F22: =SUM(F15:F21)+F13 -> 2773.185 | G22: =SUM(G15:G21)+G13 -> 2882.691 | H22: =SUM(H15:H21)+H13 -> 2725.949 | I22: =SUM(I15:I21)+I13 -> 2779.22 | J22: =SUM(J15:J21)+J13 -> 2779.22 | K22: =SUM(K15:K21)+K13 -> 2797.713 | L22: =SUM(L15:L21)+L13 -> 3139.357 | M22: =SUM(M15:M21)+M13 -> 3753.737 | ... BR22: =SUM(BR15:BR21)+BR13 -> 5169.6391
A24: LIABILITIES
A25: Current liabilities
B26: Current maturities of long-term debt | F26: 29.879 | G26: 31.014 | H26: 21.855 | I26: =J26 -> 21.334 | J26: 21.334 | K26: 14.217 | L26: 32.413 | M26: 73.836 | N26: =O26 -> 59.959 | O26: 59.959 | P26: 60.916 | Q26: 65.039 | R26: 63.832 | S26: =T26 -> 67.71 | T26: 67.71 | U26: 67.33 | V26: 108.134 | W26: 107.821 | X26: =Y26 -> 114.658 | Y26: 114.658 | Z26: 122.947 | AA26: 68.232 | AB26: 65.407 | AC26: 81.292 | AD26: =AC26 -> 81.292 | AE26: 87.6 | AF26: 86.101 | AG26: 85.897 | AH26: 88.917 | AI26: =AH26 -> 88.917 | AJ26: 99.97 | AK26: 120.256 | AL26: 108.897 | AM26: 85.89 | AN26: =AM26 -> 85.89 | AO26: 27.598 | AP26: 30.333 | AQ26: 30.951 | AR26: 30.748 | AS26: =AR26 -> 30.748 | AT26: 27.165 | AU26: 28.105 | AV26: 20.601 | AW26: 16.767 | AX26: =AW26 -> 16.767 | AY26: 11.921 | AZ26: 14.414 | BA26: 10.862 | BB26: =BB75*BB$50 -> 69.131207 | BC26: =BB26 -> 69.131207 | BD26: =BD75*BD$50 -> 71.576216 | BE26: =BE75*BE$50 -> 77.398664 | BF26: =BF75*BF$50 -> 82.640656 | BG26: =BG75*BG$50 -> 85.914074 | BH26: =BG26 -> 85.914074 | BI26: =BI75*BI$50 -> 85.468335 | BJ26: =BJ75*BJ$50 -> 85.619732 | BK26: =BK75*BK$50 -> 85.444548 | BL26: =BL75*BL$50 -> 85.914074 | BM26: =BL26 -> 85.914074 | BN26: =BN75*BN$50 -> 85.236303 | BO26: =BO75*BO$50 -> 85.089214 | BP26: =BP75*BP$50 -> 85.368649 | BQ26: =BQ75*BQ$50 -> 85.914074 | BR26: =BQ26 -> 85.914074
B27: Accounts payable, including retainage | F27: 911.184 | G27: 950.492 | H27: 829.809 | I27: =J27 -> 653.542 | J27: 653.542 | K27: 597.659 | L27: 630.178 | M27: 766.771 | N27: =O27 -> 785.725 | O27: 785.725 | P27: 684.327 | Q27: 692.94 | R27: 750.697 | S27: =T27 -> 696.473 | T27: 696.473 | U27: 705.916 | V27: 760.512 | W27: 797.129 | X27: =Y27 -> 758.225 | Y27: 758.225 | Z27: 791.638 | AA27: 849.628 | AB27: 863.643 | AC27: 798.174 | AD27: =AC27 -> 798.174 | AE27: 802.191 | AF27: 963.23 | AG27: 985.217 | AH27: 937.464 | AI27: =AH27 -> 937.464 | AJ27: 1005.906 | AK27: 968.193 | AL27: 949.648 | AM27: 994.016 | AN27: =AM27 -> 994.016 | AO27: 965.931 | AP27: 899.284 | AQ27: 949.675 | AR27: 961.791 | AS27: =AR27 -> 961.791 | AT27: 905.323 | AU27: =625.436+236.545 -> 861.981 | AV27: 824.53 | AW27: =621.728+211.956 -> 833.684 | AX27: =AW27 -> 833.684 | AY27: =597.498+221.028 -> 818.526 | AZ27: =685.745+227.884 -> 913.629 | BA27: 902.667 | BB27: =BB76*BB$50 -> 788.74378 | BC27: =BB27 -> 788.74378 | BD27: =BD76*BD$50 -> 816.6398 | BE27: =BE76*BE$50 -> 883.07028 | BF27: =BF76*BF$50 -> 942.87813 | BG27: =BG76*BG$50 -> 980.22578 | BH27: =BG27 -> 980.22578 | BI27: =BI76*BI$50 -> 975.14017 | BJ27: =BJ76*BJ$50 -> 976.86752 | BK27: =BK76*BK$50 -> 974.86878 | BL27: =BL76*BL$50 -> 980.22578 | BM27: =BL27 -> 980.22578 | BN27: =BN76*BN$50 -> 972.49284 | BO27: =BO76*BO$50 -> 970.81465 | BP27: =BP76*BP$50 -> 974.00283 | BQ27: =BQ76*BQ$50 -> 980.22578 | BR27: =BQ27 -> 980.22578
B28: Billings in Excess of Costs and Estimated Earnings | F28: 209.323 | G28: 259.963 | H28: 225.072 | I28: =J28 -> 199.75 | J28: 199.75 | K28: 235.873 | L28: 295.013 | M28: 381.464 | N28: =O28 -> 384.282 | O28: 384.282 | P28: 376.391 | Q28: 362.679 | R28: 345.428 | S28: =T28 -> 301.761 | T28: 301.761 | U28: 295.265 | V28: 306.391 | W28: 282.261 | X28: =Y28 -> 267.586 | Y28: 267.586 | Z28: 264.118 | AA28: 299.389 | AB28: 327.646 | AC28: 319.296 | AD28: =AC28 -> 319.296 | AE28: 286.042 | AF28: 263.4 | AG28: 286.565 | AH28: 288.311 | AI28: =AH28 -> 288.311 | AJ28: 285.582 | AK28: 325.29 | AL28: 334.055 | AM28: 331.112 | AN28: =AM28 -> 331.112 | AO28: 288.795 | AP28: 339.808 | AQ28: 403.635 | AR28: 456.869 | AS28: =AR28 -> 456.869 | AT28: 508.616 | AU28: 574.392 | AV28: 648.287 | AW28: 573.19 | AX28: =AW28 -> 573.19 | AY28: 579 | AZ28: 635.924 | BA28: 818.806 | BB28: =BB77*BB$50 -> 278.38016 | BC28: =BB28 -> 278.38016 | BD28: =BD77*BD$50 -> 288.22581 | BE28: =BE77*BE$50 -> 311.67187 | BF28: =BF77*BF$50 -> 332.78052 | BG28: =BG77*BG$50 -> 345.96204 | BH28: =BG28 -> 345.96204 | BI28: =BI77*BI$50 -> 344.16712 | BJ28: =BJ77*BJ$50 -> 344.77677 | BK28: =BK77*BK$50 -> 344.07134 | BL28: =BL77*BL$50 -> 345.96204 | BM28: =BL28 -> 345.96204 | BN28: =BN77*BN$50 -> 343.23277 | BO28: =BO77*BO$50 -> 342.64046 | BP28: =BP77*BP$50 -> 343.7657 | BQ28: =BQ77*BQ$50 -> 345.96204 | BR28: =BQ28 -> 345.96204
B29: Accrued Expenses | F29: 91.832 | G29: 92.864 | H29: 100.097 | I29: =J29 -> 93.488 | J29: 93.488 | K29: 93.844 | L29: 97.111 | M29: 204.085 | N29: =O29 -> 163.268 | O29: 163.268 | P29: 159.612 | Q29: 190.092 | R29: 161.495 | S29: =T29 -> 168.326 | T29: 168.326 | U29: 176.249 | V29: 180.545 | W29: 161.649 | X29: =Y29 -> 158.017 | Y29: 158.017 | Z29: 148.986 | AA29: 136.774 | AB29: 145.336 | AC29: 159.814 | AD29: =AC29 -> 159.814 | AE29: 152.916 | AF29: 166.198 | AG29: 185.764 | AH29: 159.016 | AI29: =AH29 -> 159.016 | AJ29: 160.964 | AK29: 171.15 | AL29: 209.343 | AM29: 107.925 | AN29: =AM29 -> 107.925 | AO29: 112.448 | AP29: 176.148 | AQ29: 124.385 | AR29: 132.438 | AS29: =AR29 -> 132.438 | AT29: 118.334 | AU29: 134.264 | AV29: 162.102 | AW29: 174.325 | AX29: =AW29 -> 174.325 | AY29: 173.827 | AZ29: 175.525 | BA29: 188.373 | BB29: =BB78*BB$50 -> 153.61128 | BC29: =BB29 -> 153.61128 | BD29: =BD78*BD$50 -> 159.04415 | BE29: =BE78*BE$50 -> 171.98178 | BF29: =BF78*BF$50 -> 183.62962 | BG29: =BG78*BG$50 -> 190.90323 | BH29: =BG29 -> 190.90323 | BI29: =BI78*BI$50 -> 189.91279 | BJ29: =BJ78*BJ$50 -> 190.2492 | BK29: =BK78*BK$50 -> 189.85994 | BL29: =BL78*BL$50 -> 190.90323 | BM29: =BL29 -> 190.90323 | BN29: =BN78*BN$50 -> 189.39721 | BO29: =BO78*BO$50 -> 189.07038 | BP29: =BP78*BP$50 -> 189.69129 | BQ29: =BQ78*BQ$50 -> 190.90323 | BR29: =BQ29 -> 190.90323
D30: Total Current Liabilities | F30: =SUM(F26:F29) -> 1242.218 | G30: =SUM(G26:G29) -> 1334.333 | H30: =SUM(H26:H29) -> 1176.833 | I30: =SUM(I26:I29) -> 968.114 | J30: =SUM(J26:J29) -> 968.114 | K30: =SUM(K26:K29) -> 941.593 | L30: =SUM(L26:L29) -> 1054.715 | M30: =SUM(M26:M29) -> 1426.156 | ... BR30: =SUM(BR26:BR29) -> 1603.0051
A31: Long-term liabilities
B32: Long-term debt, less current maturities | F32: 87.733 | G32: 82.939 | H32: 79.396 | I32: =J32 -> 374.35 | J32: 374.35 | K32: 408.179 | L32: 605.969 | M32: 758.97 | N32: =O32 -> 612.548 | O32: 612.548 | P32: 617.095 | Q32: 625.297 | R32: 636.932 | S32: =T32 -> 669.38 | T32: 669.38 | U32: 737.083 | V32: 675.642 | W32: 669.71 | X32: =Y32 -> 619.226 | Y32: 619.226 | Z32: 697.823 | AA32: 761.034 | AB32: 880.121 | AC32: 784.067 | AD32: =AC32 -> 784.067 | AE32: 795.742 | AF32: 806.652 | AG32: 746.283 | AH32: 734.531 | AI32: =AH32 -> 734.531 | AJ32: 725.763 | AK32: 680.265 | AL32: 684.202 | AM32: 673.629 | AN32: =AM32 -> 673.629 | AO32: 753.191 | AP32: 832.327 | AQ32: 855.325 | AR32: 705.528 | AS32: =AR32 -> 705.528 | AT32: 790.119 | AU32: 794.509 | AV32: 780.723 | AW32: 744.737 | AX32: =AW32 -> 744.737 | AY32: 886.705 | AZ32: 941.763 | BA32: 825.382 | BB32: =BB81*BB$50 -> 836.12919 | BC32: =BB32 -> 836.12919 | BD32: =BD81*BD$50 -> 865.70113 | BE32: =BE81*BE$50 -> 910.1499 | BF32: =BF81*BF$50 -> 944.06007 | BG32: =BG81*BG$50 -> 952.62436 | BH32: =BG32 -> 952.62436 | BI32: =BI81*BI$50 -> 947.68196 | BJ32: =BJ81*BJ$50 -> 920.62927 | BK32: =BK81*BK$50 -> 890.07299 | BL32: =BL81*BL$50 -> 866.13385 | BM32: =BL32 -> 866.13385 | BN32: =BN81*BN$50 -> 859.30098 | BO32: =BO81*BO$50 -> 829.26474 | BP32: =BP81*BP$50 -> 803.34093 | BQ32: =BQ81*BQ$50 -> 779.64334 | BR32: =BQ32 -> 779.64334
B33: Deferred Income Taxes | F33: 77.645 | G33: 78.15 | H33: 77.923 | I33: =J33 -> 79.082 | J33: 79.082 | K33: 78.716 | L33: 83.598 | M33: 94.445 | N33: =O33 -> 97.921 | O33: 97.921 | P33: 105.683 | Q33: 58.981 | R33: 59.78 | S33: =T33 -> 109.9 | T33: 109.9 | U33: 109.988 | V33: 109.9 | W33: 109.922 | X33: =Y33 -> 114.333 | Y33: 114.333 | Z33: 114.186 | AA33: 115.536 | AB33: 115.325 | AC33: 150.371 | AD33: =AC33 -> 150.371 | AE33: 150.018 | AF33: 150.193 | AG33: 149.021 | AH33: 273.31 | AI33: =AH33 -> 273.31 | AJ33: 274.232 | AK33: 296.728 | AL33: 283.811 | AM33: 131.007 | AN33: =AM33 -> 131.007 | AO33: 130.616 | AP33: 131.292 | AQ33: 132.335 | AR33: 108.504 | AS33: =AR33 -> 108.504 | AT33: 106.763 | AU33: 106.284 | AV33: 106.636 | AW33: 105.521 | AX33: =AW33 -> 105.521 | AY33: 106.113 | AZ33: 56.248 | BA33: 58.305 | BB33: =+BA33 -> 58.305 | BC33: =BB33 -> 58.305 | BD33: =+BB33 -> 58.305 | BE33: =+BD33 -> 58.305 | BF33: =+BE33 -> 58.305 | BG33: =+BF33 -> 58.305 | BH33: =BG33 -> 58.305 | BI33: =+BG33 -> 58.305 | BJ33: =+BI33 -> 58.305 | BK33: =+BJ33 -> 58.305 | BL33: =+BK33 -> 58.305 | BM33: =BL33 -> 58.305 | BN33: =+BL33 -> 58.305 | BO33: =+BN33 -> 58.305 | BP33: =+BO33 -> 58.305 | BQ33: =+BP33 -> 58.305 | BR33: =BQ33 -> 58.305
B34: Other Long-term Liabilities | F34: 52.896 | G34: 50.789 | H34: 50.081 | I34: =J34 -> 44.68 | J34: 44.68 | K34: 45.625 | L34: 48.04 | M34: 92.971 | N34: =O34 -> 109.597 | O34: 109.597 | P34: 111.169 | Q34: 125.093 | R34: 116.557 | S34: =T34 -> 138.996 | T34: 138.996 | U34: 133.909 | V34: 135.505 | W34: 146.484 | X34: =Y34 -> 117.858 | Y34: 117.858 | Z34: 118.631 | AA34: 122.463 | AB34: 97.115 | AC34: 114.796 | AD34: =AC34 -> 114.796 | AE34: 113.507 | AF34: 113.284 | AG34: 114.902 | AH34: 140.665 | AI34: =AH34 -> 140.665 | AJ34: 138.734 | AK34: 140.87 | AL34: 126.966 | AM34: 162.018 | AN34: =AM34 -> 162.018 | AO34: 159.777 | AP34: 155.81 | AQ34: 155.553 | AR34: 163.465 | AS34: =AR34 -> 163.465 | AT34: 166.205 | AU34: 145.764 | AV34: 148.917 | AW34: 151.639 | AX34: =AW34 -> 151.639 | AY34: 184.999 | AZ34: 186.434 | BA34: 186.965 | BB34: =BB22-BB30-BB45-BB32-BB33-BB35 -> 291.62286 | BC34: =BB34 -> 291.62286 | BD34: =BD22-BD30-BD45-BD32-BD33-BD35 -> 326.86241 | BE34: =BE22-BE30-BE45-BE32-BE33-BE35 -> 431.22907 | BF34: =BF22-BF30-BF45-BF32-BF33-BF35 -> 523.31587 | BG34: =BG22-BG30-BG45-BG32-BG33-BG35 -> 574.7959 | BH34: =BG34 -> 574.7959 | BI34: =BI22-BI30-BI45-BI32-BI33-BI35 -> 560.12876 | BJ34: =BJ22-BJ30-BJ45-BJ32-BJ33-BJ35 -> 557.66219 | BK34: =BK22-BK30-BK45-BK32-BK33-BK35 -> 548.54013 | BL34: =BL22-BL30-BL45-BL32-BL33-BL35 -> 552.52683 | BM34: =BL34 -> 552.52683 | BN34: =BN22-BN30-BN45-BN32-BN33-BN35 -> 533.2137 | BO34: =BO22-BO30-BO45-BO32-BO33-BO35 -> 524.69099 | BP34: =BP22-BP30-BP45-BP32-BP33-BP35 -> 524.79988 | BQ34: =BQ22-BQ30-BQ45-BQ32-BQ33-BQ35 -> 530.25777 | BR34: =BQ34 -> 530.25777
B35: Contingencies and Commitments | F35: 0 | G35: 0 | H35: 0 | I35: =J35 -> 0 | J35: 0 | K35: 0 | L35: 0 | M35: 0 | N35: =O35 -> 0 | O35: 0 | P35: 0 | Q35: 0 | S35: =T35 -> 0 | T35: 0 | U35: 0 | V35: 0 | W35: 0 | X35: =Y35 -> 0 | Y35: 0 | Z35: 0 | AA35: 0 | AB35: 0 | AC35: 0 | AD35: =AC35 -> 0 | AE35: 0 | AF35: 0 | AG35: 0 | AH35: 0 | AI35: =AH35 -> 0
A36: Total liabilities | F36: =SUM(F32:F35)+F30 -> 1460.492 | G36: =SUM(G32:G35)+G30 -> 1546.211 | H36: =SUM(H32:H35)+H30 -> 1384.233 | I36: =SUM(I32:I35)+I30 -> 1466.226 | J36: =SUM(J32:J35)+J30 -> 1466.226 | K36: =SUM(K32:K35)+K30 -> 1474.113 | L36: =SUM(L32:L35)+L30 -> 1792.322 | M36: =SUM(M32:M35)+M30 -> 2372.542 | ... BR36: =SUM(BR32:BR35)+BR30 -> 2971.2112
A38: EQUITY
A39: Shareholders’ equity
B40: Common stock - $1 par value | F40: 49.048 | G40: 48.596 | H40: 47.09 | I40: =J40 -> 47.09 | J40: 47.09 | K40: 47.123 | L40: 47.286 | M40: 47.315 | N40: =O40 -> 47.329 | O40: 47.329 | P40: 47.368 | Q40: 47.556 | R40: 47.556 | S40: =T40 -> 47.556 | T40: 47.556 | U40: 47.576 | V40: 47.897 | W40: 48.115 | X40: =Y40 -> 48.421 | Y40: 48.421 | Z40: 48.528 | AA40: 48.572 | AB40: 48.646 | AC40: 48.671 | AD40: =AC40 -> 48.671 | AE40: 49.001 | AF40: 49.07 | AG40: 49.073 | AH40: 49.073 | AI40: =AH40 -> 49.073 | AJ40: 49.073 | AK40: 49.17 | AL40: 49.202 | AM40: 49.211 | AN40: =AM40 -> 49.211 | AO40: 49.694 | AP40: 49.76 | AQ40: 49.781 | AR40: 49.781 | AS40: =AR40 -> 49.781 | AT40: 49.913 | AU40: 50.011 | AV40: 50.026 | AW40: 50.026 | AX40: =AW40 -> 50.026 | AY40: 50.18 | AZ40: 50.279 | BA40: 50.279 | BB40: =BA40 -> 50.279 | BC40: =BB40 -> 50.279 | BD40: =BB40 -> 50.279 | BE40: =BD40 -> 50.279 | BF40: =BE40 -> 50.279 | BG40: =BF40 -> 50.279 | BH40: =BG40 -> 50.279 | BI40: =BG40 -> 50.279 | BJ40: =BI40 -> 50.279 | BK40: =BJ40 -> 50.279 | BL40: =BK40 -> 50.279 | BM40: =BL40 -> 50.279 | BN40: =BL40 -> 50.279 | BO40: =BN40 -> 50.279 | BP40: =BO40 -> 50.279 | BQ40: =BP40 -> 50.279 | BR40: =BQ40 -> 50.279
B41: Additional Paid-in Capital | F41: 1015.757 | G41: 1007.327 | H41: 982.917 | I41: =J41 -> 985.413 | J41: 985.413 | K41: 989.013 | L41: 992.546 | M41: 991.884 | N41: =O41 -> 993.434 | O41: 993.434 | P41: 996.313 | Q41: 998.207 | R41: 1000.557 | S41: =T41 -> 1002.603 | T41: 1002.603 | U41: 1005.534 | V41: 1008.995 | W41: 1008.796 | X41: =Y41 -> 1007.918 | Y41: 1007.918 | Z41: 1011.381 | AA41: 1016.823 | AB41: 1020.806 | AC41: 1025.941 | AD41: =AC41 -> 1025.941 | AE41: 1033.997 | AF41: 1039.425 | AG41: 1043.103 | AH41: 1035.516 | AI41: =AH41 -> 1035.516 | AJ41: 1039.07 | AK41: 1070.191 | AL41: 1072.811 | AM41: 1075.6 | AN41: =AM41 -> 1075.6 | AO41: 1068.264 | AP41: 1075.637 | AQ41: 1080.371 | AR41: 1084.205 | AS41: =AR41 -> 1084.205 | AT41: 1087.164 | AU41: 1093.874 | AV41: 1098.639 | AW41: 1102.919 | AX41: =AW41 -> 1102.919 | AY41: 1105.184 | AZ41: 1110.496 | BA41: 1113.987 | BB41: =BA41 -> 1113.987 | BC41: =BB41 -> 1113.987 | BD41: =BB41 -> 1113.987 | BE41: =BD41 -> 1113.987 | BF41: =BE41 -> 1113.987 | BG41: =BF41 -> 1113.987 | BH41: =BG41 -> 1113.987 | BI41: =BG41 -> 1113.987 | BJ41: =BI41 -> 1113.987 | BK41: =BJ41 -> 1113.987 | BL41: =BK41 -> 1113.987 | BM41: =BL41 -> 1113.987 | BN41: =BL41 -> 1113.987 | BO41: =BN41 -> 1113.987 | BP41: =BO41 -> 1113.987 | BQ41: =BP41 -> 1113.987 | BR41: =BQ41 -> 1113.987
B42: Retained Earnings | F42: 281.054 | G42: 313.779 | H42: 344.712 | I42: =J42 -> 316.531 | J42: 316.531 | K42: 323.46 | L42: 343.154 | M42: 378.631 | N42: =O42 -> 402.679 | O42: 402.679 | P42: 401.476 | Q42: 53.053 | R42: 95.644 | S42: =T42 -> 137.279 | T42: 137.279 | U42: 152.079 | V42: 167.557 | W42: 191.316 | X42: =Y42 -> 224.575 | Y42: 224.575 | Z42: 240.514 | AA42: 269.059 | AB42: 304.789 | AC42: 332.511 | AD42: =AC42 -> 332.511 | AE42: 337.637 | AF42: 349.414 | AG42: 369.091 | AH42: 377.803 | AI42: =AH42 -> 377.803 | AJ42: 393.203 | AK42: 414.563 | AL42: 443.364 | AM42: 473.625 | AN42: =AM42 -> 473.625 | AO42: 487.389 | AP42: 517.485 | AQ42: 541.069 | AR42: 622.007 | AS42: =AR42 -> 622.007 | AT42: 606.199 | AU42: 631.004 | AV42: 652.276 | AW42: 701.681 | AX42: =AW42 -> 701.681 | AY42: 701.325 | AZ42: 380.795 | BA42: 400.108 | BB42: =BA42+IS!BB48 -> 430.45795 | BC42: =BB42 -> 430.45795 | BD42: =BB42+IS!BD48 -> 468.09214 | BE42: =BD42+IS!BE48 -> 526.84016 | BF42: =BE42+IS!BF48 -> 586.1165 | BG42: =BF42+IS!BG48 -> 645.79059 | BH42: =BG42 -> 645.79059 | BI42: =BG42+IS!BI48 -> 681.96663 | BJ42: =BI42+IS!BJ48 -> 741.41215 | BK42: =BJ42+IS!BK48 -> 800.15513 | BL42: =BK42+IS!BL48 -> 861.12322 | BM42: =BL42 -> 861.12322 | BN42: =BL42+IS!BN48 -> 895.94861 | BO42: =BN42+IS!BO48 -> 954.66744 | BP42: =BO42+IS!BP48 -> 1014.5315 | BQ42: =BP42+IS!BQ48 -> 1076.4559 | BR42: =BQ42 -> 1076.4559
B43: Accumulated other comprehensive loss | F43: -33.166 | G43: -33.222 | H43: -33.003 | I43: =J43 -> -36.04 | J43: -36.04 | K43: -35.996 | L43: -35.951 | M43: -36.635 | N43: =O43 -> -43.615 | O43: -43.615 | P43: -41.77 | Q43: -42.365 | R43: -43.02 | S43: =T43 -> -43.574 | T43: -43.574 | U43: -43.491 | V43: -43.594 | W43: -44.256 | X43: =Y43 -> -33.379 | Y43: -33.379 | Z43: -33.403 | AA43: -32.987 | AB43: -33.314 | AC43: -41.618 | AD43: =AC43 -> -41.618 | AE43: -42.171 | AF43: -43.331 | AG43: -44.661 | AH43: -42.165 | AI43: =AH43 -> -42.165 | AJ43: -41.015 | AK43: -41.091 | AL43: -41.333 | AM43: -45.413 | AN43: =AM43 -> -45.413 | AO43: -45.22 | AP43: -44.305 | AQ43: -43.298 | AR43: -42.718 | AS43: =AR43 -> -42.718 | AT43: -43.596 | AU43: -44.805 | AV43: -44.193 | AW43: -45.449 | AX43: =AW43 -> -45.449 | AY43: -44.2 | AZ43: -42.53 | BA43: -42.294 | BB43: =BA43 -> -42.294 | BC43: =BB43 -> -42.294 | BD43: =BB43 -> -42.294 | BE43: =BD43 -> -42.294 | BF43: =BE43 -> -42.294 | BG43: =BF43 -> -42.294 | BH43: =BG43 -> -42.294 | BI43: =BG43 -> -42.294 | BJ43: =BI43 -> -42.294 | BK43: =BJ43 -> -42.294 | BL43: =BK43 -> -42.294 | BM43: =BL43 -> -42.294 | BN43: =BL43 -> -42.294 | BO43: =BN43 -> -42.294 | BP43: =BO43 -> -42.294 | BQ43: =BP43 -> -42.294 | BR43: =BQ43 -> -42.294
B44: NCI | AP44: 1.287 | AQ44: 3.003 | AR44: -8.495 | AS44: =AR44 -> -8.495 | AT44: -14.076 | AU44: -17.618 | AV44: -23.376 | AW44: -21.288 | AX44: =AW44 -> -21.288 | AY44: -17.31 | AZ44: -9.481 | BA44: -18.532
A45: Total Equity | F45: =SUM(F40:F43) -> 1312.693 | G45: =SUM(G40:G43) -> 1336.48 | H45: =SUM(H40:H43) -> 1341.716 | I45: =SUM(I40:I43) -> 1312.994 | J45: =SUM(J40:J43) -> 1312.994 | K45: =SUM(K40:K43) -> 1323.6 | L45: =SUM(L40:L43) -> 1347.035 | M45: =SUM(M40:M43) -> 1381.195 | ... AO45: =SUM(AO40:AO43) -> 1560.127 | AP45: =SUM(AP40:AP44) -> 1599.864 | AQ45: =SUM(AQ40:AQ44) -> 1630.926 | AR45: =SUM(AR40:AR44) -> 1704.78 | AS45: =SUM(AS40:AS44) -> 1704.78 | AT45: =SUM(AT40:AT44) -> 1685.604 | AU45: =SUM(AU40:AU44) -> 1712.466 | AV45: =SUM(AV40:AV44) -> 1733.372 | AW45: =SUM(AW40:AW44) -> 1787.889 | ... BB45: =SUM(BB40:BB44) -> 1552.43 | BC45: =SUM(BC40:BC43) -> 1552.43 | BD45: =SUM(BD40:BD44) -> 1590.0641 | BE45: =SUM(BE40:BE44) -> 1648.8122 | BF45: =SUM(BF40:BF44) -> 1708.0885 | BG45: =SUM(BG40:BG44) -> 1767.7626 | BH45: =SUM(BH40:BH43) -> 1767.7626 | BI45: =SUM(BI40:BI44) -> 1803.9386 | BJ45: =SUM(BJ40:BJ44) -> 1863.3842 | BK45: =SUM(BK40:BK44) -> 1922.1271 | BL45: =SUM(BL40:BL44) -> 1983.0952 | BM45: =SUM(BM40:BM43) -> 1983.0952 | BN45: =SUM(BN40:BN44) -> 2017.9206 | BO45: =SUM(BO40:BO44) -> 2076.6394 | BP45: =SUM(BP40:BP44) -> 2136.5035 | BQ45: =SUM(BQ40:BQ44) -> 2198.4279 | BR45: =SUM(BR40:BR43) -> 2198.4279
A47: Total Liabilities and Stockholders Equity | F47: =F45+F36 -> 2773.185 | G47: =G45+G36 -> 2882.691 | H47: =H45+H36 -> 2725.949 | I47: =I45+I36 -> 2779.22 | J47: =J45+J36 -> 2779.22 | K47: =K45+K36 -> 2797.713 | L47: =L45+L36 -> 3139.357 | M47: =M45+M36 -> 3753.737 | ... BR47: =BR45+BR36 -> 5169.6391
F48: =IF(F47=F22,"OK","CHECK") -> OK | G48: =IF(G47=G22,"OK","CHECK") -> OK | H48: =IF(H47=H22,"OK","CHECK") -> OK | I48: =IF(I47=I22,"OK","CHECK") -> OK | K48: =IF(K47=K22,"OK","CHECK") -> OK | L48: =IF(L47=L22,"OK","CHECK") -> OK | M48: =IF(M47=M22,"OK","CHECK") -> OK | N48: =IF(N47=N22,"OK","CHECK") -> OK | P48: =IF(P47=P22,"OK","CHECK") -> OK | Q48: =IF(Q47=Q22,"OK","CHECK") -> OK | R48: =IF(R47=R22,"OK","CHECK") -> OK | S48: =IF(S47=S22,"OK","CHECK") -> OK | U48: =IF(U47=U22,"OK","CHECK") -> OK | V48: =IF(V47=V22,"OK","CHECK") -> OK | W48: =IF(W47=W22,"OK","CHECK") -> OK | X48: =IF(X47=X22,"OK","CHECK") -> OK | Z48: =IF(Z47=Z22,"OK","CHECK") -> OK | AA48: =IF(AA47=AA22,"OK","CHECK") -> OK | AB48: =IF(AB47=AB22,"OK","CHECK") -> OK | AC48: =IF(AC47=AC22,"OK","CHECK") -> OK | AE48: =IF(AE47=AE22,"OK","CHECK") -> OK | AF48: =IF(AF47=AF22,"OK","CHECK") -> OK | AG48: =IF(AG47=AG22,"OK","CHECK") -> OK | AH48: =IF(AH47=AH22,"OK","CHECK") -> OK | AJ48: =IF(AJ47=AJ22,"OK","CHECK") -> OK | AK48: =IF(AK47=AK22,"OK","CHECK") -> OK | AL48: =IF(AL47=AL22,"OK","CHECK") -> OK | AM48: =IF(AM47=AM22,"OK","CHECK") -> OK | AO48: =IF(AO47=AO22,"OK","CHECK") -> OK | AP48: =IF(AP47=AP22,"OK","CHECK") -> OK | AQ48: =IF(AQ47=AQ22,"OK","CHECK") -> OK | AR48: =IF(AR47=AR22,"OK","CHECK") -> OK | AT48: =IF(AT47=AT22,"OK","CHECK") -> OK | AU48: =IF(AU47=AU22,"OK","CHECK") -> OK | AV48: =IF(AV47=AV22,"OK","CHECK") -> OK | AW48: =IF(AW47=AW22,"OK","CHECK") -> OK | AY48: =IF(AY47=AY22,"OK","CHECK") -> OK | AZ48: =IF(AZ47=AZ22,"OK","CHECK") -> OK | BA48: =IF(BA47=BA22,"OK","CHECK") -> OK | BB48: =IF(BB47=BB22,"OK","CHECK") -> OK | BD48: =IF(BD47=BD22,"OK","CHECK") -> OK | BE48: =IF(BE47=BE22,"OK","CHECK") -> OK | BF48: =IF(BF47=BF22,"OK","CHECK") -> OK | BG48: =IF(BG47=BG22,"OK","CHECK") -> OK | BI48: =IF(BI47=BI22,"OK","CHECK") -> OK | BJ48: =IF(BJ47=BJ22,"OK","CHECK") -> OK | BK48: =IF(BK47=BK22,"OK","CHECK") -> OK | BL48: =IF(BL47=BL22,"OK","CHECK") -> OK | BN48: =IF(BN47=BN22,"OK","CHECK") -> OK | BO48: =IF(BO47=BO22,"OK","CHECK") -> OK | BP48: =IF(BP47=BP22,"OK","CHECK") -> OK | BQ48: =IF(BQ47=BQ22,"OK","CHECK") -> OK
A50: LTM Sales | I50: =SUM(IS!F11:I11) -> 3199.21 | K50: =SUM(IS!K11,IS!G11:I11) -> 2949.424 | L50: =SUM(IS!K11:L11,IS!H11:I11) -> 2854.906 | M50: =SUM(IS!K11:M11,IS!I11) -> 3289.51 | N50: =SUM(IS!K11:N11) -> 3716.317 | P50: =SUM(IS!P11,IS!L11:N11) -> 4013.562 | Q50: =SUM(IS!P11:Q11,IS!M11:N11) -> 4179.05 | R50: =SUM(IS!P11:R11,IS!N11) -> 4112.033 | S50: =SUM(IS!P11:S11) -> 4111.471 | U50: =SUM(IS!U11,IS!Q11:S11) -> 4191.865 | V50: =SUM(IS!U11:V11,IS!R11:S11) -> 4259.584 | W50: =SUM(IS!U11:W11,IS!S11) -> 4190.579 | X50: =SUM(IS!U11:X11) -> 4175.672 | Z50: =SUM(IS!Z11,IS!V11:X11) -> 4137.977 | AA50: =SUM(IS!Z11:AA11,IS!W11:X11) -> 4169.422 | AB50: =SUM(IS!Z11:AB11,IS!X11) -> 4389.723 | AC50: =SUM(IS!Z11:AC11) -> 4492.309 | AE50: =SUM(IS!AE11,IS!AA11:AC11) -> 4603.541 | AF50: =SUM(IS!AE11:AF11,IS!AB11:AC11) -> 4831.469 | AG50: =SUM(IS!AE11:AG11,IS!AC11) -> 4921.519 | AH50: =SUM(IS!AE11:AH11) -> 4920.472 | AJ50: =SUM(IS!AJ11,IS!AF11:AH11) -> 4939.376 | AK50: =SUM(IS!AJ11:AK11,IS!AG11:AH11) -> 4873.209 | AL50: =SUM(IS!AJ11:AL11,IS!AH11) -> 4865.448 | AM50: =SUM(IS!AJ11:AM11) -> 4911.217 | AO50: =SUM(IS!AO11,IS!AK11:AM11) -> 4943.209 | AP50: =SUM(IS!AO11:AP11,IS!AL11:AM11) -> 4944.212 | AQ50: =SUM(IS!AO11:AQ11,IS!AM11) -> 4810.739 | AR50: =SUM(IS!AO11:AR11) -> 4757.208 | AT50: =SUM(IS!AT11,IS!AP11:AR11) -> 4668.003 | AU50: =SUM(IS!AT11:AU11,IS!AQ11:AR11) -> 4540.814 | AV50: =SUM(IS!AT11:AV11,IS!AR11) -> 4464.446 | AW50: =SUM(IS!AT11:AW11) -> 4454.662 | AY50: =SUM(IS!AY11,IS!AU11:AW11) -> 4384.993 | AZ50: =SUM(IS!AY11:AZ11,IS!AV11:AW11) -> 4390.183 | BA50: =SUM(IS!AY11:BA11,IS!AW11) -> 4456.391 | BB50: =SUM(IS!AY11:BB11) -> 4639.6693 | BD50: =SUM(IS!BD11,IS!AZ11:BB11) -> 4803.7636 | BE50: =SUM(IS!BD11:BE11,IS!BA11:BB11) -> 5194.5311 | BF50: =SUM(IS!BD11:BF11,IS!BB11) -> 5546.3419 | BG50: =SUM(IS!BD11:BG11) -> 5766.034 | BI50: =SUM(IS!BI11,IS!BE11:BG11) -> 5736.1187 | BJ50: =SUM(IS!BI11:BJ11,IS!BF11:BG11) -> 5746.2795 | BK50: =SUM(IS!BI11:BK11,IS!BG11) -> 5734.5223 | BL50: =SUM(IS!BI11:BL11) -> 5766.034 | BN50: =SUM(IS!BN11,IS!BJ11:BL11) -> 5720.5461 | BO50: =SUM(IS!BN11:BO11,IS!BK11:BL11) -> 5710.6744 | BP50: =SUM(IS!BN11:BP11,IS!BL11) -> 5729.4284 | BQ50: =SUM(IS!BN11:BQ11) -> 5766.034
A52: DSO | I52: =+I9/I50*365 -> 100.46984 | K52: =+K9/K50*365 -> 112.76025 | L52: =+L9/L50*365 -> 130.56947 | M52: =+M9/M50*365 -> 145.61786 | N52: =+N9/N50*365 -> 125.22783 | P52: =+P9/P50*365 -> 107.6943 | Q52: =+Q9/Q50*365 -> 104.70056 | R52: =+R9/R50*365 -> 110.93594 | S52: =+S9/S50*365 -> 108.71626 | U52: =+U9/U50*365 -> 115.94304 | V52: =+V9/V50*365 -> 119.06597 | W52: =+W9/W50*365 -> 121.75353 | X52: =+X9/X50*365 -> 112.86921 | Z52: =+Z9/Z50*365 -> 111.44029 | AA52: =+AA9/AA50*365 -> 127.29017 | AB52: =+AB9/AB50*365 -> 131.42442 | AC52: =+AC9/AC50*365 -> 120.20967 | AE52: =+AE9/AE50*365 -> 110.5353 | AF52: =+AF9/AF50*365 -> 117.36236 | AG52: =+AG9/AG50*365 -> 115.0185 | AH52: =+AH9/AH50*365 -> 109.31258 | AJ52: =+AJ9/AJ50*365 -> 119.39084 | AK52: =+AK9/AK50*365 -> 130.27559 | AL52: =+AL9/AL50*365 -> 128.93366 | AM52: =+AM9/AM50*365 -> 129.56147 | AO52: =+AO9/AO50*365 -> 129.18829 | AP52: =+AP9/AP50*365 -> 135.71445 | AQ52: =+AQ9/AQ50*365 -> 140.96016 | AR52: =+AR9/AR50*365 -> 138.23327 | AT52: =+AT9/AT50*365 -> 138.22099 | AU52: =+AU9/AU50*365 -> 141.76848 | AV52: =+AV9/AV50*365 -> 148.66721 | AW52: =+AW9/AW50*365 -> 142.55466 | AY52: =+AY9/AY50*365 -> 152.99334 | AZ52: =+AZ9/AZ50*365 -> 164.42074 | BA52: =+BA9/BA50*365 -> 164.03279
A53: DPO | I53: =+I27/I50*365 -> 74.563042 | K53: =+K27/K50*365 -> 73.96208 | L53: =+L27/L50*365 -> 80.568316 | M53: =+M27/M50*365 -> 85.079971 | N53: =+N27/N50*365 -> 77.170388 | P53: =+P27/P50*365 -> 62.233835 | Q53: =+Q27/Q50*365 -> 60.521674 | R53: =+R27/R50*365 -> 66.634778 | S53: =+S27/S50*365 -> 61.830096 | U53: =+U27/U50*365 -> 61.466517 | V53: =+V27/V50*365 -> 65.167603 | W53: =+W27/W50*365 -> 69.430044 | X53: =+X27/X50*365 -> 66.277266 | Z53: =+Z27/Z50*365 -> 69.828293 | AA53: =+AA27/AA50*365 -> 74.378228 | AB53: =+AB27/AB50*365 -> 71.81084 | AC53: =+AC27/AC50*365 -> 64.851619 | AE53: =+AE27/AE50*365 -> 63.603151 | AF53: =+AF27/AF50*365 -> 72.768541 | AG53: =+AG27/AG50*365 -> 73.067727 | AH53: =+AH27/AH50*365 -> 69.540963 | AJ53: =+AJ27/AJ50*365 -> 74.332404 | AK53: =+AK27/AK50*365 -> 72.516989 | AL53: =+AL27/AL50*365 -> 71.24144 | AM53: =+AM27/AM50*365 -> 73.874936 | AO53: =+AO27/AO50*365 -> 71.323065 | AP53: =+AP27/AP50*365 -> 66.388468 | AQ53: =+AQ27/AQ50*365 -> 72.053665 | AR53: =+AR27/AR50*365 -> 73.794065 | AT53: =+AT27/AT50*365 -> 70.788921 | AU53: =+AU27/AU50*365 -> 69.287812 | AV53: =+AV27/AV50*365 -> 67.411152 | AW53: =+AW27/AW50*365 -> 68.309259 | AY53: =+AY27/AY50*365 -> 68.132832 | AZ53: =+AZ27/AZ50*365 -> 75.959154 | BA53: =+BA27/BA50*365 -> 73.932798
A54: CCC | I54: =+I52-I53 -> 25.906796 | K54: =+K52-K53 -> 38.798167 | L54: =+L52-L53 -> 50.001149 | M54: =+M52-M53 -> 60.537887 | N54: =+N52-N53 -> 48.057442 | P54: =+P52-P53 -> 45.460464 | Q54: =+Q52-Q53 -> 44.178883 | R54: =+R52-R53 -> 44.301164 | S54: =+S52-S53 -> 46.886163 | U54: =+U52-U53 -> 54.476524 | V54: =+V52-V53 -> 53.89837 | W54: =+W52-W53 -> 52.32349 | X54: =+X52-X53 -> 46.591941 | Z54: =+Z52-Z53 -> 41.611995 | AA54: =+AA52-AA53 -> 52.91194 | AB54: =+AB52-AB53 -> 59.613583 | AC54: =+AC52-AC53 -> 55.358046 | AE54: =+AE52-AE53 -> 46.932152 | AF54: =+AF52-AF53 -> 44.59382 | AG54: =+AG52-AG53 -> 41.950772 | AH54: =+AH52-AH53 -> 39.771614 | AJ54: =+AJ52-AJ53 -> 45.05844 | AK54: =+AK52-AK53 -> 57.758604 | AL54: =+AL52-AL53 -> 57.692222 | AM54: =+AM52-AM53 -> 55.686536 | AO54: =+AO52-AO53 -> 57.865228 | AP54: =+AP52-AP53 -> 69.325987 | AQ54: =+AQ52-AQ53 -> 68.906498 | AR54: =+AR52-AR53 -> 64.43921 | AT54: =+AT52-AT53 -> 67.432065 | AU54: =+AU52-AU53 -> 72.480668 | AV54: =+AV52-AV53 -> 81.256057 | AW54: =+AW52-AW53 -> 74.245404 | AY54: =+AY52-AY53 -> 84.860513 | AZ54: =+AZ52-AZ53 -> 88.461587 | BA54: =+BA52-BA53 -> 90.099995
A56: Assumptions
C58: Cash and cash equivalents
C59: Restricted Cash
C60: Accounts Receivable, including retainage | I60: =I9/I$50 -> 0.27525983 | K60: =K9/K$50 -> 0.30893218 | L60: =L9/L$50 -> 0.35772456 | M60: =M9/M$50 -> 0.39895304 | N60: =N9/N$50 -> 0.34308995 | P60: =P9/P$50 -> 0.29505287 | Q60: =Q9/Q$50 -> 0.28685084 | R60: =R9/R$50 -> 0.30393409 | S60: =S9/S$50 -> 0.29785276 | U60: =U9/U$50 -> 0.31765217 | V60: =V9/V$50 -> 0.32620815 | W60: =W9/W$50 -> 0.33357133 | X60: =X9/X$50 -> 0.30923071 | Z60: =Z9/Z$50 -> 0.30531586 | AA60: =AA9/AA$50 -> 0.34874019 | AB60: =AB9/AB$50 -> 0.36006691 | AC60: =AC9/AC$50 -> 0.32934155 | AE60: =AE9/AE$50 -> 0.30283645 | AF60: =AF9/AF$50 -> 0.32154072 | AG60: =AG9/AG$50 -> 0.31511917 | AH60: =AH9/AH$50 -> 0.29948651 | AJ60: =AJ9/AJ$50 -> 0.3270982 | AK60: =AK9/AK$50 -> 0.35691943 | AL60: =AL9/AL$50 -> 0.35324291 | AM60: =AM9/AM$50 -> 0.35496293 | AO60: =AO9/AO$50 -> 0.35394053 | AP60: =AP9/AP$50 -> 0.37182042 | AQ60: =AQ9/AQ$50 -> 0.38619223 | AR60: =AR9/AR$50 -> 0.3787213 | AT60: =AT9/AT$50 -> 0.37868763 | AU60: =AU9/AU$50 -> 0.38840679 | AV60: =AV9/AV$50 -> 0.40730742 | AW60: =AW9/AW$50 -> 0.39056072 | AY60: =AY9/AY$50 -> 0.41915985 | AZ60: =AZ9/AZ$50 -> 0.45046778 | BA60: =BA9/BA$50 -> 0.44940491 | BB60: =BA60-0.0005 -> 0.44890491 | BD60: =BB60-0.0005 -> 0.44840491 | BE60: =BD60-0.0005 -> 0.44790491 | BF60: =BE60-0.0005 -> 0.44740491 | BG60: =BF60-0.0005 -> 0.44690491 | BI60: =BG60-0.0005 -> 0.44640491 | BJ60: =BI60-0.0005 -> 0.44590491 | BK60: =BJ60-0.0005 -> 0.44540491 | BL60: =BK60-0.0005 -> 0.44490491 | BN60: =BL60-0.0005 -> 0.44440491 | BO60: =BN60-0.0005 -> 0.44390491 | BP60: =BO60-0.0005 -> 0.44340491 | BQ60: =BP60-0.0005 -> 0.44290491
C61: Costs and Estimated Earnings in Excess of Billings | I61: =I10/I$50 -> 0.043588573 | K61: =K10/K$50 -> 0.058499558 | L61: =L10/L$50 -> 0.075349941 | M61: =M10/M$50 -> 0.11379354 | N61: =N10/N$50 -> 0.096439028 | P61: =P10/P$50 -> 0.094080769 | Q61: =Q10/Q$50 -> 0.089717998 | R61: =R10/R$50 -> 0.10011155 | S61: =S10/S$50 -> 0.11309869 | U61: =U10/U$50 -> 0.11435507 | V61: =V10/V$50 -> 0.11853528 | W61: =W10/W$50 -> 0.12848368 | X61: =X10/X$50 -> 0.13728281 | Z61: =Z10/Z$50 -> 0.16878368 | AA61: =AA10/AA$50 -> 0.15852365 | AB61: =AB10/AB$50 -> 0.16405978 | AC61: =AC10/AC$50 -> 0.16169903 | AE61: =AE10/AE$50 -> 0.17280394 | AF61: =AF10/AF$50 -> 0.16899208 | AG61: =AG10/AG$50 -> 0.17958053 | AH61: =AH10/AH$50 -> 0.18396101 | AJ61: =AJ10/AJ$50 -> 0.17377823 | AK61: =AK10/AK$50 -> 0.16650343 | AL61: =AL10/AL$50 -> 0.1685853 | AM61: =AM10/AM$50 -> 0.16937268 | AO61: =AO10/AO$50 -> 0.17008385 | AP61: =AP10/AP$50 -> 0.17204643 | AQ61: =AQ10/AQ$50 -> 0.18756204 | AR61: =AR10/AR$50 -> 0.19607257 | AT61: =AT10/AT$50 -> 0.21013183 | AU61: =AU10/AU$50 -> 0.22996604 | AV61: =AV10/AV$50 -> 0.24317709 | AW61: =AW10/AW$50 -> 0.25642686 | AY61: =AY10/AY$50 -> 0.26651696 | AZ61: =AZ10/AZ$50 -> 0.26545773 | BA61: =BA10/BA$50 -> 0.26015065 | BB61: 0.12 | BD61: 0.12 | BE61: 0.12 | BF61: 0.12 | BG61: 0.12 | BI61: 0.12 | BJ61: 0.12 | BK61: 0.12 | BL61: 0.12 | BN61: 0.12 | BO61: 0.12 | BP61: 0.12 | BQ61: 0.12
C62: Deferred Income taxes | I62: =I11/I$50 -> 0.0011681009 | K62: =K11/K$50 -> 0.0012822843 | L62: =L11/L$50 -> 0.0040071372 | M62: =M11/M$50 -> 0.0056418737 | N62: =N11/N$50 -> 0 | P62: =P11/P$50 -> 0.00048784596 | Q62: =Q11/Q$50 -> 0.00070135557 | R62: =R11/R$50 -> 0.00078939055 | S62: =S11/S$50 -> 0.0024494883 | U62: =U11/U$50 -> 0.0023190155 | V62: =V11/V$50 -> 0.002218996 | W62: =W11/W$50 -> 0.0022982504 | X62: =X11/X$50 -> 0.0019733351 | Z62: =Z11/Z$50 -> 0.0019804363 | AA62: =AA11/AA$50 -> 0.001914414 | AB62: =AB11/AB$50 -> 0.001811276 | AC62: =AC11/AC$50 -> 0.0039983892 | AE62: =AE11/AE$50 -> 0.0039017791 | AF62: =AF11/AF$50 -> 0.0037156401 | AG62: =AG11/AG$50 -> 0.0038347917 | AH62: =AH11/AH$50 -> 0.0053462351 | AJ62: =AJ11/AJ$50 -> 0.0053751729 | AK62: =AK11/AK$50 -> 0.0039189782 | AL62: =AL11/AL$50 -> 0.0053497643 | AM62: =AM11/AM$50 -> 0 | AO62: =AO11/AO$50 -> 0 | AP62: =AP11/AP$50 -> 0 | AQ62: =AQ11/AQ$50 -> 0 | AR62: =AR11/AR$50 -> 0 | AT62: =AT11/AT$50 -> 0 | AU62: =AU11/AU$50 -> 0 | AV62: =AV11/AV$50 -> 0 | AW62: =AW11/AW$50 -> 0 | AY62: =AY11/AY$50 -> 0 | AZ62: =AZ11/AZ$50 -> 0 | BA62: =BA11/BA$50 -> 0 | BB62: 0.001811276 | BD62: 0.001811276 | BE62: 0.001811276 | BF62: 0.001811276 | BG62: 0.001811276 | BI62: 0.001811276 | BJ62: 0.001811276 | BK62: 0.001811276 | BL62: 0.001811276 | BN62: 0.001811276 | BO62: 0.001811276 | BP62: 0.001811276 | BQ62: 0.001811276
C63: Other Current Assets | I63: =I12/I$50 -> 0.01322639 | K63: =K12/K$50 -> 0.01199285 | L63: =L12/L$50 -> 0.018515496 | M63: =M12/M$50 -> 0.028504853 | N63: =N12/N$50 -> 0.020700064 | P63: =P12/P$50 -> 0.021891278 | Q63: =Q12/Q$50 -> 0.024331846 | R63: =R12/R$50 -> 0.018487449 | S63: =S12/S$50 -> 0.018336016 | U63: =U12/U$50 -> 0.017772519 | V63: =V12/V$50 -> 0.012633628 | W63: =W12/W$50 -> 0.011540171 | X63: =X12/X$50 -> 0.012134334 | Z63: =Z12/Z$50 -> 0.013257203 | AA63: =AA12/AA$50 -> 0.012572486 | AB63: =AB12/AB$50 -> 0.015790974 | AC63: =AC12/AC$50 -> 0.015300595 | AE63: =AE12/AE$50 -> 0.016154304 | AF63: =AF12/AF$50 -> 0.021368863 | AG63: =AG12/AG$50 -> 0.017623421 | AH63: =AH12/AH$50 -> 0.022120642 | AJ63: =AJ12/AJ$50 -> 0.01862381 | AK63: =AK12/AK$50 -> 0.015792469 | AL63: =AL12/AL$50 -> 0.013464536 | AM63: =AM12/AM$50 -> 0.013443307 | AO63: =AO12/AO$50 -> 0.011830776 | AP63: =AP12/AP$50 -> 0.015722627 | AQ63: =AQ12/AQ$50 -> 0.014713124 | AR63: =AR12/AR$50 -> 0.018774878 | AT63: =AT12/AT$50 -> 0.028341456 | AU63: =AU12/AU$50 -> 0.031155647 | AV63: =AV12/AV$50 -> 0.029124106 | AW63: =AW12/AW$50 -> 0.025933954 | AY63: =AY12/AY$50 -> 0.028347366 | AZ63: =AZ12/AZ$50 -> 0.037740568 | BA63: =BA12/BA$50 -> 0.036443391 | BB63: 0.015790974 | BD63: 0.015790974 | BE63: 0.015790974 | BF63: 0.015790974 | BG63: 0.015790974 | BI63: 0.015790974 | BJ63: 0.015790974 | BK63: 0.015790974 | BL63: 0.015790974 | BN63: 0.015790974 | BO63: 0.015790974 | BP63: 0.015790974 | BQ63: 0.015790974
C66: Long-term Investments | I66: =I15/I$50 -> 0.027547113 | K66: =K15/K$50 -> 0.029880071 | L66: =L15/L$50 -> 0.030869318 | M66: =M15/M$50 -> 0.020386319 | N66: =N15/N$50 -> 0.016766869 | P66: =P15/P$50 -> 0.011531652 | Q66: =Q15/Q$50 -> 0.011075005 | R66: =R15/R$50 -> 0.011255503 | S66: =S15/S$50 -> 0.011257042 | U66: =U15/U$50 -> 0.011041148 | V66: =V15/V$50 -> 0.010865615 | W66: =W15/W$50 -> 0.011044536 | X66: =X15/X$50 -> 0.011083964 | Z66: =Z15/Z$50 -> 0.011184934 | AA66: =AA15/AA$50 -> 0 | AB66: =AB15/AB$50 -> 0 | AC66: =AC15/AC$50 -> 0 | AE66: =AE15/AE$50 -> 0 | AF66: =AF15/AF$50 -> 0 | AG66: =AG15/AG$50 -> 0 | AH66: =AH15/AH$50 -> 0 | AJ66: =AJ15/AJ$50 -> 0 | AK66: =AK15/AK$50 -> 0 | AL66: =AL15/AL$50 -> 0 | AM66: =AM15/AM$50 -> 0 | AO66: =AO15/AO$50 -> 0 | AP66: =AP15/AP$50 -> 0 | AQ66: =AQ15/AQ$50 -> 0 | AR66: =AR15/AR$50 -> 0 | AT66: =AT15/AT$50 -> 0 | AU66: =AU15/AU$50 -> 0 | AV66: =AV15/AV$50 -> 0 | AW66: =AW15/AW$50 -> 0 | AY66: =AY15/AY$50 -> 0 | AZ66: =AZ15/AZ$50 -> 0 | BA66: =BA15/BA$50 -> 0 | BB66: 0 | BD66: 0 | BE66: 0 | BF66: 0 | BG66: 0 | BI66: 0 | BJ66: 0 | BK66: 0 | BL66: 0 | BN66: 0 | BO66: 0 | BP66: 0 | BQ66: 0
C67: Property, Plant and Equipment (less Accumulated Depreciation) | I67: =I18/I$50 -> 0.11328953 | K67: =K18/K$50 -> 0.12661794 | L67: =L18/L$50 -> 0.14882066 | M67: =M18/M$50 -> 0.14364693 | N67: =N18/N$50 -> 0.1322215 | P67: =P18/P$50 -> 0.12208881 | Q67: =Q18/Q$50 -> 0.11689044 | R67: =R18/R$50 -> 0.11870381 | S67: =S18/S$50 -> 0.11798575 | U67: =U18/U$50 -> 0.11626925 | V67: =V18/V$50 -> 0.11537676 | W67: =W18/W$50 -> 0.11772263 | X67: =X18/X$50 -> 0.11929218 | Z67: =Z18/Z$50 -> 0.12486367 | AA67: =AA18/AA$50 -> 0.12700681 | AB67: =AB18/AB$50 -> 0.1200488 | AC67: =AC18/AC$50 -> 0.11744562 | AE67: =AE18/AE$50 -> 0.11374331 | AF67: =AF18/AF$50 -> 0.11131873 | AG67: =AG18/AG$50 -> 0.10798252 | AH67: =AH18/AH$50 -> 0.10639731 | AJ67: =AJ18/AJ$50 -> 0.10525419 | AK67: =AK18/AK$50 -> 0.10411928 | AL67: =AL18/AL$50 -> 0.10118863 | AM67: =AM18/AM$50 -> 0.097252066 | AO67: =AO18/AO$50 -> 0.093602152 | AP67: =AP18/AP$50 -> 0.092229257 | AQ67: =AQ18/AQ$50 -> 0.093039344 | AR67: =AR18/AR$50 -> 0.098271717 | AT67: =AT18/AT$50 -> 0.10136626 | AU67: =AU18/AU$50 -> 0.10804539 | AV67: =AV18/AV$50 -> 0.11076358 | AW67: =AW18/AW$50 -> 0.1101473 | AY67: =AY18/AY$50 -> 0.11241272 | AZ67: =AZ18/AZ$50 -> 0.11449978 | BA67: =BA18/BA$50 -> 0.11443924 | BB67: 0.1200488 | BD67: 0.1200488 | BE67: 0.1200488 | BF67: 0.1200488 | BG67: 0.1200488 | BI67: 0.1200488 | BJ67: 0.1200488 | BK67: 0.1200488 | BL67: 0.1200488 | BN67: 0.1200488 | BO67: 0.1200488 | BP67: 0.1200488 | BQ67: 0.1200488
C68: Goodwill | I68: =I19/I$50 -> 0.19439799 | K68: =K19/K$50 -> 0.22086651 | L68: =L19/L$50 -> 0.24206646 | M68: =M19/M$50 -> 0.26798459 | N68: =N19/N$50 -> 0.24018457 | P68: =P19/P$50 -> 0.22269246 | Q68: =Q19/Q$50 -> 0.13654922 | R68: =R19/R$50 -> 0.13877466 | S68: =S19/S$50 -> 0.13879363 | U68: =U19/U$50 -> 0.13613177 | V68: =V19/V$50 -> 0.13396754 | W68: =W19/W$50 -> 0.13648042 | X68: =X19/X$50 -> 0.1383624 | Z68: =Z19/Z$50 -> 0.13962282 | AA68: =AA19/AA$50 -> 0.14030866 | AB68: =AB19/AB$50 -> 0.13326718 | AC68: =AC19/AC$50 -> 0.1302239 | AE68: =AE19/AE$50 -> 0.1270774 | AF68: =AF19/AF$50 -> 0.12108243 | AG68: =AG19/AG$50 -> 0.11886696 | AH68: =AH19/AH$50 -> 0.11889225 | AJ68: =AJ19/AJ$50 -> 0.11843723 | AK68: =AK19/AK$50 -> 0.12004533 | AL68: =AL19/AL$50 -> 0.12023682 | AM68: =AM19/AM$50 -> 0.1191163 | AO68: =AO19/AO$50 -> 0.11834539 | AP68: =AP19/AP$50 -> 0.11832138 | AQ68: =AQ19/AQ$50 -> 0.12160419 | AR68: =AR19/AR$50 -> 0.12297255 | AT68: =AT19/AT$50 -> 0.12532254 | AU68: =AU19/AU$50 -> 0.12883285 | AV68: =AV19/AV$50 -> 0.13103664 | AW68: =AW19/AW$50 -> 0.13132444 | AY68: =AY19/AY$50 -> 0.13341093 | AZ68: =AZ19/AZ$50 -> 0.046727665 | BA68: =BA19/BA$50 -> 0.046033438 | BB68: 0.13326718 | BD68: 0.13326718 | BE68: 0.13326718 | BF68: 0.13326718 | BG68: 0.13326718 | BI68: 0.13326718 | BJ68: 0.13326718 | BK68: 0.13326718 | BL68: 0.13326718 | BN68: 0.13326718 | BO68: 0.13326718 | BP68: 0.13326718 | BQ68: 0.13326718
C69: Intangible Assets, net | I69: =I20/I$50 -> 0.041432416 | K69: =K20/K$50 -> 0.0512239 | L69: =L20/L$50 -> 0.056116033 | M69: =M20/M$50 -> 0.061734118 | N69: =N20/N$50 -> 0.053278286 | P69: =P20/P$50 -> 0.048076995 | Q69: =Q20/Q$50 -> 0.031996506 | R69: =R20/R$50 -> 0.031636906 | S69: =S20/S$50 -> 0.030845651 | U69: =U20/U$50 -> 0.029473993 | V69: =V20/V$50 -> 0.028237734 | W69: =W20/W$50 -> 0.027922156 | X69: =X20/X$50 -> 0.027238729 | Z69: =Z20/Z$50 -> 0.026600196 | AA69: =AA20/AA$50 -> 0.025519844 | AB69: =AB20/AB$50 -> 0.023538843 | AC69: =AC20/AC$50 -> 0.022316809 | AE69: =AE20/AE$50 -> 0.021572742 | AF69: =AF20/AF$50 -> 0.020359853 | AG69: =AG20/AG$50 -> 0.019795718 | AH69: =AH20/AH$50 -> 0.019620069 | AJ69: =AJ20/AJ$50 -> 0.019365604 | AK69: =AK20/AK$50 -> 0.019446734 | AL69: =AL20/AL$50 -> 0.019295859 | AM69: =AM20/AM$50 -> 0.018935632 | AO69: =AO20/AO$50 -> 0.018633847 | AP69: =AP20/AP$50 -> 0.01845107 | AQ69: =AQ20/AQ$50 -> 0.01877882 | AR69: =AR20/AR$50 -> 0.018803887 | AT69: =AT20/AT$50 -> 0.018973424 | AU69: =AU20/AU$50 -> 0.019309974 | AV69: =AV20/AV$50 -> 0.01944183 | AW69: =AW20/AW$50 -> 0.019285638 | AY69: =AY20/AY$50 -> 0.019390225 | AZ69: =AZ20/AZ$50 -> 0.019165488 | BA69: =BA20/BA$50 -> 0.018681933 | BB69: 0.023538843 | BD69: 0.023538843 | BE69: 0.023538843 | BF69: 0.023538843 | BG69: 0.023538843 | BI69: 0.023538843 | BJ69: 0.023538843 | BK69: 0.023538843 | BL69: 0.023538843 | BN69: 0.023538843 | BO69: 0.023538843 | BP69: 0.023538843 | BQ69: 0.023538843
C70: Other assets | I70: =I21/I$50 -> 0.0041075766 | K70: =K21/K$50 -> 0.0053040865 | L70: =L21/L$50 -> 0.00734455 | M70: =M21/M$50 -> 0.0065012722 | N70: =N21/N$50 -> 0.0050598482 | P70: =P21/P$50 -> 0.0044947605 | Q70: =Q21/Q$50 -> 0.0083875522 | R70: =R21/R$50 -> 0.0097591629 | S70: =S21/S$50 -> 0.020848499 | U70: =U21/U$50 -> 0.020727528 | V70: =V21/V$50 -> 0.01911736 | W70: =W21/W$50 -> 0.019271561 | X70: =X21/X$50 -> 0.018108223 | Z70: =Z21/Z$50 -> 0.017727745 | AA70: =AA21/AA$50 -> 0.018152396 | AB70: =AB21/AB$50 -> 0.013200833 | AC70: =AC21/AC$50 -> 0.019566107 | AE70: =AE21/AE$50 -> 0.018796618 | AF70: =AF21/AF$50 -> 0.017557807 | AG70: =AG21/AG$50 -> 0.016384982 | AH70: =AH21/AH$50 -> 0.041078376 | AJ70: =AJ21/AJ$50 -> 0.040214594 | AK70: =AK21/AK$50 -> 0.044844167 | AL70: =AL21/AL$50 -> 0.041067544 | AM70: =AM21/AM$50 -> 0.009210548 | AO70: =AO21/AO$50 -> 0.0090734582 | AP70: =AP21/AP$50 -> 0.0082775577 | AQ70: =AQ21/AQ$50 -> 0.008483312 | AR70: =AR21/AR$50 -> 0.010042025 | AT70: =AT21/AT$50 -> 0.010470645 | AU70: =AU21/AU$50 -> 0.0110489 | AV70: =AV21/AV$50 -> 0.011195342 | AW70: =AW21/AW$50 -> 0.011341601 | AY70: =AY21/AY$50 -> 0.020935951 | AZ70: =AZ21/AZ$50 -> 0.021159938 | BA70: =BA21/BA$50 -> 0.020407321 | BB70: 0.013200833 | BD70: 0.013200833 | BE70: 0.013200833 | BF70: 0.013200833 | BG70: 0.013200833 | BI70: 0.013200833 | BJ70: 0.013200833 | BK70: 0.013200833 | BL70: 0.013200833 | BN70: 0.013200833 | BO70: 0.013200833 | BP70: 0.013200833 | BQ70: 0.013200833
C75: Current maturities of long-term debt | I75: =I26/I$50 -> 0.0066685213 | K75: =K26/K$50 -> 0.0048202632 | L75: =L26/L$50 -> 0.011353439 | M75: =M26/M$50 -> 0.022445896 | N75: =N26/N$50 -> 0.016133984 | P75: =P26/P$50 -> 0.015177541 | Q75: =Q26/Q$50 -> 0.015563106 | R75: =R26/R$50 -> 0.015523222 | S75: =S26/S$50 -> 0.016468558 | U75: =U26/U$50 -> 0.016062063 | V75: =V26/V$50 -> 0.025386047 | W75: =W26/W$50 -> 0.02572938 | X75: =X26/X$50 -> 0.027458574 | Z75: =Z26/Z$50 -> 0.029711862 | AA75: =AA26/AA$50 -> 0.016364858 | AB75: =AB26/AB$50 -> 0.014900029 | AC75: =AC26/AC$50 -> 0.018095817 | AE75: =AE26/AE$50 -> 0.01902883 | AF75: =AF26/AF$50 -> 0.017820874 | AG75: =AG26/AG$50 -> 0.017453351 | AH75: =AH26/AH$50 -> 0.018070827 | AJ75: =AJ26/AJ$50 -> 0.020239399 | AK75: =AK26/AK$50 -> 0.024676963 | AL75: =AL26/AL$50 -> 0.022381701 | AM75: =AM26/AM$50 -> 0.017488537 | AO75: =AO26/AO$50 -> 0.005583013 | AP75: =AP26/AP$50 -> 0.0061350525 | AQ75: =AQ26/AQ$50 -> 0.0064337309 | AR75: =AR26/AR$50 -> 0.006463455 | AT75: =AT26/AT$50 -> 0.005819405 | AU75: =AU26/AU$50 -> 0.0061894189 | AV75: =AV26/AV$50 -> 0.0046144583 | AW75: =AW26/AW$50 -> 0.0037639219 | AY75: =AY26/AY$50 -> 0.0027185904 | AZ75: =AZ26/AZ$50 -> 0.0032832344 | BA75: =BA26/BA$50 -> 0.0024373983 | BB75: 0.014900029 | BD75: 0.014900029 | BE75: 0.014900029 | BF75: 0.014900029 | BG75: 0.014900029 | BI75: 0.014900029 | BJ75: 0.014900029 | BK75: 0.014900029 | BL75: 0.014900029 | BN75: 0.014900029 | BO75: 0.014900029 | BP75: 0.014900029 | BQ75: 0.014900029
C76: Accounts payable, including retainage | I76: =I27/I$50 -> 0.20428231 | K76: =K27/K$50 -> 0.20263584 | L76: =L27/L$50 -> 0.22073511 | M76: =M27/M$50 -> 0.23309581 | N76: =N27/N$50 -> 0.21142572 | P76: =P27/P$50 -> 0.17050366 | Q76: =Q27/Q$50 -> 0.1658128 | R76: =R27/R$50 -> 0.18256103 | S76: =S27/S$50 -> 0.16939752 | U76: =U27/U$50 -> 0.16840142 | V76: =V27/V$50 -> 0.17854138 | W76: =W27/W$50 -> 0.1902193 | X76: =X27/X$50 -> 0.18158155 | Z76: =Z27/Z$50 -> 0.19131039 | AA76: =AA27/AA$50 -> 0.20377597 | AB76: =AB27/AB$50 -> 0.19674203 | AC76: =AC27/AC$50 -> 0.17767567 | AE76: =AE27/AE$50 -> 0.17425521 | AF76: =AF27/AF$50 -> 0.19936587 | AG76: =AG27/AG$50 -> 0.20018555 | AH76: =AH27/AH$50 -> 0.19052319 | AJ76: =AJ27/AJ$50 -> 0.20365042 | AK76: =AK27/AK$50 -> 0.19867668 | AL76: =AL27/AL$50 -> 0.19518203 | AM76: =AM27/AM$50 -> 0.20239708 | AO76: =AO27/AO$50 -> 0.19540566 | AP76: =AP27/AP$50 -> 0.18188621 | AQ76: =AQ27/AQ$50 -> 0.1974073 | AR76: =AR27/AR$50 -> 0.20217552 | AT76: =AT27/AT$50 -> 0.19394225 | AU76: =AU27/AU$50 -> 0.18982962 | AV76: =AV27/AV$50 -> 0.18468809 | AW76: =AW27/AW$50 -> 0.18714865 | AY76: =AY27/AY$50 -> 0.18666529 | AZ76: =AZ27/AZ$50 -> 0.20810727 | BA76: =BA27/BA$50 -> 0.20255561 | BB76: 0.17 | BD76: 0.17 | BE76: 0.17 | BF76: 0.17 | BG76: 0.17 | BI76: 0.17 | BJ76: 0.17 | BK76: 0.17 | BL76: 0.17 | BN76: 0.17 | BO76: 0.17 | BP76: 0.17 | BQ76: 0.17
C77: Billings in Excess of Costs and Estimated Earnings | I77: =I28/I$50 -> 0.062437289 | K77: =K28/K$50 -> 0.079972564 | L77: =L28/L$50 -> 0.10333545 | M77: =M28/M$50 -> 0.11596378 | N77: =N28/N$50 -> 0.10340399 | P77: =P28/P$50 -> 0.09377979 | Q77: =Q28/Q$50 -> 0.086785035 | R77: =R28/R$50 -> 0.08400419 | S77: =S28/S$50 -> 0.073394899 | U77: =U28/U$50 -> 0.070437621 | V77: =V28/V$50 -> 0.071929794 | W77: =W28/W$50 -> 0.067356086 | X77: =X28/X$50 -> 0.064082141 | Z77: =Z28/Z$50 -> 0.063827808 | AA77: =AA28/AA$50 -> 0.071805876 | AB77: =AB28/AB$50 -> 0.074639334 | AC77: =AC28/AC$50 -> 0.071076144 | AE77: =AE28/AE$50 -> 0.062135213 | AF77: =AF28/AF$50 -> 0.05451758 | AG77: =AG28/AG$50 -> 0.058226942 | AH77: =AH28/AH$50 -> 0.058594176 | AJ77: =AJ28/AJ$50 -> 0.057817425 | AK77: =AK28/AK$50 -> 0.066750677 | AL77: =AL28/AL$50 -> 0.068658631 | AM77: =AM28/AM$50 -> 0.067419542 | AO77: =AO28/AO$50 -> 0.058422575 | AP77: =AP28/AP$50 -> 0.068728444 | AQ77: =AQ28/AQ$50 -> 0.08390291 | AR77: =AR28/AR$50 -> 0.096037213 | AT77: =AT28/AT$50 -> 0.10895794 | AU77: =AU28/AU$50 -> 0.12649538 | AV77: =AV28/AV$50 -> 0.14521107 | AW77: =AW28/AW$50 -> 0.12867194 | AY77: =AY28/AY$50 -> 0.13204126 | AZ77: =AZ28/AZ$50 -> 0.14485136 | BA77: =BA28/BA$50 -> 0.18373747 | BB77: 0.06 | BD77: 0.06 | BE77: 0.06 | BF77: 0.06 | BG77: 0.06 | BI77: 0.06 | BJ77: 0.06 | BK77: 0.06 | BL77: 0.06 | BN77: 0.06 | BO77: 0.06 | BP77: 0.06 | BQ77: 0.06
C78: Accrued Expenses | I78: =I29/I$50 -> 0.029222214 | K78: =K29/K$50 -> 0.031817738 | L78: =L29/L$50 -> 0.034015481 | M78: =M29/M$50 -> 0.062041155 | N78: =N29/N$50 -> 0.043932743 | P78: =P29/P$50 -> 0.039768166 | Q78: =Q29/Q$50 -> 0.045486893 | R78: =R29/R$50 -> 0.039273761 | S78: =S29/S$50 -> 0.040940578 | U78: =U29/U$50 -> 0.042045486 | V78: =V29/V$50 -> 0.042385594 | W78: =W29/W$50 -> 0.038574383 | X78: =X29/X$50 -> 0.037842292 | Z78: =Z29/Z$50 -> 0.03600455 | AA78: =AA29/AA$50 -> 0.032804067 | AB78: =AB29/AB$50 -> 0.033108239 | AC78: =AC29/AC$50 -> 0.035575024 | AE78: =AE29/AE$50 -> 0.033217039 | AF78: =AF29/AF$50 -> 0.034399062 | AG78: =AG29/AG$50 -> 0.037745257 | AH78: =AH29/AH$50 -> 0.032317225 | AJ78: =AJ29/AJ$50 -> 0.032587922 | AK78: =AK29/AK$50 -> 0.035120595 | AL78: =AL29/AL$50 -> 0.043026459 | AM78: =AM29/AM$50 -> 0.021975205 | AO78: =AO29/AO$50 -> 0.022747976 | AP78: =AP29/AP$50 -> 0.035627113 | AQ78: =AQ29/AQ$50 -> 0.025855695 | AR78: =AR29/AR$50 -> 0.027839439 | AT78: =AT29/AT$50 -> 0.025350027 | AU78: =AU29/AU$50 -> 0.029568267 | AV78: =AV29/AV$50 -> 0.036309544 | AW78: =AW29/AW$50 -> 0.03913316 | AY78: =AY29/AY$50 -> 0.03964134 | AZ78: =AZ29/AZ$50 -> 0.039981249 | BA78: =BA29/BA$50 -> 0.042270303 | BB78: 0.033108239 | BD78: 0.033108239 | BE78: 0.033108239 | BF78: 0.033108239 | BG78: 0.033108239 | BI78: 0.033108239 | BJ78: 0.033108239 | BK78: 0.033108239 | BL78: 0.033108239 | BN78: 0.033108239 | BO78: 0.033108239 | BP78: 0.033108239 | BQ78: 0.033108239
C81: Long-term debt, less current maturities | I81: =I32/I$50 -> 0.11701326 | K81: =K32/K$50 -> 0.13839278 | L81: =L32/L$50 -> 0.21225532 | M81: =M32/M$50 -> 0.23072433 | N81: =N32/N$50 -> 0.16482663 | P81: =P32/P$50 -> 0.15375245 | Q81: =Q32/Q$50 -> 0.14962659 | R81: =R32/R$50 -> 0.15489467 | S81: =S32/S$50 -> 0.16280791 | U81: =U32/U$50 -> 0.17583653 | V81: =V32/V$50 -> 0.1586169 | W81: =W32/W$50 -> 0.15981324 | X81: =X32/X$50 -> 0.14829374 | Z81: =Z32/Z$50 -> 0.16863869 | AA81: =AA32/AA$50 -> 0.18252746 | AB81: =AB32/AB$50 -> 0.20049579 | AC81: =AC32/AC$50 -> 0.17453541 | AE81: =AE32/AE$50 -> 0.17285433 | AF81: =AF32/AF$50 -> 0.16695792 | AG81: =AG32/AG$50 -> 0.15163672 | AH81: =AH32/AH$50 -> 0.1492806 | AJ81: =AJ32/AJ$50 -> 0.14693415 | AK81: =AK32/AK$50 -> 0.13959282 | AL81: =AL32/AL$50 -> 0.14062467 | AM81: =AM32/AM$50 -> 0.13716132 | AO81: =AO32/AO$50 -> 0.15236884 | AP81: =AP32/AP$50 -> 0.16834371 | AQ81: =AQ32/AQ$50 -> 0.17779493 | AR81: =AR32/AR$50 -> 0.14830716 | AT81: =AT32/AT$50 -> 0.16926274 | AU81: =AU32/AU$50 -> 0.17497061 | AV81: =AV32/AV$50 -> 0.17487567 | AW81: =AW32/AW$50 -> 0.16718148 | AY81: =AY32/AY$50 -> 0.20221355 | AZ81: =AZ32/AZ$50 -> 0.21451566 | BA81: =BA32/BA$50 -> 0.1852131 | BB81: =+BA81-0.005 -> 0.1802131 | BD81: =BB81 -> 0.1802131 | BE81: =+BD81-0.005 -> 0.1752131 | BF81: =+BE81-0.005 -> 0.1702131 | BG81: =+BF81-0.005 -> 0.1652131 | BI81: =BG81 -> 0.1652131 | BJ81: =+BI81-0.005 -> 0.1602131 | BK81: =+BJ81-0.005 -> 0.1552131 | BL81: =+BK81-0.005 -> 0.1502131 | BN81: =BL81 -> 0.1502131 | BO81: =+BN81-0.005 -> 0.1452131 | BP81: =+BO81-0.005 -> 0.1402131 | BQ81: =+BP81-0.005 -> 0.1352131
C82: Deferred Income Taxes | I82: =I33/I$50 -> 0.024719228 | K82: =K33/K$50 -> 0.026688601 | L82: =L33/L$50 -> 0.029282225 | M82: =M33/M$50 -> 0.028710963 | N82: =N33/N$50 -> 0.026348936 | P82: =P33/P$50 -> 0.026331473 | Q82: =Q33/Q$50 -> 0.014113495 | R82: =R33/R$50 -> 0.014537821 | S82: =S33/S$50 -> 0.026730092 | U82: =U33/U$50 -> 0.02623844 | V82: =V33/V$50 -> 0.025800642 | W82: =W33/W$50 -> 0.026230743 | X82: =X33/X$50 -> 0.027380743 | Z82: =Z33/Z$50 -> 0.027594643 | AA82: =AA33/AA$50 -> 0.027710316 | AB82: =AB33/AB$50 -> 0.026271589 | AC82: =AC33/AC$50 -> 0.033472987 | AE82: =AE33/AE$50 -> 0.032587523 | AF82: =AF33/AF$50 -> 0.031086405 | AG82: =AG33/AG$50 -> 0.030279473 | AH82: =AH33/AH$50 -> 0.055545484 | AJ82: =AJ33/AJ$50 -> 0.055519564 | AK82: =AK33/AK$50 -> 0.060889652 | AL82: =AL33/AL$50 -> 0.058331936 | AM82: =AM33/AM$50 -> 0.026675058 | AO82: =AO33/AO$50 -> 0.026423321 | AP82: =AP33/AP$50 -> 0.026554687 | AQ82: =AQ33/AQ$50 -> 0.027508248 | AR82: =AR33/AR$50 -> 0.022808336 | AT82: =AT33/AT$50 -> 0.022871236 | AU82: =AU33/AU$50 -> 0.023406376 | AV82: =AV33/AV$50 -> 0.023885606 | AW82: =AW33/AW$50 -> 0.023687768 | AY82: =AY33/AY$50 -> 0.024199126 | AZ82: =AZ33/AZ$50 -> 0.012812222 | BA82: =BA33/BA$50 -> 0.013083457 | BB82: 0.026271589 | BD82: 0.026271589 | BE82: 0.026271589 | BF82: 0.026271589 | BG82: 0.026271589 | BI82: 0.026271589 | BJ82: 0.026271589 | BK82: 0.026271589 | BL82: 0.026271589 | BN82: 0.026271589 | BO82: 0.026271589 | BP82: 0.026271589 | BQ82: 0.026271589
C83: Other Long-term Liabilities | I83: =I34/I$50 -> 0.013965948 | K83: =K34/K$50 -> 0.015469122 | L83: =L34/L$50 -> 0.016827174 | M83: =M34/M$50 -> 0.028262872 | N83: =N34/N$50 -> 0.029490757 | P83: =P34/P$50 -> 0.027698339 | Q83: =Q34/Q$50 -> 0.029933358 | R83: =R34/R$50 -> 0.028345346 | S83: =S34/S$50 -> 0.033806878 | U83: =U34/U$50 -> 0.03194497 | V83: =V34/V$50 -> 0.031811792 | W83: =W34/W$50 -> 0.034955551 | X83: =X34/X$50 -> 0.028224918 | Z83: =Z34/Z$50 -> 0.02866884 | AA83: =AA34/AA$50 -> 0.029371697 | AB83: =AB34/AB$50 -> 0.022123264 | AC83: =AC34/AC$50 -> 0.025553897 | AE83: =AE34/AE$50 -> 0.024656455 | AF83: =AF34/AF$50 -> 0.023447113 | AG83: =AG34/AG$50 -> 0.023346857 | AH83: =AH34/AH$50 -> 0.028587705 | AJ83: =AJ34/AJ$50 -> 0.028087354 | AK83: =AK34/AK$50 -> 0.02890703 | AL83: =AL34/AL$50 -> 0.026095439 | AM83: =AM34/AM$50 -> 0.032989379 | AO83: =AO34/AO$50 -> 0.032322526 | AP83: =AP34/AP$50 -> 0.031513616 | AQ83: =AQ34/AQ$50 -> 0.032334533 | AR83: =AR34/AR$50 -> 0.034361541 | AT83: =AT34/AT$50 -> 0.035605161 | AU83: =AU34/AU$50 -> 0.032100852 | AV83: =AV34/AV$50 -> 0.03335621 | AW83: =AW34/AW$50 -> 0.034040518 | AY83: =AY34/AY$50 -> 0.042189121 | AZ83: =AZ34/AZ$50 -> 0.042466111 | BA83: =BA34/BA$50 -> 0.041954353 | BB83: 0.022123264 | BD83: 0.022123264 | BE83: 0.022123264 | BF83: 0.022123264 | BG83: 0.022123264 | BI83: 0.022123264 | BJ83: 0.022123264 | BK83: 0.022123264 | BL83: 0.022123264 | BN83: 0.022123264 | BO83: 0.022123264 | BP83: 0.022123264 | BQ83: 0.022123264
C84: Contingencies and Commitments | I84: =I35/I$50 -> 0 | K84: =K35/K$50 -> 0 | L84: =L35/L$50 -> 0 | M84: =M35/M$50 -> 0 | N84: =N35/N$50 -> 0 | P84: =P35/P$50 -> 0 | Q84: =Q35/Q$50 -> 0 | R84: =R35/R$50 -> 0 | S84: =S35/S$50 -> 0 | U84: =U35/U$50 -> 0 | V84: =V35/V$50 -> 0 | W84: =W35/W$50 -> 0 | X84: =X35/X$50 -> 0 | Z84: =Z35/Z$50 -> 0 | AA84: =AA35/AA$50 -> 0 | AB84: =AB35/AB$50 -> 0 | AC84: =AC35/AC$50 -> 0 | AE84: =AE35/AE$50 -> 0 | AF84: =AF35/AF$50 -> 0 | AG84: =AG35/AG$50 -> 0 | AH84: =AH35/AH$50 -> 0 | AJ84: =AJ35/AJ$50 -> 0 | AK84: =AK35/AK$50 -> 0 | AL84: =AL35/AL$50 -> 0 | AM84: =AM35/AM$50 -> 0 | AO84: =AO35/AO$50 -> 0 | AP84: =AP35/AP$50 -> 0 | AQ84: =AQ35/AQ$50 -> 0 | AR84: =AR35/AR$50 -> 0 | AT84: =AT35/AT$50 -> 0 | AU84: =AU35/AU$50 -> 0 | AV84: =AV35/AV$50 -> 0 | AW84: =AW35/AW$50 -> 0 | AY84: =AY35/AY$50 -> 0 | AZ84: =AZ35/AZ$50 -> 0 | BA84: =BA35/BA$50 -> 0 | BB84: 0 | BD84: 0 | BE84: 0 | BF84: 0 | BG84: 0 | BI84: 0 | BJ84: 0 | BK84: 0 | BL84: 0 | BN84: 0 | BO84: 0 | BP84: 0 | BQ84: 0
AB90: 40268 | AC90: =+HLOOKUP(AB90,$F$2:$AW$54,53,FALSE) -> 0
AB91: =+EOMONTH(AB90,3) -> 40359 | AC91: =+HLOOKUP(AB91,$F$2:$AW$54,53,FALSE) -> 0
AB92: =+EOMONTH(AB91,3) -> 40451 | AC92: =+HLOOKUP(AB92,$F$2:$AW$54,53,FALSE) -> 0
AB93: =+EOMONTH(AB92,3) -> 40543 | AC93: =+HLOOKUP(AB93,$F$2:$AW$54,53,FALSE) -> 25.906796
AB94: =+EOMONTH(AB93,3) -> 40633 | AC94: =+HLOOKUP(AB94,$F$2:$AW$54,53,FALSE) -> 38.798167
AB95: =+EOMONTH(AB94,3) -> 40724 | AC95: =+HLOOKUP(AB95,$F$2:$AW$54,53,FALSE) -> 50.001149
AB96: =+EOMONTH(AB95,3) -> 40816 | AC96: =+HLOOKUP(AB96,$F$2:$AW$54,53,FALSE) -> 60.537887
AB97: =+EOMONTH(AB96,3) -> 40908 | AC97: =+HLOOKUP(AB97,$F$2:$AW$54,53,FALSE) -> 48.057442
AB98: =+EOMONTH(AB97,3) -> 40999 | AC98: =+HLOOKUP(AB98,$F$2:$AW$54,53,FALSE) -> 45.460464
AB99: =+EOMONTH(AB98,3) -> 41090 | AC99: =+HLOOKUP(AB99,$F$2:$AW$54,53,FALSE) -> 44.178883
AB100: =+EOMONTH(AB99,3) -> 41182 | AC100: =+HLOOKUP(AB100,$F$2:$AW$54,53,FALSE) -> 44.301164
AB101: =+EOMONTH(AB100,3) -> 41274 | AC101: =+HLOOKUP(AB101,$F$2:$AW$54,53,FALSE) -> 46.886163
AB102: =+EOMONTH(AB101,3) -> 41364 | AC102: =+HLOOKUP(AB102,$F$2:$AW$54,53,FALSE) -> 54.476524
... AB113: =+EOMONTH(AB112,3) -> 42369 | AC113: =+HLOOKUP(AB113,$F$2:$AW$54,53,FALSE) -> 39.771614
AB114: =+EOMONTH(AB113,3) -> 42460 | AC114: =+HLOOKUP(AB114,$F$2:$AW$54,53,FALSE) -> 45.05844 | AD114: =+AC114-AC113 -> 5.2868252
AB115: =+EOMONTH(AB114,3) -> 42551 | AC115: =+HLOOKUP(AB115,$F$2:$AW$54,53,FALSE) -> 57.758604
AB116: =+EOMONTH(AB115,3) -> 42643 | AC116: =+HLOOKUP(AB116,$F$2:$AW$54,53,FALSE) -> 57.692222
AB117: =+EOMONTH(AB116,3) -> 42735 | AC117: =+HLOOKUP(AB117,$F$2:$AW$54,53,FALSE) -> 55.686536
AB118: =+EOMONTH(AB117,3) -> 42825 | AC118: =+HLOOKUP(AB118,$F$2:$AW$54,53,FALSE) -> 57.865228
AB119: =+EOMONTH(AB118,3) -> 42916 | AC119: =+HLOOKUP(AB119,$F$2:$AW$54,53,FALSE) -> 69.325987
AB120: =+EOMONTH(AB119,3) -> 43008 | AC120: =+HLOOKUP(AB120,$F$2:$AW$54,53,FALSE) -> 68.906498
AB121: =+EOMONTH(AB120,3) -> 43100 | AC121: =+HLOOKUP(AB121,$F$2:$AW$54,53,FALSE) -> 64.43921

Sheet CF
A1: Tutor Perini | Y1: =+Y44 -> 0 | AD1: =+AD44 -> 0
A2: Cash Flow | F2: 40268 | G2: =+EOMONTH(B2,12) -> 397 | H2: =+EOMONTH(C2,12) -> 397 | I2: =+EOMONTH(D2,12) -> 397 | K2: =+EOMONTH(F2,12) -> 40633 | L2: =+EOMONTH(G2,12) -> 762 | M2: =+EOMONTH(H2,12) -> 762 | N2: =+EOMONTH(I2,12) -> 762 | Y2: =+Y6-T6 -> 352.696 | AE2: =+EOMONTH(Z2,12) -> 397 | AF2: =+EOMONTH(AA2,12) -> 397 | AG2: =+EOMONTH(AB2,12) -> 397 | AH2: =+EOMONTH(AC2,12) -> 397 | AI2: =AI3 -> 2015
A3: TPC | F3: 2010 | J3: =+F3 -> 2010 | K3: 2011 | O3: =+K3 -> 2011 | P3: 2012 | T3: =+P3 -> 2012 | U3: 2013 | Y3: =+U3 -> 2013 | Z3: 2014 | AD3: =+Z3 -> 2014 | AE3: 2015 | AI3: =+AE3 -> 2015 | AJ3: 2016 | AN3: 2016 | AO3: 2017 | AS3: 2017 | AT3: 2018 | AX3: =+AT3 -> 2018 | AY3: 2019E | BC3: =+AY3 -> 2019E | BD3: 2020E | BH3: =+BD3 -> 2020E | BI3: 2021E | BM3: =+BI3 -> 2021E | BN3: 2022E | BR3: =+BN3 -> 2022E
A4: Fiscal YE December | F4: 1Q | G4: 2Q | H4: 3Q | I4: 4Q | J4: Year | K4: 1Q | L4: 2Q | M4: 3Q | N4: 4Q | O4: Year | P4: 1Q | Q4: 2Q | R4: 3Q | S4: 4Q | T4: Year | U4: 1Q | V4: 2QE | W4: 3QE | X4: 4QE | Y4: Year | Z4: 1Q | AA4: 2Q | AB4: 3Q | AC4: 4Q | AD4: Year | AE4: 1Q | AF4: 2Q | AG4: 3Q | AH4: 4Q | AI4: Year | AJ4: 1Q | AK4: 2Q | AL4: 3Q | AM4: 4Q | AN4: Year | AO4: 1Q | AP4: 2Q | AQ4: 3Q | AR4: 4Q | AS4: Year | AT4: 1Q | AU4: 2Q | AV4: 3Q | AW4: 4Q | AX4: Year | AY4: 1Q | AZ4: 2Q | BA4: 3Q | BB4: 4QE | BC4: Year | BD4: 1QE | BE4: 2QE | BF4: 3QE | BG4: 4QE | BH4: Year | BI4: 1QE | BJ4: 2QE | BK4: 3QE | BL4: 4QE | BM4: Year | BN4: 1QE | BO4: 2QE | BP4: 3QE | BQ4: 4QE | BR4: Year
A5: CASH FLOWS FROM OPERATING ACTIVITIES
A6: Consolidated net income | F6: =IS!F48 -> 62.909 | G6: =IS!G48 -> 75.786 | H6: =IS!H48 -> 71.643 | I6: =J6-H6-G6-F6 -> -106.838 | J6: 103.5 | K6: =IS!K48 -> 50.879 | L6: =IS!L48 -> 69.869 | M6: =IS!M48 -> 93.796 | N6: =O6-M6-L6-K6 -> -128.396 | O6: 86.148 | P6: =IS!P48 -> 67.993 | Q6: =IS!Q48 -> -283.762 | R6: =IS!R48 -> 103.378 | S6: =T6-R6-Q6-P6 -> -153.009 | T6: -265.4 | U6: 14.8 | V6: =IS!V48 -> 81.959 | W6: =IS!W48 -> 86.522 | X6: =Y6-W6-V6-U6 -> -95.985 | Y6: 87.296 | Z6: =IS!Z48 -> 15.939 | AA6: =IS!AA48 -> 28.545 | AB6: =IS!AB48 -> 102.813 | AC6: =IS!AC48 -> 27.722 | AD6: =SUM(Z6:AC6) -> 175.019 | AE6: =IS!AE48 -> 5.126 | AF6: =IS!AF48 -> 11.777 | AG6: =36.58-AF6-AE6 -> 19.677 | AH6: =IS!AH48 -> 8.712 | AI6: 45.292 | AJ6: 15.4 | AK6: =36.76-AJ6 -> 21.36 | AL6: =65.561-AK6-AJ6 -> 28.801 | AM6: =IS!AM48 -> 30.26 | AN6: 95.822 | AO6: 13.764 | AP6: =46.397-AO6 -> 32.633 | AQ6: =71.697-SUM(AO6:AP6) -> 25.3 | AR6: =AS6-SUM(AO6:AQ6) -> 82.847 | AS6: 154.544 | AT6: -10.942 | AU6: =16.954-AT6 -> 27.896 | AV6: =42.39-SUM(AT6:AU6) -> 25.436 | AW6: =AX6-SUM(AT6:AV6) -> 55.391 | AX6: 97.781 | AY6: 4.722 | AZ6: =-310.717-AY6 -> -315.439 | BA6: =-283.996-SUM(AY6:AZ6) -> 26.721 | BB6: =IS!BB48 -> 30.34995 | BC6: =SUM(AY6:BB6) -> -253.64605 | BD6: =IS!BD48 -> 37.634185 | BE6: =IS!BE48 -> 58.748027 | BF6: =IS!BF48 -> 59.276335 | BG6: =IS!BG48 -> 59.674089 | BH6: =SUM(BD6:BG6) -> 215.33264 | BI6: =IS!BI48 -> 36.176038 | BJ6: =IS!BJ48 -> 59.445525 | BK6: =IS!BK48 -> 58.742979 | BL6: =IS!BL48 -> 60.968095 | BM6: =SUM(BI6:BL6) -> 215.33264 | BN6: =IS!BN48 -> 34.825386 | BO6: =IS!BO48 -> 58.718826 | BP6: =IS!BP48 -> 59.864109 | BQ6: =IS!BQ48 -> 61.924317 | BR6: =SUM(BN6:BQ6) -> 215.33264
A7: Adjustments to reconcile consolidated net income to net cash provided by operating activities | Q7: 376.574 | R7: 0 | S7: 0 | T7: 376.574 | AR7: =AS7-SUM(AO7:AQ7) -> 0 | AW7: =AX7-SUM(AT7:AV7) -> 0
B8: Depreciation and amortization | F8: 8.03 | G8: =15.889-F8 -> 7.859 | H8: =23.328-G8-F8 -> 7.439 | I8: =J8-H8-G8-F8 -> 8.006 | J8: =21.38+9.954 -> 31.334 | K8: 8.043 | L8: =16.985-K8 -> 8.942 | M8: =29.594-L8-K8 -> 12.609 | N8: =O8-M8-L8-K8 -> 18.037 | O8: =32.193+15.438 -> 47.631 | P8: 15.79 | Q8: =32.106-P8 -> 16.316 | R8: =46.676-Q8-P8 -> 14.57 | S8: =T8-R8-Q8-P8 -> 14.781 | T8: =40.583+20.874 -> 61.457 | U8: 13.793 | V8: =27.566-U8 -> 13.773 | W8: =41.766-V8-U8 -> 14.2 | X8: =Y8-W8-V8-U8 -> 17.644 | Y8: =43.383+16.027 -> 59.41 | Z8: 14.659 | AA8: =30.078-Z8 -> 15.419 | AB8: =42.165-AA8-Z8 -> 12.087 | AC8: =AD8-AB8-AA8-Z8 -> 13.807 | AD8: 55.972 | AE8: 10.594 | AF8: =21.434-AE8 -> 10.84 | AG8: =32.528-AF8-AE8 -> 11.094 | AH8: =AI8-AG8-AF8-AE8 -> 11.201 | AI8: 43.729 | AJ8: 14.496 | AK8: =29.956-AJ8 -> 15.46 | AL8: =47.295-AK8-AJ8 -> 17.339 | AM8: =AN8-AL8-AK8-AJ8 -> 20.007 | AN8: =63.759+3.543 -> 67.302 | AO8: =20.11+0.886 -> 20.996 | AP8: =28.987-AO8+1.771 -> 9.762 | AQ8: =37.806+2.657-SUM(AO8:AP8) -> 9.705 | AR8: =AS8-SUM(AO8:AQ8) -> 11.467 | AS8: =3.543+48.387 -> 51.93 | AT8: =9.301+0.886 -> 10.187 | AU8: =21.164-AT8 -> 10.977 | AV8: =33.581-SUM(AT8:AU8) -> 12.417 | AW8: =AX8-SUM(AT8:AV8) -> 13.686 | AX8: 47.267 | AY8: 13.717 | AZ8: =28.314-AY8 -> 14.597 | BA8: =44.541-SUM(AY8:AZ8) -> 16.227 | BB8: =+BC8-BA8-AZ8-AY8 -> 20.459 | BC8: 65 | BD8: =BH8/4 -> 16.25 | BE8: =+(BH8-BD8)/3 -> 16.25 | BF8: =+(BH8-BE8-BD8)/2 -> 16.25 | BG8: =+BH8-BF8-BE8-BD8 -> 16.25 | BH8: 65 | BI8: =BM8/4 -> 16.25 | BJ8: =+(BM8-BI8)/3 -> 16.25 | BK8: =+(BM8-BJ8-BI8)/2 -> 16.25 | BL8: =+BM8-BK8-BJ8-BI8 -> 16.25 | BM8: 65 | BN8: =BR8/4 -> 16.25 | BO8: =+(BR8-BN8)/3 -> 16.25 | BP8: =+(BR8-BO8-BN8)/2 -> 16.25 | BQ8: =+BR8-BP8-BO8-BN8 -> 16.25 | BR8: 65
B9: Stock-based compensation expense | F9: 3.909 | G9: =7.477-F9 -> 3.568 | H9: =10.168-G9-F9 -> 2.691 | I9: =J9-H9-G9-F9 -> 2.584 | J9: 12.752 | K9: 3.615 | L9: =7.085-K9 -> 3.47 | M9: =6.82-L9-K9 -> -0.265 | N9: =O9-M9-L9-K9 -> 1.998 | O9: 8.818 | P9: 3.419 | Q9: =5.074-P9 -> 1.655 | R9: =7.424-Q9-P9 -> 2.35 | S9: =T9-R9-Q9-P9 -> 2.046 | T9: 9.47 | U9: 3.078 | V9: =4.624-U9 -> 1.546 | W9: =6.597-V9-U9 -> 1.973 | X9: =Y9-W9-V9-U9 -> 0.026 | Y9: 6.623 | Z9: 5.429 | AA9: =9.92-Z9 -> 4.491 | AB9: =14.376-AA9-Z9 -> 4.456 | AC9: =AD9-AB9-AA9-Z9 -> 3.452 | AD9: =18.615-0.787 -> 17.828 | AE9: 9.159 | AF9: =13.324-AE9 -> 4.165 | AG9: =17.064-AF9-AE9-0.186 -> 3.554 | AH9: =AI9-AG9-AF9-AE9 -> -7.401 | AI9: 9.477 | AJ9: 3.647 | AK9: =6.959-AJ9 -> 3.312 | AL9: =10.109-AK9-AJ9 -> 3.15 | AM9: =AN9-AL9-AK9-AJ9 -> 3.314 | AN9: 13.423 | AO9: 4.306 | AP9: =10.42-AO9 -> 6.114 | AQ9: =16.057-SUM(AO9:AP9) -> 5.637 | AR9: =AS9-SUM(AO9:AQ9) -> 5.117 | AS9: 21.174 | AT9: 6.081 | AU9: =12.063-AT9 -> 5.982 | AV9: =17.779-SUM(AT9:AU9) -> 5.716 | AW9: =AX9-SUM(AT9:AV9) -> 5.003 | AX9: 22.782 | AY9: 5.506 | AZ9: =10.078-AY9 -> 4.572 | BA9: =14.331-SUM(AY9:AZ9) -> 4.253 | BB9: =$AI$9/4 -> 2.36925 | BC9: 10 | BD9: =$AI$9/4 -> 2.36925 | BE9: =$AI$9/4 -> 2.36925 | BF9: =$AI$9/4 -> 2.36925 | BG9: =$AI$9/4 -> 2.36925 | BH9: 10 | BI9: =$AI$9/4 -> 2.36925 | BJ9: =$AI$9/4 -> 2.36925 | BK9: =$AI$9/4 -> 2.36925 | BL9: =$AI$9/4 -> 2.36925 | BM9: 10 | BN9: =$AI$9/4 -> 2.36925 | BO9: =$AI$9/4 -> 2.36925 | BP9: =$AI$9/4 -> 2.36925 | BQ9: =$AI$9/4 -> 2.36925 | BR9: 10
B10: Adjustments of investments to fair value | F10: -0.057 | G10: =0.182-F10 -> 0.239 | H10: =0.025-G10-F10 -> -0.157 | I10: =J10-H10-G10-F10 -> 5.717 | J10: 5.742 | L10: 0 | M10: 0 | N10: =O10-M10-L10-K10 -> 4.75 | O10: 4.75 | P10: 0 | Q10: 0 | R10: 0 | S10: =T10-R10-Q10-P10 -> 0 | T10: 0 | U10: 0 | V10: 0 | W10: 0 | X10: =Y10-W10-V10-U10 -> 0 | Y10: 0 | Z10: 0 | AA10: 0 | AB10: 0 | AC10: =AD10-AB10-AA10-Z10 -> 0 | AD10: 0 | AE10: 0 | AH10: =AI10-AG10-AF10-AE10 -> 0 | AI10: 0 | AJ10: 0 | AM10: =AN10-AL10-AK10-AJ10 -> 0 | AN10: 0 | AO10: 0 | AP10: =0-AO10 -> 0 | AQ10: 0 | AR10: =AS10-SUM(AO10:AQ10) -> 0 | AW10: =AX10-SUM(AT10:AV10) -> 0 | BC10: =SUM(AY10:BB10) -> 0 | BH10: =SUM(BD10:BG10) -> 0 | BM10: =SUM(BI10:BL10) -> 0 | BR10: =SUM(BN10:BQ10) -> 0
B11: Deferred income taxes | F11: -1.137 | G11: =-2.124-F11 -> -0.987 | H11: =-3.059-G11-F11 -> -0.935 | I11: =J11-H11-G11-F11 -> -0.767 | J11: -3.826 | K11: -0.411 | L11: =-1.275-K11 -> -0.864 | M11: =0.412-L11-K11 -> 1.687 | N11: =O11-M11-L11-K11 -> 10.442 | O11: 10.854 | P11: 5.693 | Q11: =-42.421-P11 -> -48.114 | R11: =-42.008-Q11-P11 -> 0.413 | S11: =T11-R11-Q11-P11 -> 16.402 | T11: -25.606 | U11: 0.348 | V11: =0.5-U11 -> 0.152 | W11: =-0.503-V11-U11 -> -1.003 | X11: =Y11-W11-V11-U11 -> 9.512 | Y11: 9.009 | Z11: 0.045 | AA11: =-0.064-Z11 -> -0.109 | AB11: =15.988-AA11-Z11 -> 16.052 | AC11: =AD11-AB11-AA11-Z11 -> 5.472 | AD11: 21.46 | AE11: 0 | AF11: -0.177 | AG11: =6.366-AF11-AE11 -> 6.543 | AH11: =AI11-AG11-AF11-AE11 -> 15.848 | AI11: 22.214 | AJ11: -0.155 | AK11: =-0.371-AJ11 -> -0.216 | AL11: =-8.636-AK11-AJ11 -> -8.265 | AM11: =AN11-AL11-AK11-AJ11 -> -1.533 | AN11: -10.169 | AO11: -0.526 | AP11: =-0.001-AO11 -> 0.525 | AQ11: =0.642-SUM(AO11:AP11) -> 0.643 | AR11: =AS11-SUM(AO11:AQ11) -> -23.738 | AS11: -23.096 | AT11: 0.186 | AU11: =0.116-AT11 -> -0.07 | AV11: =0.233-SUM(AT11:AU11) -> 0.117 | AW11: =AX11-SUM(AT11:AV11) -> -0.682 | AX11: -0.449 | AY11: 0.142 | AZ11: =-50.321-AY11 -> -50.463 | BA11: =-48.318-SUM(AY11:AZ11) -> 2.003 | BC11: =SUM(AY11:BB11) -> -48.318 | BH11: =SUM(BD11:BG11) -> 0 | BM11: =SUM(BI11:BL11) -> 0 | BR11: =SUM(BN11:BQ11) -> 0
B12: Loss on sale of equipment | F12: 0 | G12: =0.434-F12 -> 0.434 | H12: =0.35-G12-F12 -> -0.084 | I12: =J12-H12-G12-F12 -> 0.924 | J12: 1.274 | K12: 0.596 | L12: =0.146-K12 -> -0.45 | M12: =-0.896-L12-K12 -> -1.042 | N12: =O12-M12-L12-K12 -> 0.18 | O12: -0.716 | P12: -0.079 | Q12: =0.53-P12 -> 0.609 | R12: =0.509-Q12-P12 -> -0.021 | S12: =T12-R12-Q12-P12 -> -0.193 | T12: 0.316 | U12: -0.076 | V12: =-0.18-U12 -> -0.104 | W12: =-0.22-V12-U12 -> -0.04 | X12: =Y12-W12-V12-U12 -> 0.269 | Y12: 0.049 | Z12: 0.427 | AA12: =0.427-Z12 -> 0 | AB12: =0.926-AA12-Z12 -> 0.499 | AC12: =AD12-AB12-AA12-Z12 -> -0.125 | AD12: 0.801 | AE12: -0.276 | AF12: =-0.313-AE12 -> -0.037 | AG12: =-0.821-AF12-AE12 -> -0.508 | AH12: =AI12-AG12-AF12-AE12 -> -2.088 | AI12: -2.909 | AJ12: 0.285 | AK12: =0.204-AJ12 -> -0.081 | AL12: =0.3-AK12-AJ12 -> 0.096 | AM12: =AN12-AL12-AK12-AJ12 -> -0.3 | AN12: 0 | AO12: -0.131 | AP12: =-0.349-AO12 -> -0.218 | AQ12: =-0.376-SUM(AO12:AP12) -> -0.027 | AR12: =AS12-SUM(AO12:AQ12) -> 1.507 | AS12: 1.131 | AT12: 1.471 | AU12: =1.474-AT12 -> 0.003 | AV12: =0.823-SUM(AT12:AU12) -> -0.651 | AW12: =AX12-SUM(AT12:AV12) -> -0.421 | AX12: 0.402 | AY12: -0.107 | AZ12: =-1.479-AY12 -> -1.372 | BA12: =-1.799-SUM(AY12:AZ12) -> -0.32 | BC12: =SUM(AY12:BB12) -> -1.799 | BH12: =SUM(BD12:BG12) -> 0 | BM12: =SUM(BI12:BL12) -> 0 | BR12: =SUM(BN12:BQ12) -> 0
B13: Other Long-term Liabilities | F13: -4.089 | G13: =-3.077-F13 -> 1.012 | H13: =-3.677-G13-F13 -> -0.6 | I13: =J13-H13-G13-F13 -> -0.946 | J13: -4.623 | K13: -0.243 | L13: =-3.323-K13 -> -3.08 | M13: =-6.823-L13-K13 -> -3.5 | N13: =O13-M13-L13-K13 -> -5.9 | O13: -12.723 | P13: 0.214 | Q13: =-4.006-P13 -> -4.22 | R13: =-8.399-Q13-P13 -> -4.393 | S13: =T13-R13-Q13-P13 -> 3.295 | T13: -5.104 | U13: 1.851 | V13: =8.449-U13 -> 6.598 | W13: =17.877-V13-U13 -> 9.428 | X13: =Y13-W13-V13-U13 -> 5.23 | Y13: 23.107 | Z13: 3.494 | AA13: =5.559-Z13 -> 2.065 | AB13: =1.256-AA13-Z13 -> -4.303 | AC13: =AD13-AB13-AA13-Z13 -> 1.818 | AD13: 3.074 | AE13: 2.381 | AF13: =0.042-AE13 -> -2.339 | AG13: =-1.379-AF13-AE13 -> -1.421 | AH13: =AI13-AG13-AF13-AE13 -> 30.291 | AI13: 28.912 | AJ13: -4.061 | AK13: =3.348-3.811+1.2-AJ13 -> 4.798 | AL13: =-8.555-AK13-AJ13 -> -9.292 | AM13: =AN13-AL13-AK13-AJ13 -> 36.765 | AN13: 28.21 | AO13: 3.836 | AP13: =-2.801-AO13 -> -6.637 | AQ13: =-2.876-SUM(AO13:AP13) -> -0.075 | AR13: =AS13-SUM(AO13:AQ13) -> 6.532 | AS13: 3.656 | AT13: 1.139 | AU13: =-5.276-AT13 -> -6.415 | AV13: =-2.606-SUM(AT13:AU13) -> 2.67 | AW13: =AX13-SUM(AT13:AV13) -> 0.599 | AX13: -2.007 | AY13: 2.177 | AZ13: =3.209-AY13 -> 1.032 | BA13: =3.979-SUM(AY13:AZ13) -> 0.77 | BC13: =SUM(AY13:BB13) -> 3.979 | BH13: =SUM(BD13:BG13) -> 0 | BM13: =SUM(BI13:BL13) -> 0 | BR13: =SUM(BN13:BQ13) -> 0
B14: Other, net | F14: 0 | G14: 0 | H14: 0 | I14: 0 | J14: 0 | K14: =0.064-0.018 -> 0.046 | L14: =-1.399-0.018-K14 -> -1.463 | M14: =-3.251-L14-K14-4-0.018 -> -5.852 | N14: =O14-M14-L14-K14 -> 6.603 | O14: =-0.601-0.047-0.018 -> -0.666 | P14: =1.031+2.699 -> 3.73 | Q14: =2.699+0.517-P14 -> -0.514 | R14: =-0.446+2.699+0.264-Q14-P14 -> -0.699 | S14: =T14-R14-Q14-P14 -> 0.594 | T14: =0.148+2.699+0.264 -> 3.111 | U14: =+-0.197 -> -0.197 | V14: =-0.358-0.111-U14 -> -0.272 | W14: =0.444-0.356-V14-U14 -> 0.557 | X14: =Y14-W14-V14-U14 -> -4.955 | Y14: =-3.719-1.148 -> -4.867 | Z14: -0.427 | AA14: =1.562+1.786-Z14 -> 3.775 | AB14: =1.324+1.786-0.656-AA14-Z14 -> -0.894 | AC14: =AD14-AB14-AA14-Z14 -> 2.605 | AD14: =3.273+1.786 -> 5.059 | AE14: -2.227 | AF14: =-3.259-0.162-AE14 -> -1.194 | AG14: =-5.692-AF14-AE14 -> -2.271 | AH14: =AI14-AG14-AF14-AE14 -> 1.826 | AI14: =-0.186-3.68 -> -3.866 | AJ14: 1.399 | AK14: =0-AJ14 -> -1.399 | AL14: =-0.01+7.124-0.353-AK14-AJ14 -> 6.761 | AM14: =AN14-AL14-AK14-AJ14 -> 2.517 | AN14: =-0.269+10.968+0.453-1.874 -> 9.278 | AO14: =-1.824+0.267 -> -1.557 | AP14: =11.95+1.785-AO14 -> 15.292 | AQ14: =4.785-SUM(AO14:AP14)+14.725 -> 5.775 | AR14: =AS14-SUM(AO14:AQ14) -> -5.085 | AS14: =-3.17+17.595 -> 14.425 | AT14: =-0.18+2.927 -> 2.747 | AU14: =5.012-AT14 -> 2.265 | AV14: =9.152-SUM(AT14:AU14) -> 4.14 | AW14: =AX14-SUM(AT14:AV14) -> 3.318 | AX14: 12.47 | AY14: =0.076+3.174 -> 3.25 | AZ14: =386.901-AY14 -> 383.651 | BA14: =389.775-SUM(AY14:AZ14) -> 2.874 | BC14: =SUM(AY14:BB14) -> 389.775 | BH14: =SUM(BD14:BG14) -> 0 | BM14: =SUM(BI14:BL14) -> 0 | BR14: =SUM(BN14:BQ14) -> 0
B15: Changes in other components of working capital | F15: -87.88 | G15: =-59.755-F15 -> 28.125 | H15: =-147.675-G15-F15 -> -87.92 | I15: =J15-H15-G15-F15 -> 27.794 | J15: =-22.054+7.144-4.69-101.143+11.957-10.791-0.086-0.218 -> -119.881 | K15: -66.229 | L15: =-132.2-K15 -> -65.971 | M15: =-207.854-L15-K15 -> -75.654 | N15: =O15-M15-L15-K15 -> 33.234 | O15: =6.657-80.67+6.631-45.278-25.31-36.65 -> -174.62 | P15: -52.602 | Q15: =-53.314-P15 -> -0.712 | R15: =-104.135-Q15-P15 -> -50.821 | S15: =T15-R15-Q15-P15 -> -118.546 | T15: =50.655-106.604+2.237-89.252-82.521+2.804 -> -222.681 | U15: -118.052 | V15: =-109.338-U15 -> 8.714 | W15: =-130.7-V15-U15 -> -21.362 | X15: =Y15-W15-V15-U15 -> 0.801 | Y15: =-62.991-107.983+25.25+59.169-36.835-6.509 -> -129.899 | Z15: -80.696 | AA15: =-155.187-Z15 -> -74.491 | AB15: =-300.804-AA15-Z15 -> -145.617 | AC15: =AD15-AB15-AA15-Z15 -> 31.996 | AD15: -268.808 | AE15: -27.081 | AF15: =-79.55-AE15 -> -52.469 | AG15: =-63.786-AF15-AE15 -> 15.764 | AH15: =AI15-AG15-AF15-AE15 -> -64.991 | AI15: -128.777 | AJ15: -15.067 | AK15: =-69.669-AJ15 -> -54.602 | AL15: =-18.669-AK15-AJ15 -> 51 | AM15: =AN15-AL15-AK15-AJ15 -> -71.861 | AN15: -90.53 | AO15: -73.533 | AP15: =-132.779-AO15 -> -59.246 | AQ15: =-143.213-SUM(AO15:AP15) -> -10.434 | AR15: =AS15-SUM(AO15:AQ15) -> 82.999 | AS15: -60.214 | AT15: -84.272 | AU15: =-113.887-AT15 -> -29.615 | AV15: =-136.113-SUM(AT15:AU15) -> -22.226 | AW15: =AX15-SUM(AT15:AV15) -> -20.731 | AX15: -156.844 | AY15: -154.192 | AZ15: =-177.471-AY15 -> -23.279 | BA15: =-7.148-SUM(AY15:AZ15) -> 170.323 | BB15: =$AS$15/4 -> -15.0535 | BC15: 100 | BD15: =$AS$15/4 -> -15.0535 | BE15: =$AS$15/4 -> -15.0535 | BF15: =$AS$15/4 -> -15.0535 | BG15: =$AS$15/4 -> -15.0535 | BH15: 100 | BI15: =$AS$15/4 -> -15.0535 | BJ15: =$AS$15/4 -> -15.0535 | BK15: =$AS$15/4 -> -15.0535 | BL15: =$AS$15/4 -> -15.0535 | BM15: 100 | BN15: =$AS$15/4 -> -15.0535 | BO15: =$AS$15/4 -> -15.0535 | BP15: =$AS$15/4 -> -15.0535 | BQ15: =$AS$15/4 -> -15.0535 | BR15: 100
B16: Costs and Estimated Earnings in Excess of Billings | G16: =BS!F10-BS!G10 -> 14.545 | H16: =BS!G10-BS!H10 -> -3.217 | I16: =BS!H10-BS!I10 -> -15.952 | J16: =SUM(F16:I16) -> -4.624 | K16: =BS!I10-BS!K10 -> -33.091 | L16: =BS!K10-BS!L10 -> -42.577 | M16: =BS!L10-BS!M10 -> -159.208 | N16: =BS!M10-BS!N10 -> 15.927 | O16: =SUM(K16:N16) -> -218.949 | P16: =BS!N10-BS!P10 -> -19.201 | Q16: =BS!P10-BS!Q10 -> 2.663 | R16: =BS!Q10-BS!R10 -> -36.726 | S16: =BS!R10-BS!S10 -> -53.34 | T16: =SUM(P16:S16) -> -106.604 | U16: =BS!S10-BS!U10 -> -14.359 | V16: =BS!U10-BS!V10 -> -25.55 | W16: =BS!V10-BS!W10 -> -33.51 | X16: =BS!W10-BS!X10 -> -34.827 | Y16: =SUM(U16:X16) -> -108.246 | Z16: =BS!X10-BS!Z10 -> -125.175 | AA16: =BS!Z10-BS!AA10 -> 37.471 | AB16: =BS!AA10-BS!AB10 -> -59.225 | AC16: =BS!AB10-BS!AC10 -> -6.225 | AD16: =SUM(Z16:AC16) -> -153.154 | AE16: =BS!AC10-BS!AE10 -> -69.108 | AF16: =BS!AE10-BS!AF10 -> -20.97 | AG16: =BS!AF10-BS!AG10 -> -67.329 | AH16: =BS!AG10-BS!AH10 -> -21.366 | AI16: =SUM(AE16:AH16) -> -178.773 | AJ16: =BS!AH10-BS!AJ10 -> 46.819 | AK16: =BS!AJ10-BS!AK10 -> 46.95 | AL16: =BS!AK10-BS!AL10 -> -8.837 | AM16: =BS!AL10-BS!AM10 -> -11.583 | AN16: =SUM(AJ16:AM16) -> 73.349 | AO16: =BS!AM10-BS!AO10 -> -8.934 | AP16: =BS!AO10-BS!AP10 -> -9.874 | AQ16: =BS!AP10-BS!AQ10 -> -51.678 | AR16: =BS!AQ10-BS!AR10 -> -30.446 | AS16: =SUM(AO16:AR16) -> -100.932 | AT16: =BS!AR10-BS!AT10 -> -48.138 | AU16: =BS!AT10-BS!AU10 -> -63.337 | AV16: =BS!AU10-BS!AV10 -> -41.418 | AW16: =BS!AV10-BS!AW10 -> -56.644 | AX16: =SUM(AT16:AW16) -> -209.537 | AY16: =BS!AW10-BS!AY10 -> -26.38 | AZ16: =BS!AY10-BS!AZ10 -> 3.267 | BA16: =BS!AZ10-BS!BA10 -> 6.075 | BB16: =BS!BA10-BS!BB10 -> 602.57269 | BC16: =SUM(AY16:BB16) -> 585.53469 | BD16: =BS!BB10-BS!BD10 -> -19.691315 | BE16: =BS!BD10-BS!BE10 -> -46.892104 | BF16: =BS!BE10-BS!BF10 -> -42.217302 | BG16: =BS!BF10-BS!BG10 -> -26.363047 | BH16: =SUM(BD16:BG16) -> -135.16377 | BI16: =BS!BG10-BS!BI10 -> 3.5898389 | BJ16: =BS!BI10-BS!BJ10 -> -1.2193049 | BK16: =BS!BJ10-BS!BK10 -> 1.4108739 | BL16: =BS!BK10-BS!BL10 -> -3.7814079 | BM16: =SUM(BI16:BL16) -> 0 | BN16: =BS!BL10-BS!BN10 -> 5.4585428 | BO16: =BS!BN10-BS!BO10 -> 1.1846092 | BP16: =BS!BO10-BS!BP10 -> -2.2504803 | BQ16: =BS!BP10-BS!BQ10 -> -4.3926717 | BR16: =SUM(BN16:BQ16) -> 0
B17: Billings in Excess of Costs and Estimated Earnings | G17: =BS!G28-BS!F28 -> 50.64 | H17: =BS!H28-BS!G28 -> -34.891 | I17: =BS!I28-BS!H28 -> -25.322 | J17: =SUM(F17:I17) -> -9.573 | K17: =BS!K28-BS!I28 -> 36.123 | L17: =BS!L28-BS!K28 -> 59.14 | M17: =BS!M28-BS!L28 -> 86.451 | N17: =BS!N28-BS!M28 -> 2.818 | O17: =SUM(K17:N17) -> 184.532 | P17: =BS!P28-BS!N28 -> -7.891 | Q17: =BS!Q28-BS!P28 -> -13.712 | R17: =BS!R28-BS!Q28 -> -17.251 | S17: =BS!S28-BS!R28 -> -43.667 | T17: =SUM(P17:S17) -> -82.521 | U17: =BS!U28-BS!S28 -> -6.496 | V17: =BS!V28-BS!U28 -> 11.126 | W17: =BS!W28-BS!V28 -> -24.13 | X17: =BS!X28-BS!W28 -> -14.675 | Y17: =SUM(U17:X17) -> -34.175 | Z17: =BS!Z28-BS!X28 -> -3.468 | AA17: =BS!AA28-BS!Z28 -> 35.271 | AB17: =BS!AB28-BS!AA28 -> 28.257 | AC17: =BS!AC28-BS!AB28 -> -8.35 | AD17: =SUM(Z17:AC17) -> 51.71 | AE17: =BS!AE28-BS!AC28 -> -33.254 | AF17: =BS!AF28-BS!AE28 -> -22.642 | AG17: =BS!AG28-BS!AF28 -> 23.165 | AH17: =BS!AH28-BS!AG28 -> 1.746 | AI17: =SUM(AE17:AH17) -> -30.985 | AJ17: =BS!AJ28-BS!AH28 -> -2.729 | AK17: =BS!AK28-BS!AJ28 -> 39.708 | AL17: =BS!AL28-BS!AK28 -> 8.765 | AM17: =BS!AM28-BS!AL28 -> -2.943 | AN17: =SUM(AJ17:AM17) -> 42.801 | AO17: =BS!AO28-BS!AM28 -> -42.317 | AP17: =BS!AP28-BS!AO28 -> 51.013 | AQ17: =BS!AQ28-BS!AP28 -> 63.827 | AR17: =BS!AR28-BS!AQ28 -> 53.234 | AS17: =SUM(AO17:AR17) -> 125.757 | AT17: =BS!AT28-BS!AR28 -> 51.747 | AU17: =BS!AU28-BS!AT28 -> 65.776 | AV17: =BS!AV28-BS!AU28 -> 73.895 | AW17: =BS!AW28-BS!AV28 -> -75.097 | AX17: =SUM(AT17:AW17) -> 116.321 | AY17: =BS!AY28-BS!AW28 -> 5.81 | AZ17: =BS!AZ28-BS!AY28 -> 56.924 | BA17: =BS!BA28-BS!AZ28 -> 182.882 | BB17: =BS!BB28-BS!BA28 -> -540.42584 | BC17: =SUM(AY17:BB17) -> -294.80984 | BD17: =BS!BD28-BS!BB28 -> 9.8456573 | BE17: =BS!BE28-BS!BD28 -> 23.446052 | BF17: =BS!BF28-BS!BE28 -> 21.108651 | BG17: =BS!BG28-BS!BF28 -> 13.181523 | BH17: =SUM(BD17:BG17) -> 67.581884 | BI17: =BS!BI28-BS!BG28 -> -1.7949194 | BJ17: =BS!BJ28-BS!BI28 -> 0.60965244 | BK17: =BS!BK28-BS!BJ28 -> -0.70543694 | BL17: =BS!BL28-BS!BK28 -> 1.8907039 | BM17: =SUM(BI17:BL17) -> 0 | BN17: =BS!BN28-BS!BL28 -> -2.7292714 | BO17: =BS!BO28-BS!BN28 -> -0.59230459 | BP17: =BS!BP28-BS!BO28 -> 1.1252401 | BQ17: =BS!BQ28-BS!BP28 -> 2.1963359 | BR17: =SUM(BN17:BQ17) -> 0
A18: Net cash provided by operating activities | F18: =SUM(F6:F15) -> -18.315 | G18: =SUM(G6:G15) -> 116.036 | H18: =SUM(H6:H15) -> -7.923 | I18: =SUM(I6:I15) -> -63.526 | J18: =SUM(J6:J15) -> 26.272 | K18: =SUM(K6:K15) -> -3.704 | L18: =SUM(L6:L15) -> 10.453 | M18: =SUM(M6:M15) -> 21.779 | ... BR18: =SUM(BR6:BR15) -> 390.33264
AJ19: =+AJ17+AJ16 -> 44.09 | AK19: =+AK17+AK16 -> 86.658 | AL19: =+AL17+AL16 -> -0.072 | AM19: =+AM17+AM16 -> -14.526 | AO19: =+AO17+AO16 -> -51.251 | AP19: =+AP17+AP16 -> 41.139 | AQ19: =+AQ17+AQ16 -> 12.149
A20: CASH FLOWS FROM INVESTING ACTIVITIES
B21: Business acquisition related payments | F21: 0 | G21: -6.734 | H21: =-6.734-G21-F21 -> 0 | I21: =J21-H21-G21-F21 -> -30.924 | J21: =-6.734-30.924 -> -37.658 | K21: =-70.62-3 -> -73.62 | L21: =-161.711-3-K21 -> -91.091 | M21: =-337.873-3-L21-K21 -> -176.162 | N21: =O21-M21-L21-K21 -> -4.025 | O21: =-341.898-3 -> -344.898 | P21: -1.188 | Q21: =0-P21 -> 1.188 | R21: =0-Q21-P21 -> 0 | S21: =T21-R21-Q21-P21 -> 0 | T21: 0 | U21: 0 | V21: 0 | W21: 0 | X21: =Y21-W21-V21-U21 -> 0 | Y21: 0 | Z21: 0 | AA21: 0 | AB21: 0 | AC21: 0 | AD21: 0 | AH21: 0 | AI21: 0 | AM21: 0 | AN21: =SUM(AJ21:AM21) -> 0 | AS21: =SUM(AO21:AR21) -> 0 | BC21: =SUM(AY21:BB21) -> 0 | BH21: =SUM(BD21:BG21) -> 0 | BM21: =SUM(BI21:BL21) -> 0 | BR21: =SUM(BN21:BQ21) -> 0
B22: Acquisition of property and equipment | F22: -4.188 | G22: =-8.509-F22 -> -4.321 | H22: =-16.135-G22-F22 -> -7.626 | I22: =J22-H22-G22-F22 -> -9.065 | J22: -25.2 | K22: -8.932 | L22: =-22.171-K22 -> -13.239 | M22: =-39.694-L22-K22 -> -17.523 | N22: =O22-M22-L22-K22 -> -27.053 | O22: -66.747 | P22: -10.649 | Q22: =-21.788-P22 -> -11.139 | R22: =-33.737-Q22-P22 -> -11.949 | S22: =T22-R22-Q22-P22 -> -7.615 | T22: -41.352 | U22: -12.179 | V22: =-28.127-U22 -> -15.948 | W22: =-39.81-V22-U22 -> -11.683 | X22: =Y22-W22-V22-U22 -> -2.55 | Y22: -42.36 | Z22: -8.352 | AA22: =-26.73-Z22 -> -18.378 | AB22: =-37.778-AA22-Z22 -> -11.048 | AC22: =AD22-AB22-AA22-Z22 -> -37.235 | AD22: -75.013 | AE22: -5.691 | AF22: =-29.544-AE22 -> -23.853 | AG22: =-33.365-AF22-AE22 -> -3.821 | AH22: =AI22-AG22-AF22-AE22 -> -2.547 | AI22: -35.912 | AJ22: -4.812 | AK22: =-8.681-AJ22 -> -3.869 | AL22: =-10.273-AK22-AJ22 -> -1.592 | AM22: =AN22-AL22-AK22-AJ22 -> -5.47 | AN22: -15.743 | AO22: -5.672 | AP22: =-8.183-AO22 -> -2.511 | AQ22: =-9.712-SUM(AO22:AP22) -> -1.529 | AR22: =AS22-SUM(AO22:AQ22) -> -20.568 | AS22: -30.28 | AT22: -19.97 | AU22: =-48.303-AT22 -> -28.333 | AV22: =-64.411-SUM(AT22:AU22) -> -16.108 | AW22: =AX22-SUM(AT22:AV22) -> -12.658 | AX22: -77.069 | AY22: -14.412 | AZ22: =-39.346-AY22 -> -24.934 | BA22: =-62.677-SUM(AY22:AZ22) -> -23.331 | BB22: =+BC22-BA22-AZ22-AY22 -> 37.677 | BC22: -25 | BD22: =BH22/4 -> -6.25 | BE22: =+(BH22-BD22)/3 -> -6.25 | BF22: =+(BH22-BE22-BD22)/2 -> -6.25 | BG22: =+BH22-BF22-BE22-BD22 -> -6.25 | BH22: -25 | BI22: =BM22/4 -> -6.25 | BJ22: =+(BM22-BI22)/3 -> -6.25 | BK22: =+(BM22-BJ22-BI22)/2 -> -6.25 | BL22: =+BM22-BK22-BJ22-BI22 -> -6.25 | BM22: -25 | BN22: =BR22/4 -> -6.25 | BO22: =+(BR22-BN22)/3 -> -6.25 | BP22: =+(BR22-BO22-BN22)/2 -> -6.25 | BQ22: =+BR22-BP22-BO22-BN22 -> -6.25 | BR22: -25
B23: Proceeds from sale of PP&E | F23: 0.573 | G23: =0.808-F23 -> 0.235 | H23: =1.856-G23-F23 -> 1.048 | I23: =J23-H23-G23-F23 -> -0.045 | J23: 1.811 | K23: 0.893 | L23: =3.422-K23 -> 2.529 | M23: =6.526-L23-K23 -> 3.104 | N23: =O23-M23-L23-K23 -> 3.523 | O23: 10.049 | P23: 3.968 | Q23: =9.614-P23 -> 5.646 | R23: =11.75-Q23-P23 -> 2.136 | S23: =T23-R23-Q23-P23 -> 0.009 | T23: 11.759 | U23: 0.239 | V23: =2.359-U23 -> 2.12 | W23: =2.551-V23-U23 -> 0.192 | X23: =Y23-W23-V23-U23 -> 0.112 | Y23: 2.663 | Z23: 1.417 | AA23: =1.906-Z23 -> 0.489 | AB23: =5.153-AA23-Z23 -> 3.247 | AC23: =AD23-AB23-AA23-Z23 -> 0.182 | AD23: 5.335 | AE23: 0.798 | AF23: =1.122-AE23 -> 0.324 | AG23: =2.22-AF23-AE23 -> 1.098 | AH23: =AI23-AG23-AF23-AE23 -> 2.76 | AI23: 4.98 | AJ23: 0.939 | AK23: =1.092-AJ23 -> 0.153 | AL23: =1.139-AK23-AJ23 -> 0.047 | AM23: =AN23-AL23-AK23-AJ23 -> 0.76 | AN23: 1.899 | AO23: 0.259 | AP23: =1.336-AO23 -> 1.077 | AQ23: =1.44-SUM(AO23:AP23) -> 0.104 | AR23: =AS23-SUM(AO23:AQ23) -> 1.304 | AS23: 2.744 | AT23: 3.303 | AU23: =4.12-AT23 -> 0.817 | AV23: =5.462-SUM(AT23:AU23) -> 1.342 | AW23: =AX23-SUM(AT23:AV23) -> 0.925 | AX23: 6.387 | AY23: 0.201 | AZ23: =3.629-AY23 -> 3.428 | BA23: =4.3-SUM(AY23:AZ23) -> 0.671 | BC23: =SUM(AY23:BB23) -> 4.3 | BH23: =SUM(BD23:BG23) -> 0 | BM23: =SUM(BI23:BL23) -> 0 | BR23: =SUM(BN23:BQ23) -> 0
B24: Proceeds from sale of available-for-sale securities | F24: 0.375 | G24: =0.525-F24 -> 0.15 | H24: =6.918-G24-F24 -> 6.393 | I24: =J24-H24-G24-F24 -> 0.148 | J24: 7.066 | K24: 0 | L24: =7.388-K24 -> 7.388 | M24: =7.388-L24-K24 -> 0 | N24: =O24-M24-L24-K24 -> 22.803 | O24: 30.191 | P24: -0.535 | Q24: =16.553-P24 -> 17.088 | R24: =16.553-Q24-P24 -> 0 | S24: =T24-R24-Q24-P24 -> -0.535 | T24: =-0.535+16.553 -> 16.018 | U24: 0 | V24: 0 | W24: 0 | X24: =Y24-W24-V24-U24 -> 0 | Y24: 0 | Z24: 0 | AA24: =44.497-Z24 -> 44.497 | AB24: =44.497-AA24-Z24 -> 0 | AC24: =AD24-AB24-AA24-Z24 -> 0 | AD24: 44.497 | AE24: 0 | AF24: 0 | AG24: 0 | AH24: =AI24-AG24-AF24-AE24 -> 0 | AI24: 0 | AM24: =AN24-AL24-AK24-AJ24 -> 0 | AN24: 0 | AO24: 0 | AP24: =0-AO24 -> 0 | AQ24: 0 | AR24: =AS24-SUM(AO24:AQ24) -> 0 | AT24: 3.007 | AU24: =7.982-AT24 -> 4.975 | AV24: =-13.841-SUM(AT24:AU24) -> -21.823 | AW24: =AX24-SUM(AT24:AV24) -> 35.163 | AX24: 21.322 | AY24: 3.324 | AZ24: =8.131-AY24 -> 4.807 | BA24: =11.078-SUM(AY24:AZ24) -> 2.947 | BC24: =SUM(AY24:BB24) -> 11.078 | BH24: =SUM(BD24:BG24) -> 0 | BM24: =SUM(BI24:BL24) -> 0 | BR24: =SUM(BN24:BQ24) -> 0
B25: Increase in Restricted Cash | F25: -23.523 | G25: =-23.523-F25 -> 0 | H25: =-23.541-G25-F25 -> -0.018 | I25: =J25-H25-G25-F25 -> -0.009 | J25: -23.55 | K25: -0.008 | L25: =-3.822-K25 -> -3.814 | M25: =-7.196-L25-K25 -> -3.374 | N25: =O25-M25-L25-K25 -> 0.38 | O25: -6.816 | P25: -0.013 | Q25: =-3.247-P25 -> -3.234 | R25: =-3.263-Q25-P25 -> -0.016 | S25: =T25-R25-Q25-P25 -> -0.017 | T25: -3.28 | U25: -6.514 | V25: =-8.302-U25 -> -1.788 | W25: =-8.749-V25-U25 -> -0.447 | X25: =Y25-W25-V25-U25 -> 4.872 | Y25: -3.877 | Z25: -0.675 | AA25: =-0.033-Z25 -> 0.642 | AB25: =-4.394-AA25-Z25 -> -4.361 | AC25: =AD25-AB25-AA25-Z25 -> 2.618 | AD25: -1.776 | AE25: 0.277 | AF25: =4.877-AE25 -> 4.6 | AG25: =5.798-AF25-AE25 -> 0.921 | AH25: =AI25-AG25-AF25-AE25 -> -7.281 | AI25: -1.483 | AJ25: -3.305 | AK25: =+-3.599-AJ25 -> -0.294 | AL25: =-2.872-AK25-AJ25 -> 0.727 | AM25: =AN25-AL25-AK25-AJ25 -> -1.779 | AN25: -4.651 | AO25: -9.654 | AP25: =-1.547-AO25 -> 8.107 | AQ25: =-48.657-SUM(AO25:AP25) -> -47.11 | AR25: =AS25-SUM(AO25:AQ25) -> 94.381 | AS25: 45.724 | AT25: -3.288 | AU25: =-8.549-AT25 -> -5.261 | AV25: =14.302-SUM(AT25:AU25) -> 22.851 | AW25: =AX25-SUM(AT25:AV25) -> -35.15 | AX25: -20.848 | AY25: -8.357 | AZ25: =-13.66-AY25 -> -5.303 | BA25: =-18.79-SUM(AY25:AZ25) -> -5.13 | BC25: =SUM(AY25:BB25) -> -18.79 | BH25: =SUM(BD25:BG25) -> 0 | BM25: =SUM(BI25:BL25) -> 0 | BR25: =SUM(BN25:BQ25) -> 0
B26: Investment in other activities | F26: 0.285 | G26: =-0.146-F26 -> -0.431 | H26: =0.053-G26-F26 -> 0.199 | I26: =J26-H26-G26-F26 -> -0.053 | J26: 0 | L26: -2.725 | M26: =0-L26-K26 -> 2.725 | N26: =O26-M26-L26-K26 -> 0 | O26: 0 | P26: 16.553 | Q26: =-0.535-P26 -> -17.088 | R26: =-0.535-Q26-P26 -> 0 | S26: =T26-R26-Q26-P26 -> 0.535 | T26: 0 | U26: 0 | V26: 0 | W26: 0 | X26: =Y26-W26-V26-U26 -> 0 | Y26: 0 | Z26: 0 | AA26: 0 | AB26: 0 | AC26: =AD26-AB26-AA26-Z26 -> 0 | AD26: 0 | AH26: =AI26-AG26-AF26-AE26 -> 0 | AI26: 0 | AM26: =AN26-AL26-AK26-AJ26 -> 0 | AN26: 0 | AP26: =-9.297-AO26 -> -9.297 | AQ26: =33.08-SUM(AO26:AP26) -> 42.377 | AR26: =AS26-SUM(AO26:AQ26) -> -92.677 | AS26: =-54.504-6.463+1.37 -> -59.597 | AT26: 0 | AU26: 0 | AV26: 0 | AW26: =AX26-SUM(AT26:AV26) -> 0 | AX26: 0 | AY26: 0 | AZ26: 0 | BA26: 0 | BC26: =SUM(AY26:BB26) -> 0 | BH26: =SUM(BD26:BG26) -> 0 | BM26: =SUM(BI26:BL26) -> 0 | BR26: =SUM(BN26:BQ26) -> 0
A27: Net cash used in investing activities | F27: =SUM(F21:F26) -> -26.478 | G27: =SUM(G21:G26) -> -11.101 | H27: =SUM(H21:H26) -> -0.004 | I27: =SUM(I21:I26) -> -39.948 | J27: =SUM(J21:J26) -> -77.531 | K27: =SUM(K21:K26) -> -81.667 | L27: =SUM(L21:L26) -> -100.952 | M27: =SUM(M21:M26) -> -191.23 | ... BR27: =SUM(BR21:BR26) -> -25
A29: CASH FLOWS FROM FINANCING ACTIVITIES
B30: Proceeds from LT Debt | F30: 4.664 | G30: =8.724-F30 -> 4.06 | H30: =8.724-G30-F30 -> 0 | I30: =J30-H30-G30-F30 -> 295.853 | J30: =297.774+6.803 -> 304.577 | K30: 58.175 | L30: =258.175-K30 -> 200 | M30: =567.782-L30-K30 -> 309.607 | N30: =O30-M30-L30-K30 -> 133.971 | O30: 701.753 | P30: 98.5 | Q30: =306.582-P30 -> 208.082 | R30: =511.579-Q30-P30 -> 204.997 | S30: =T30-R30-Q30-P30 -> 176.846 | T30: 688.425 | U30: 293.014 | V30: =421.55-U30 -> 128.536 | W30: =571.285-V30-U30 -> 149.735 | X30: =Y30-W30-V30-U30 -> 81.995 | Y30: 653.28 | Z30: 178.038 | AA30: =717.484-Z30 -> 539.446 | AB30: =993.01-AA30-Z30 -> 275.526 | AC30: =AD30-AB30-AA30-Z30 -> 163.729 | AD30: 1156.739 | AE30: 280.2 | AF30: =473.49-AE30 -> 193.29 | AG30: =672.719-AF30-AE30 -> 199.229 | AH30: =AI30-AG30-AF30-AE30 -> 340.486 | AI30: 1013.205 | AJ30: 299.785 | AK30: =200+711.092-AJ30 -> 611.307 | AL30: =1003.092-AK30-AJ30+200 -> 292 | AM30: =AN30-AL30-AK30-AJ30 -> 350.803 | AN30: =1353.895+200 -> 1553.895 | AO30: 313.977 | AP30: =1276.457-AO30 -> 962.48 | AQ30: =1991.457-SUM(AO30:AP30) -> 715 | AR30: =AS30-SUM(AO30:AQ30) -> 169.927 | AS30: 2161.384 | AT30: 665 | AU30: =1246.677-AT30 -> 581.677 | AV30: =1502.177-SUM(AT30:AU30) -> 255.5 | AW30: =AX30-SUM(AT30:AV30) -> 250.983 | AX30: 1753.16 | AY30: 394 | AZ30: =716.139-AY30 -> 322.139 | BA30: =649.139-SUM(AY30:AZ30) -> -67 | BB30: =BS!BB32-BS!BA32 -> 10.74719 | BC30: =SUM(AY30:BB30) -> 659.88619 | BD30: =BS!BD32-BS!BB32 -> 29.571941 | BE30: =BS!BE32-BS!BD32 -> 44.448773 | BF30: =BS!BF32-BS!BE32 -> 33.910161 | BG30: =BS!BG32-BS!BF32 -> 8.5642963 | BH30: =SUM(BD30:BG30) -> 116.49517 | BI30: =BS!BI32-BS!BG32 -> -4.9424034 | BJ30: =BS!BJ32-BS!BI32 -> -27.052688 | BK30: =BS!BK32-BS!BJ32 -> -30.556282 | BL30: =BS!BL32-BS!BK32 -> -23.939136 | BM30: =SUM(BI30:BL30) -> -86.49051 | BN30: =BS!BN32-BS!BL32 -> -6.8328721 | BO30: =BS!BO32-BS!BN32 -> -30.036237 | BP30: =BS!BP32-BS!BO32 -> -25.923815 | BQ30: =BS!BQ32-BS!BP32 -> -23.697586 | BR30: =SUM(BN30:BQ30) -> -86.49051
B31: Repayment of LT Debt | F31: -7.91 | G31: =-16.181-F31 -> -8.271 | H31: =-28.803-G31-F31 -> -12.622 | I31: =J31-H31-G31-F31 -> -6.957 | J31: -35.76 | K31: -33.119 | L31: =-36.621-K31 -> -3.502 | M31: =-263.059-L31-K31 -> -226.438 | N31: =O31-M31-L31-K31 -> -291.91 | O31: -554.969 | P31: -95.107 | Q31: =-290.917-P31 -> -195.81 | R31: =-485.543-Q31-P31 -> -194.626 | S31: =T31-R31-Q31-P31 -> -140.579 | T31: -626.122 | U31: -225.684 | V31: =-374.987-U31 -> -149.303 | W31: =-536.227-V31-U31 -> -161.24 | X31: =Y31-W31-V31-U31 -> -140.568 | Y31: -676.795 | Z31: -113.551 | AA31: =-649.282-Z31 -> -535.731 | AB31: =-808.611-AA31-Z31 -> -159.329 | AC31: =AD31-AB31-AA31-Z31 -> -217.738 | AD31: -1026.349 | AE31: -262.112 | AF31: =-446.239-AE31 -> -184.127 | AG31: =-706.113-AF31-AE31 -> -259.874 | AH31: =AI31-AG31-AF31-AE31 -> -348.258 | AI31: -1054.371 | AJ31: -287.484 | AK31: =-871.654-AJ31 -> -584.17 | AL31: =-1174.679-AK31-AJ31 -> -303.025 | AM31: =AN31-AL31-AK31-AJ31 -> -388.005 | AN31: -1562.684 | AO31: -296.485 | AP31: =-1171.954-AO31 -> -875.469 | AQ31: =-1866.072-SUM(AO31:AP31) -> -694.118 | AR31: =AS31-SUM(AO31:AQ31) -> -328.996 | AS31: -2195.068 | AT31: -586.559 | AU31: =-1165.283-AT31 -> -578.724 | AV31: =-1444.76-SUM(AT31:AU31) -> -279.477 | AW31: =AX31-SUM(AT31:AV31) -> -293.554 | AX31: -1738.314 | AY31: -259.691 | AZ31: =-527.159-AY31 -> -267.468 | BA31: =-583.039-SUM(AY31:AZ31) -> -55.88 | BB31: 0 | BC31: =SUM(AY31:BB31) -> -583.039 | BD31: 0 | BE31: 0 | BF31: 0 | BG31: 0 | BH31: =SUM(BD31:BG31) -> 0 | BI31: 0 | BJ31: 0 | BK31: 0 | BL31: 0 | BM31: =SUM(BI31:BL31) -> 0 | BN31: 0 | BO31: 0 | BP31: 0 | BQ31: 0 | BR31: =SUM(BN31:BQ31) -> 0
B32: Common Stock repurchased | F32: 0 | G32: -11.2 | H32: =-39.391-G32-F32 -> -28.191 | I32: =J32-H32-G32-F32 -> 0 | J32: -39.391 | K32: 0 | L32: 0 | M32: 0 | N32: =O32-M32-L32-K32 -> 0 | O32: 0 | P32: 0 | Q32: 0 | R32: 0 | S32: =T32-R32-Q32-P32 -> 0 | T32: 0 | U32: 0 | V32: 0 | W32: 0 | X32: =Y32-W32-V32-U32 -> 0 | Y32: 0 | Z32: 0 | AA32: 0 | AB32: 0 | AC32: =AD32-AB32-AA32-Z32 -> 0 | AD32: 0 | AG32: 0 | AH32: =AI32-AG32-AF32-AE32 -> 0 | AI32: 0 | AM32: =AN32-AL32-AK32-AJ32 -> 0 | AN32: 0 | AO32: 0 | AR32: =AS32-SUM(AO32:AQ32) -> 0 | AW32: =AX32-SUM(AT32:AV32) -> 0 | AX32: 0 | BC32: =SUM(AY32:BB32) -> 0 | BH32: =SUM(BD32:BG32) -> 0 | BM32: =SUM(BI32:BL32) -> 0 | BR32: =SUM(BN32:BQ32) -> 0
B33: Issuance of Common stock and effect of cashless exercise | F33: -0.203 | G33: =0.063-F33 -> 0.266 | H33: =-0.325-G33-F33 -> -0.388 | I33: =J33-H33-G33-F33 -> 0 | J33: -0.325 | K33: 0 | L33: =0.256-K33 -> 0.256 | M33: =-0.044-L33-K33 -> -0.3 | N33: =O33-M33-L33-K33 -> -0.147 | O33: -0.191 | P33: -0.307 | Q33: =-0.307-P33 -> 0 | R33: =-0.307-Q33-P33 -> 0 | S33: =T33-R33-Q33-P33 -> -0.001 | T33: -0.308 | U33: -0.159 | V33: =0.341-U33 -> 0.5 | W33: =-0.786-V33-U33 -> -1.127 | X33: =Y33-W33-V33-U33 -> -1.096 | Y33: -1.882 | Z33: -1.575 | AA33: =-1.531-Z33 -> 0.044 | AB33: =-1.692-AA33-Z33 -> -0.161 | AC33: =AD33-AB33-AA33-Z33 -> -0.079 | AD33: -1.771 | AE33: -0.773 | AF33: =-0.776-AE33 -> -0.003 | AG33: =0.186-AF33-AE33 -> 0.962 | AH33: =AI33-AG33-AF33-AE33 -> -0.994 | AI33: -0.808 | AM33: =AN33-AL33-AK33-AJ33 -> -0.584 | AN33: -0.584 | AO33: -10.809 | AP33: =-10.809-AO33 -> 0 | AQ33: =-11.147-SUM(AO33:AP33) -> -0.338 | AR33: =AS33-SUM(AO33:AQ33) -> -0.622 | AS33: -11.769 | AT33: -2.308 | AU33: =-2.458-AT33 -> -0.15 | AV33: =-2.671-SUM(AT33:AU33) -> -0.213 | AW33: =AX33-SUM(AT33:AV33) -> 0 | AX33: -2.671 | AY33: -2.364 | AZ33: =-2.363-AY33 -> 0.001 | BA33: =0-SUM(AY33:AZ33) -> 2.363 | BC33: =SUM(AY33:BB33) -> 0 | BH33: =SUM(BD33:BG33) -> 0 | BM33: =SUM(BI33:BL33) -> 0 | BR33: =SUM(BN33:BQ33) -> 0
B34: Deferred Debt costs | F34: -1.164 | G34: =-1.608-F34 -> -0.444 | H34: =-1.905-G34-F34 -> -0.297 | I34: =J34-H34-G34-F34 -> 1.905 | J34: 0 | K34: 0 | L34: 0 | M34: 0 | N34: =O34-M34-L34-K34 -> 0 | O34: 0 | P34: 0 | Q34: 0 | R34: 0 | S34: =T34-R34-Q34-P34 -> 0 | T34: 0 | U34: 0 | V34: 0 | W34: 0 | X34: =Y34-W34-V34-U34 -> 0 | Y34: 0 | Z34: 0 | AA34: 0 | AB34: 0 | AC34: =AD34-AB34-AA34-Z34 -> -3.681 | AD34: -3.681 | AG34: 0 | AH34: =AI34-AG34-AF34-AE34 -> 0 | AI34: 0 | AM34: =AN34-AL34-AK34-AJ34 -> 0 | AN34: 0 | AO34: 0 | AP34: =-13.309-AO34 -> -13.309 | AQ34: =-15.268-SUM(AO34:AP34) -> -1.959 | AR34: =AS34-SUM(AO34:AQ34) -> 0.002 | AS34: -15.266 | AT34: 0 | AW34: =AX34-SUM(AT34:AV34) -> 0 | AX34: 0 | BC34: =SUM(AY34:BB34) -> 0 | BH34: =SUM(BD34:BG34) -> 0 | BM34: =SUM(BI34:BL34) -> 0 | BR34: =SUM(BN34:BQ34) -> 0
B35: Other,net | F35: 0 | G35: 0 | H35: 0 | I35: =J35-H35-G35-F35 -> -54.773 | J35: =-47.09-7.901+0.218 -> -54.773 | K35: =0.018-0.025 -> -0.007 | L35: =-2.233+0.018-K35 -> -2.208 | M35: =-4.989+0.018-L35-K35 -> -2.756 | N35: =O35-M35-L35-K35 -> -0.015 | O35: =-5.004+0.018 -> -4.986 | P35: -0.01 | Q35: =-0.01-P35-2.932 -> -2.932 | R35: =-1.993-10.09-Q35-P35 -> -9.141 | S35: =T35-R35-Q35-P35 -> -1.378 | T35: =-1.999-11.462 -> -13.461 | U35: 0 | V35: =0.358-U35 -> 0.358 | W35: =-17.716+0.356-V35-U35 -> -17.718 | X35: =Y35-W35-V35-U35 -> -12.53 | Y35: =-31.038+1.148 -> -29.89 | Z35: -1.031 | AA35: =-1.26-3.681-Z35 -> -3.91 | AB35: =-26.43+0.656-3.681-AA35-Z35 -> -24.514 | AC35: =AD35-AB35-AA35-Z35 -> 3.812 | AD35: =+-26.43+0.787 -> -25.643 | AF35: =0.162-AE35 -> 0.162 | AG35: =-0.808-AF35-AE35 -> -0.97 | AH35: =AI35-AG35-AF35-AE35 -> 0.994 | AI35: 0.186 | AJ35: -5.937 | AK35: =-14.656-AJ35 -> -8.719 | AL35: =-0.423-14.868+0.01-AK35-AJ35 -> -0.625 | AM35: =AN35-AL35-AK35-AJ35 -> 0.464 | AN35: =0.269+-15.086 -> -14.817 | AO35: -0.057 | AP35: =1.25-2.5-AO35 -> -1.193 | AQ35: =+AQ36-SUM(AQ30:AQ34) -> -2.2026825e-13 | AR35: =AS35-SUM(AO35:AQ35) -> -13.407 | AS35: =-17.499+2.842 -> -14.657 | AT35: -5 | AU35: =-27.451-AT35 -> -22.451 | AV35: =-37.451-SUM(AT35:AU35) -> -10 | AW35: =AX35-SUM(AT35:AV35) -> -3.703 | AX35: -41.154 | AY35: =2.798-4 -> -1.202 | AZ35: =0.875-AY35 -> 2.077 | BA35: =-17.848-SUM(AY35:AZ35) -> -18.723 | BC35: =SUM(AY35:BB35) -> -17.848 | BH35: =SUM(BD35:BG35) -> 0 | BM35: =SUM(BI35:BL35) -> 0 | BR35: =SUM(BN35:BQ35) -> 0
A36: Net cash used in financing activities | F36: =SUM(F30:F35) -> -4.613 | G36: =SUM(G30:G35) -> -15.589 | H36: =SUM(H30:H35) -> -41.498 | I36: =SUM(I30:I35) -> 236.028 | J36: =SUM(J30:J35) -> 174.328 | K36: =SUM(K30:K35) -> 25.049 | L36: =SUM(L30:L35) -> 194.546 | M36: =SUM(M30:M35) -> 80.113 | ... AP36: =SUM(AP30:AP35) -> 72.509 | AQ36: =97.72-SUM(AO36:AP36) -> 18.585 | AR36: =SUM(AR30:AR35) -> -173.096 | AS36: =SUM(AS30:AS35) -> -75.376 | AT36: =SUM(AT30:AT35) -> 71.133 | AU36: =SUM(AU30:AU35) -> -19.648 | AV36: =SUM(AV30:AV35) -> -34.19 | AW36: =SUM(AW30:AW35) -> -46.274 | AX36: =SUM(AX30:AX35) -> -28.979 | AY36: =SUM(AY30:AY35) -> 130.743 | ... BR36: =SUM(BR30:BR35) -> -86.49051
A38: Net increase (decrease) in cash and cash equivalents | F38: =F36+F27+F18 -> -49.406 | G38: =G36+G27+G18 -> 89.346 | H38: =H36+H27+H18 -> -49.425 | I38: =I36+I27+I18 -> 132.554 | J38: =J18+J27+J36 -> 123.069 | K38: =K36+K27+K18 -> -60.322 | L38: =L36+L27+L18 -> 104.047 | M38: =M36+M27+M18 -> -89.338 | N38: =N36+N27+N18 -> -221.525 | O38: =O18+O27+O36 -> -267.138 | P38: =P36+P27+P18 -> 55.37 | Q38: =Q36+Q27+Q18 -> 59.633 | R38: =R36+R27+R18 -> 56.178 | S38: =S36+S27+S18 -> -207.365 | T38: =T18+T27+T36 -> -36.184 | U38: =U36+U27+U18 -> -35.738 | V38: =V36+V27+V18 -> 76.841 | W38: =W36+W27+W18 -> 47.987 | X38: =X36+X27+X18 -> -137.223 | Y38: =Y18+Y27+Y36 -> -48.133 | Z38: =Z36+Z27+Z18 -> 13.141 | AA38: =AA36+AA27+AA18 -> 6.794 | AB38: =AB36+AB27+AB18 -> 64.453 | AC38: =AC36+AC27+AC18 -> -1.645 | AD38: =AD18+AD27+AD36 -> 82.743 | AE38: =AE36+AE27+AE18 -> 10.375 | AF38: =AF36+AF27+AF18 -> -39.041 | AG38: =AG36+AG27+AG18 -> -10.023 | AH38: =AH36+AH27+AH18 -> -21.442 | AI38: =AI18+AI27+AI36 -> -60.131 | AJ38: =AJ36+AJ27+AJ18 -> 15.13 | AK38: =AK36+AK27+AK18 -> 3.04 | AL38: =AL36+AL27+AL18 -> 77.122 | AM38: =AM36+AM27+AM18 -> -24.642 | AN38: =AN18+AN27+AN36 -> 70.651 | AO38: =AO36+AO27+AO18 -> -41.286 | AP38: =AP36+AP27+AP18 -> 68.11 | AQ38: =AQ36+AQ27+AQ18 -> 48.951 | AR38: =AR36+AR27+AR18 -> -29.01 | AS38: 46.765 | AT38: =AT36+AT27+AT18 -> -19.218 | AU38: =AU36+AU27+AU18 -> -36.427 | AV38: =AV36+AV27+AV18 -> -20.309 | AW38: =AW36+AW27+AW18 -> -1.831 | AX38: =AX18+AX27+AX36 -> -77.785 | AY38: =AY36+AY27+AY18 -> -13.286 | AZ38: =AZ36+AZ27+AZ18 -> 48.046 | BA38: =BA36+BA27+BA18 -> 58.768 | BB38: =BB36+BB27+BB18 -> 86.54889 | BC38: =BC18+BC27+BC36 -> 295.57814 | BD38: =BD36+BD27+BD18 -> 64.521876 | BE38: =BE36+BE27+BE18 -> 100.51255 | BF38: =BF36+BF27+BF18 -> 90.502246 | BG38: =BG36+BG27+BG18 -> 65.554136 | BH38: =BH18+BH27+BH36 -> 481.82781 | BI38: =BI36+BI27+BI18 -> 28.549385 | BJ38: =BJ36+BJ27+BJ18 -> 29.708587 | BK38: =BK36+BK27+BK18 -> 25.502447 | BL38: =BL36+BL27+BL18 -> 34.344709 | BM38: =BM18+BM27+BM36 -> 278.84213 | BN38: =BN36+BN27+BN18 -> 25.308264 | BO38: =BO36+BO27+BO18 -> 25.998339 | BP38: =BP36+BP27+BP18 -> 31.256044 | BQ38: =BQ36+BQ27+BQ18 -> 35.542481 | BR38: =BR18+BR27+BR36 -> 278.84213
A40: Cash and cash equivalents at beginning of period | F40: 348.309 | G40: =F41 -> 298.903 | H40: =G41 -> 388.249 | I40: =H41 -> 338.824 | J40: =F40 -> 348.309 | K40: =J41 -> 471.378 | L40: =K41 -> 411.056 | M40: =L41 -> 515.103 | N40: =M41 -> 425.765 | O40: =K40 -> 471.378 | P40: =O41 -> 204.24 | Q40: =P41 -> 259.61 | R40: =Q41 -> 319.243 | S40: =R41 -> 375.421 | T40: =P40 -> 204.24 | U40: =T41 -> 168.056 | V40: =U41 -> 132.318 | W40: =V41 -> 209.159 | X40: =W41 -> 257.146 | Y40: =U40 -> 168.056 | Z40: =Y41 -> 119.923 | AA40: =Z41 -> 133.064 | AB40: =AA41 -> 139.858 | AC40: =AB41 -> 204.311 | AD40: =Z40 -> 119.923 | AE40: =AD41 -> 202.666 | AF40: =AE41 -> 213.041 | AG40: =AF41 -> 174 | AH40: =AG41 -> 163.977 | AI40: =AE40 -> 202.666 | AJ40: =AI41 -> 142.535 | AK40: =AJ41 -> 157.665 | AL40: =AK41 -> 160.705 | AM40: =AL41 -> 237.827 | AN40: =AJ40 -> 142.535 | AO40: =AN41 -> 213.186 | AP40: =AO41 -> 171.9 | AQ40: =AP41 -> 240.01 | AR40: =AQ41 -> 288.961 | AS40: =AO40 -> 213.186 | AT40: =AS41 -> 259.951 | AU40: =AT41 -> 240.733 | AV40: =AU41 -> 204.306 | AW40: =AV41 -> 183.997 | AX40: =AT40 -> 259.951 | AY40: =AX41 -> 182.166 | AZ40: =AY41 -> 168.88 | BA40: =AZ41 -> 216.926 | BB40: =BA41 -> 275.694 | BC40: =AY40 -> 182.166 | BD40: =BC41 -> 362.24289 | BE40: =BD41 -> 426.76477 | BF40: =BE41 -> 527.27732 | BG40: =BF41 -> 617.77956 | BH40: =BD40 -> 362.24289 | BI40: =BH41 -> 683.3337 | BJ40: =BI41 -> 711.88308 | BK40: =BJ41 -> 741.59167 | BL40: =BK41 -> 767.09412 | BM40: =BI40 -> 683.3337 | BN40: =BM41 -> 801.43883 | BO40: =BN41 -> 826.74709 | BP40: =BO41 -> 852.74543 | BQ40: =BP41 -> 884.00147 | BR40: =BN40 -> 801.43883
A41: Cash and cash equivalents at end of period | F41: =F40+F38 -> 298.903 | G41: =G40+G38 -> 388.249 | H41: =H40+H38 -> 338.824 | I41: =I40+I38 -> 471.378 | J41: =J38+J40 -> 471.378 | K41: =K40+K38 -> 411.056 | L41: =L40+L38 -> 515.103 | M41: =M40+M38 -> 425.765 | N41: =N40+N38 -> 204.24 | O41: =N41 -> 204.24 | P41: =P40+P38 -> 259.61 | Q41: =Q40+Q38 -> 319.243 | R41: =R40+R38 -> 375.421 | S41: =S38+S40 -> 168.056 | T41: =T40+T38 -> 168.056 | U41: =U40+U38 -> 132.318 | V41: =V40+V38 -> 209.159 | W41: =W40+W38 -> 257.146 | X41: =X40+X38 -> 119.923 | Y41: =Y40+Y38 -> 119.923 | Z41: =Z40+Z38 -> 133.064 | AA41: =AA40+AA38 -> 139.858 | ... AC41: =AC40+AC38 -> 202.666 | AD41: =AC41 -> 202.666 | AE41: =AE40+AE38 -> 213.041 | AF41: =AF40+AF38 -> 174 | AG41: =AG40+AG38 -> 163.977 | AH41: =AH40+AH38 -> 142.535 | AI41: =AH41 -> 142.535 | AJ41: =AJ40+AJ38 -> 157.665 | AK41: =AK40+AK38 -> 160.705 | AL41: =AL40+AL38 -> 237.827 | AM41: =AM40+AM38+0.001 -> 213.186 | AN41: =AM41 -> 213.186 | AO41: =AO40+AO38 -> 171.9 | AP41: =AP40+AP38 -> 240.01 | AQ41: =AQ40+AQ38 -> 288.961 | AR41: =AR40+AR38 -> 259.951 | AS41: =AR41 -> 259.951 | AT41: =AT40+AT38 -> 240.733 | AU41: =AU40+AU38 -> 204.306 | AV41: =AV40+AV38 -> 183.997 | AW41: =AW40+AW38 -> 182.166 | AX41: =AW41 -> 182.166 | AY41: =AY40+AY38 -> 168.88 | AZ41: =AZ40+AZ38 -> 216.926 | BA41: =BA40+BA38 -> 275.694 | BB41: =BB40+BB38 -> 362.24289 | BC41: =BB41 -> 362.24289 | BD41: =BD40+BD38 -> 426.76477 | BE41: =BE40+BE38 -> 527.27732 | BF41: =BF40+BF38 -> 617.77956 | BG41: =BG40+BG38 -> 683.3337 | BH41: =BG41 -> 683.3337 | BI41: =BI40+BI38 -> 711.88308 | BJ41: =BJ40+BJ38 -> 741.59167 | BK41: =BK40+BK38 -> 767.09412 | BL41: =BL40+BL38 -> 801.43883 | BM41: =BL41 -> 801.43883 | BN41: =BN40+BN38 -> 826.74709 | BO41: =BO40+BO38 -> 852.74543 | BP41: =BP40+BP38 -> 884.00147 | BQ41: =BQ40+BQ38 -> 919.54395 | BR41: =BQ41 -> 919.54395

Sheet Backlog
A1: Backlog
C2: 40178 | D2: 40268 | E2: =EOMONTH(D2,3) -> 40359 | F2: =EOMONTH(E2,3) -> 40451 | G2: =EOMONTH(F2,3) -> 40543 | H2: =EOMONTH(G2,3) -> 40633 | I2: =EOMONTH(H2,3) -> 40724 | J2: =EOMONTH(I2,3) -> 40816 | K2: =EOMONTH(J2,3) -> 40908 | L2: =EOMONTH(K2,3) -> 40999 | ... BC2: =EOMONTH(BB2,3) -> 44926
A3: Civil | C3: 1001.5 | D3: 922.1 | E3: 1042.1 | F3: 879.4 | G3: 1360.084 | H3: 1374.5 | I3: 1903.9 | J3: 2338.6 | K3: 2222.2 | L3: 2148.7 | M3: 1903.6 | N3: 1669.4 | O3: 1774 | P3: 1665.9 | Q3: 2643.3 | R3: 3078.3 | S3: 3437.6 | T3: 3887.1 | U3: 3707.9 | V3: 3886.4 | W3: 3563.2 | X3: 3411.8 | Y3: 3128.6 | Z3: 2810.6 | AA3: 2743.7 | AB3: 3346.1 | AC3: 2973.9 | AD3: 2799.4 | AE3: 2672.1 | AF3: 3865.7 | AG3: 4240.6 | AH3: 4307.4 | AI3: 4118.2 | AJ3: 4475.4 | AK3: 4737.4 | AL3: 4651.6 | AM3: 5141.863 | AN3: 6505.9 | AO3: 6181.5 | AP3: 5949.6 | AQ3: =+AP3*(1+AQ10) -> 6068.592 | AR3: =+AQ3*(1+AR10) -> 7403.6822 | AS3: =+AR3*(1+AS10) -> 7551.7559 | AT3: =+AS3*(1+AT10) -> 7702.791 | AU3: =+AT3*(1+AU10) -> 7856.8468 | AV3: =+AU3*(1+AV10) -> 9585.3531 | AW3: =+AV3*(1+AW10) -> 9777.0602 | AX3: =+AW3*(1+AX10) -> 9972.6014 | ... BC3: =+BB3*(1+BC10) -> 13169.491
A4: Building | C4: 3125.8 | D4: 2685.1 | E4: 3054.8 | F4: 2925 | G4: 2663.315 | H4: 2528.2 | I4: 2745.4 | J4: 2482.1 | K4: 2248.9 | L4: 2195.4 | M4: 2186.5 | N4: 2177.3 | O4: 1964.9 | P4: 2042.1 | Q4: 2063.3 | R4: 1848.9 | S4: 1654.4 | T4: 1732.9 | U4: 2007.6 | V4: 2188 | W4: 2187.8 | X4: 2254.8 | Y4: 2483.2 | Z4: 2680.4 | AA4: 2780.4 | AB4: 2874.7 | AC4: 2501.4 | AD4: 2228.4 | AE4: 1981.2 | AF4: 1750.3 | AG4: 1808.4 | AH4: 1598.7 | AI4: 1701.4 | AJ4: 2237 | AK4: 2085.6 | AL4: 2122.8 | AM4: 2333.127 | AN4: 2968.9 | AO4: 2868.3 | AP4: 2652.4 | AQ4: =+AP4*(1+AQ11) -> 2678.924 | AR4: =+AQ4*(1+AR11) -> 2705.7132 | AS4: =+AR4*(1+AS11) -> 2732.7704 | AT4: =+AS4*(1+AT11) -> 2760.0981 | AU4: =+AT4*(1+AU11) -> 2787.6991 | AV4: =+AU4*(1+AV11) -> 2815.576 | AW4: =+AV4*(1+AW11) -> 2843.7318 | AX4: =+AW4*(1+AX11) -> 2872.1691 | ... BC4: =+BB4*(1+BC11) -> 3018.6786
A5: Specialty Contractors | J5: 1330 | K5: 1371.5 | L5: 1311.3 | M5: 1469.2 | N5: 1413 | O5: 1507.3 | P5: 1494.4 | Q5: 1586.5 | R5: 1671.8 | S5: 1661.1 | T5: 2032.4 | U5: 2048.8 | V5: 2011.2 | W5: 2080.7 | X5: 2121.7 | Y5: 2137.7 | Z5: 2048 | AA5: 1941 | AB5: 1938.4 | AC5: 1794.2 | AD5: 1668.5 | AE5: 1573.8 | AF5: 1554.5 | AG5: 1511.5 | AH5: 1595.6 | AI5: 1463.8 | AJ5: 1765 | AK5: 1868.3 | AL5: 1741.8 | AM5: 1821.701 | AN5: 2109.5 | AO5: 2324.9 | AP5: 2273.9 | AQ5: =+AP5*(1+AQ12) -> 2296.639 | AR5: =+AQ5*(1+AR12) -> 2319.6054 | AS5: =+AR5*(1+AS12) -> 2342.8014 | AT5: =+AS5*(1+AT12) -> 2366.2295 | AU5: =+AT5*(1+AU12) -> 2389.8918 | AV5: =+AU5*(1+AV12) -> 2413.7907 | AW5: =+AV5*(1+AW12) -> 2437.9286 | AX5: =+AW5*(1+AX12) -> 2462.3079 | ... BC5: =+BB5*(1+BC12) -> 2587.9103
A6: Management Services | C6: 182.9 | D6: 150.2 | E6: 194.6 | F6: 243 | G6: 260.891 | H6: 328.6 | I6: 316.7 | J6: 339.2 | K6: 265.7 | L6: 261.4 | M6: 295.6 | N6: 293.9 | O6: 357.4 | P6: 323.9 | Q6: 293.6 | R6: 303.5 | S6: 201.1 | T6: =+T3/SUM(T3:T5) -> 0.50795829 | U6: =+U3/SUM(U3:U5) -> 0.47755754 | V6: =+V3/SUM(V3:V5) -> 0.48065697 | W6: =+W3/SUM(W3:W5) -> 0.45497146 | X6: =+X3/SUM(X3:X5) -> 0.43806736 | Y6: =+Y3/SUM(Y3:Y5) -> 0.40371637 | Z6: =+Z3/SUM(Z3:Z5) -> 0.37280806 | AA6: =+AA3/SUM(AA3:AA5) -> 0.36753694 | ... AP6: =+AP3/SUM(AP3:AP5) -> 0.54704438
A7: Eliminations | J7: -40.1 | AF7: =AF8/AE8-1 -> 0.15150632 | AG7: =AG8/AF8-1 -> 0.05438846 | AH7: =AH8/AG8-1 -> -0.0077749273 | AI7: =AI8/AH8-1 -> -0.029099012 | AJ7: =AJ8/AI8-1 -> 0.16391655 | AK7: =AK8/AJ8-1 -> 0.025232245 | AL7: =AL8/AK8-1 -> -0.02014519 | AM7: =AM8/AL8-1 -> 0.091642731 | ... AP7: =AP8/AO8-1 -> -0.043849294
A8: Total | D8: =SUM(D3:D6) -> 3757.4 | E8: =SUM(E3:E6) -> 4291.5 | F8: =SUM(F3:F6) -> 4047.4 | G8: =SUM(G3:G6) -> 4284.29 | H8: =SUM(H3:H6) -> 4231.3 | I8: =SUM(I3:I6) -> 4966 | J8: =SUM(J3:J7) -> 6449.8 | K8: =SUM(K3:K6) -> 6108.3 | L8: =SUM(L3:L6) -> 5916.8 | M8: =SUM(M3:M6) -> 5854.9 | N8: =SUM(N3:N6) -> 5553.6 | O8: =SUM(O3:O6) -> 5603.6 | P8: =SUM(P3:P6) -> 5526.3 | Q8: =SUM(Q3:Q6) -> 6586.7 | R8: =SUM(R3:R6) -> 6902.5 | ... BC8: =SUM(BC3:BC6) -> 18776.08
AI9: =AI8/AE8-1 -> 0.16963972
A10: =+A3 -> Civil | E10: =+E3/D3-1 -> 0.13013773 | F10: =+F3/E3-1 -> -0.15612705 | G10: =+G3/F3-1 -> 0.5466045 | H10: =+H3/G3-1 -> 0.010599345 | I10: =+I3/H3-1 -> 0.38515824 | J10: =+J3/I3-1 -> 0.22832082 | K10: =+K3/J3-1 -> -0.049773369 | L10: =+L3/K3-1 -> -0.033075331 | ... AP10: =+AP3/AO3-1 -> -0.037515166 | AQ10: 0.02 | AR10: 0.22 | AS10: 0.02 | AT10: 0.02 | AU10: 0.02 | AV10: 0.22 | AW10: 0.02 | AX10: 0.02 | AY10: 0.02 | AZ10: 0.22 | BA10: 0.02 | BB10: 0.02 | BC10: 0.02
A11: =+A4 -> Building | E11: =+E4/D4-1 -> 0.13768575 | F11: =+F4/E4-1 -> -0.042490507 | G11: =+G4/F4-1 -> -0.089464957 | H11: =+H4/G4-1 -> -0.050731889 | I11: =+I4/H4-1 -> 0.085910925 | J11: =+J4/I4-1 -> -0.095905879 | K11: =+K4/J4-1 -> -0.093952701 | L11: =+L4/K4-1 -> -0.023789408 | ... AP11: =+AP4/AO4-1 -> -0.075271066 | AQ11: 0.01 | AR11: 0.01 | AS11: 0.01 | AT11: 0.01 | AU11: 0.01 | AV11: 0.01 | AW11: 0.01 | AX11: 0.01 | AY11: 0.01 | AZ11: 0.01 | BA11: 0.01 | BB11: 0.01 | BC11: 0.01
A12: =+A5 -> Specialty Contractors | K12: =+K5/J5-1 -> 0.031203008 | L12: =+L5/K5-1 -> -0.043893547 | M12: =+M5/L5-1 -> 0.12041486 | N12: =+N5/M5-1 -> -0.03825211 | O12: =+O5/N5-1 -> 0.066737438 | P12: =+P5/O5-1 -> -0.0085583494 | Q12: =+Q5/P5-1 -> 0.061630086 | R12: =+R5/Q5-1 -> 0.053766152 | ... AP12: =+AP5/AO5-1 -> -0.021936427 | AQ12: 0.01 | AR12: 0.01 | AS12: 0.01 | AT12: 0.01 | AU12: 0.01 | AV12: 0.01 | AW12: 0.01 | AX12: 0.01 | AY12: 0.01 | AZ12: 0.01 | BA12: 0.01 | BB12: 0.01 | BC12: 0.01
A13: =+A8 -> Total | E13: =+E8/D8-1 -> 0.14214616 | F13: =+F8/E8-1 -> -0.056879879 | G13: =+G8/F8-1 -> 0.058528932 | H13: =+H8/G8-1 -> -0.012368444 | I13: =+I8/H8-1 -> 0.17363458 | J13: =+J8/I8-1 -> 0.29879178 | K13: =+K8/J8-1 -> -0.052947378 | L13: =+L8/K8-1 -> -0.031350785 | ... BC13: =+BC8/BB8-1 -> 0.016993297
T14: =+T5/P5-1 -> 0.36001071 | U14: =+U5/Q5-1 -> 0.29139616 | V14: =+V5/R5-1 -> 0.20301471 | W14: =+W5/S5-1 -> 0.2526037 | X14: =+X5/T5-1 -> 0.043938201 | Y14: =+Y5/U5-1 -> 0.043391253 | Z14: =+Z5/V5-1 -> 0.018297534 | AA14: =+AA5/W5-1 -> -0.067140866 | ... AF14: =+AF5/AB5-1 -> -0.19804994 | AG14: =+AG8/AC8-1 -> 0.040048891 | AH14: =+AH3/AG3-1 -> 0.015752488 | AI14: =+AI3/AH3-1 -> -0.043924409 | AJ14: =+AJ5/AF5-1 -> 0.13541332
A15: Revenue
A16: =+A3 -> Civil | E16: =+IS!K7 -> 128.825 | F16: =+IS!L7 -> 141.442 | G16: =+IS!M7 -> 281.355 | H16: =+IS!N7 -> 345.274 | I16: =+IS!O7 -> 896.896 | J16: =+IS!P7 -> 250.589 | K16: =+IS!Q7 -> 327.072 | L16: =+IS!R7 -> 350.542 | ... O16: =+IS!U7 -> 283.975 | P16: =+IS!U7 -> 283.975 | Q16: =+IS!V7 -> 332.223 | R16: =+IS!W7 -> 379.765 | S16: =+IS!X7 -> 427.809 | T16: =+IS!Z7 -> 376.392 | U16: =+IS!AA7 -> 398.123 | V16: =+IS!AB7 -> 496.142 | W16: =+IS!AC7 -> 459.811 | X16: =+IS!AE7 -> 392.876 | Y16: =+IS!AF7 -> 573.36 | Z16: =+IS!AG7 -> 604.317 | AA16: =+IS!AH7 -> 434.64 | AB16: =+IS!AJ7 -> 367.501 | AC16: =+IS!AK7 -> 465.707 | AD16: =+IS!AL7 -> 506.1 | AE16: =+IS!AM7 -> 452.327 | AF16: =+IS!AO7 -> 338.108 | AG16: =+IS!AP7 -> 538.552 | AH16: =+IS!AQ7 -> 458.487 | AI16: =+IS!AR7 -> 492.314 | AJ16: =+IS!AS7 -> 1827.461 | AK16: =+IS!AT7 -> 325.4 | AL16: =+IS!AU7 -> 461.614 | AM16: =+IS!AV7 -> 479.581 | ... AP16: =+IS!AY7 -> 383.622 | AQ16: =+IS!BB7 -> 469.37366 | AR16: =+IS!BD7 -> 546.95096 | AS16: =+IS!BE7 -> 830.33826 | AT16: =+IS!BF7 -> 828.41794 | AU16: =+IS!BG7 -> 815.48769 | AV16: =+IS!BH7 -> 3555.3498 | AW16: =+IS!BI7 -> 528.76148 | AX16: =+IS!BJ7 -> 841.59494 | AY16: =+IS!BK7 -> 822.16609 | ... BC16: =+IS!BO7 -> 829.40746
A17: =+A4 -> Building | E17: =+IS!K6 -> 440.429 | F17: =+IS!L6 -> 599.977 | G17: =+IS!M6 -> 567.676 | H17: =+IS!N6 -> 343.948 | I17: =+IS!O6 -> 1952.03 | J17: =+IS!P6 -> 343.039 | K17: =+IS!Q6 -> 331.924 | L17: =+IS!R6 -> 391.531 | ... O17: =+IS!U6 -> 425.114 | P17: =+IS!U6 -> 425.114 | Q17: =+IS!V6 -> 422.366 | R17: =+IS!W6 -> 352.013 | S17: =+IS!X6 -> 337.734 | T17: =+IS!Z6 -> 311.315 | U17: =+IS!AA6 -> 390.353 | V17: =+IS!AB6 -> 420.404 | W17: =+IS!AC6 -> 436.359 | X17: =+IS!AE6 -> 416.063 | Y17: =+IS!AF6 -> 472.247 | Z17: =+IS!AG6 -> 506.259 | AA17: =+IS!AH6 -> 505.924 | AB17: =+IS!AJ6 -> 487.994 | AC17: =+IS!AK6 -> 523.521 | AD17: =+IS!AL6 -> 560.795 | AE17: =+IS!AM6 -> 551.801 | AF17: =+IS!AO6 -> 515.251 | AG17: =+IS!AP6 -> 508.769 | AH17: =+IS!AQ6 -> 500.42 | AI17: =+IS!AR6 -> 462.501 | AJ17: =+IS!AS6 -> 1986.941 | AK17: =+IS!AT6 -> 490.617 | AL17: =+IS!AU6 -> 447.975 | AM17: =+IS!AV6 -> 457.304 | ... AP17: =+IS!AY6 -> 436.243 | AQ17: =+IS!BB6 -> 517.08347 | AR17: =+IS!BD6 -> 388.89198 | AS17: =+IS!BE6 -> 457.09044 | AT17: =+IS!BF6 -> 466.79635 | AU17: =+IS!BG6 -> 509.67947 | AV17: =+IS!BH6 -> 1988.2877 | AW17: =+IS!BI6 -> 381.44193 | AX17: =+IS!BJ6 -> 459.06958 | AY17: =+IS!BK6 -> 463.20683 | ... BC17: =+IS!BO6 -> 457.17395
A18: =+A5 -> Specialty Contractors | E18: =+IS!K8 -> 0 | F18: =+IS!L8 -> 0 | G18: =+IS!M8 -> 335.921 | H18: =+IS!N8 -> 466.614 | I18: =+IS!O8 -> 802.535 | J18: =+IS!P8 -> 267.736 | K18: =+IS!Q8 -> 275.902 | L18: =+IS!R8 -> 315.27 | ... O18: =+IS!U8 -> 301.877 | P18: =+IS!U8 -> 301.877 | Q18: =+IS!V8 -> 284.036 | R18: =+IS!W8 -> 287.633 | S18: =+IS!X8 -> 309.298 | T18: =+IS!Z8 -> 292.145 | U18: =+IS!AA8 -> 321.959 | V18: =+IS!AB8 -> 355.932 | W18: =+IS!AC8 -> 331.292 | X18: =+IS!AE8 -> 293.017 | Y18: =+IS!AF8 -> 326.798 | Z18: =+IS!AG8 -> 325.365 | AA18: =+IS!AH8 -> 282.849 | AB18: =+IS!AJ8 -> 281.773 | AC18: =+IS!AK8 -> 318.902 | AD18: =+IS!AL8 -> 331.613 | AE18: =+IS!AM8 -> 301.983 | AF18: =+IS!AO8 -> 315.696 | AG18: =+IS!AP8 -> 281.857 | AH18: =+IS!AQ8 -> 310.137 | AI18: =+IS!AR8 -> 306.018 | AJ18: =+IS!AS8 -> 1213.708 | AK18: =+IS!AT8 -> 274.801 | AL18: =+IS!AU8 -> 270.633 | AM18: =+IS!AV8 -> 236.157 | ... AP18: =+IS!AY8 -> 191.527 | AQ18: =+IS!BB8 -> 481.26714 | AR18: =+IS!BD8 -> 264.23834 | AS18: =+IS!BE8 -> 306.11383 | AT18: =+IS!BF8 -> 323.44155 | AU18: =+IS!BG8 -> 338.58717 | AV18: =+IS!BH8 -> 1263.4234 | AW18: =+IS!BI8 -> 259.96255 | AX18: =+IS!BJ8 -> 303.03887 | AY18: =+IS!BK8 -> 321.52565 | ... BC18: =+IS!BO8 -> 307.25025
AH19: =+AH16/AVERAGE(AD16:AG16)-1 -> -0.00062067902
A20: New Order
A21: =+A10 -> Civil | E21: =+E3-D3+E16 -> 248.825 | F21: =+F3-E3+F16 -> -21.258 | G21: =+G3-F3+G16 -> 762.039 | H21: =+H3-G3+H16 -> 359.69 | I21: =+I3-H3+I16 -> 1426.296 | J21: =+J3-I3+J16 -> 685.289 | K21: =+K3-J3+K16 -> 210.672 | L21: =+L3-K3+L16 -> 277.042 | ... AE21: =+AE3-AD3+AE16 -> 325.027 | AF21: 1498.2 | AG21: 847.5 | AH21: =+AH3-AG3+AH16 -> 525.287 | AI21: =+AI3-AH3+AI16 -> 303.114 | AJ21: =+AJ3-AI3+AJ16 -> 2184.661 | AK21: =+AK3-AJ3+AK16 -> 587.4 | AL21: =+AL3-AK3+AL16 -> 375.814 | AM21: =+AM3-AL3+AM16 -> 969.844 | AN21: =+AN3-AM3+AN16 -> 1907.674 | AO21: =+AO3-AN3+AO16 -> 1485.832 | ... BC21: =+BC3-BB3+BC16 -> 1087.6328
A22: =+A11 -> Building | E22: =+E4-D4+E17 -> 810.129 | F22: =+F4-E4+F17 -> 470.177 | G22: =+G4-F4+G17 -> 305.991 | H22: =+H4-G4+H17 -> 208.833 | I22: =+I4-H4+I17 -> 2169.23 | J22: =+J4-I4+J17 -> 79.739 | K22: =+K4-J4+K17 -> 98.724 | L22: =+L4-K4+L17 -> 338.031 | ... AE22: =+AE4-AD4+AE17 -> 304.601 | AF22: 266.2 | AG22: 550.9 | AH22: =+AH4-AG4+AH17 -> 290.72 | AI22: =+AI4-AH4+AI17 -> 565.201 | AJ22: =+AJ4-AI4+AJ17 -> 2522.541 | AK22: =+AK4-AJ4+AK17 -> 339.217 | AL22: =+AL4-AK4+AL17 -> 485.175 | AM22: =+AM4-AL4+AM17 -> 667.631 | AN22: =+AN4-AM4+AN17 -> 1106.779 | AO22: =+AO4-AN4+AO17 -> 1766.302 | ... BC22: =+BC4-BB4+BC17 -> 487.06185
A23: =+A12 -> Specialty Contractors | E23: =+E5-D5+E18 -> 0 | F23: =+F5-E5+F18 -> 0 | G23: =+G5-F5+G18 -> 335.921 | H23: =+H5-G5+H18 -> 466.614 | I23: =+I5-H5+I18 -> 802.535 | J23: =+J5-I5+J18 -> 1597.736 | K23: =+K5-J5+K18 -> 317.402 | L23: =+L5-K5+L18 -> 255.07 | ... AF23: =+AF5-AE5+AF18 -> 296.396 | AG23: 238.9 | AH23: =+AH5-AG5+AH18 -> 394.237 | AI23: =+AI5-AH5+AI18 -> 174.218 | AJ23: =+AJ5-AI5+AJ18 -> 1514.908 | AK23: =+AK5-AJ5+AK18 -> 378.101 | AL23: =+AL5-AK5+AL18 -> 144.133 | AM23: =+AM5-AL5+AM18 -> 316.058 | AN23: =+AN5-AM5+AN18 -> 513.078 | AO23: =+AO5-AN5+AO18 -> 1222.27 | AP23: 1116.5 | AQ23: =+AQ5-AP5+AQ18 -> 504.00614 | AR23: =+AR5-AQ5+AR18 -> 287.20473 | AS23: =+AS5-AR5+AS18 -> 329.30988 | AT23: =+AT5-AS5+AT18 -> 346.86957 | AU23: =+AU5-AT5+AU18 -> 362.24946 | AV23: =+AV5-AU5+AV18 -> 1287.3223 | AW23: =+AW5-AV5+AW18 -> 284.10046 | AX23: =+AX5-AW5+AX18 -> 327.41816 | ... BC23: =+BC5-BB5+BC18 -> 332.87313
H25: =+SUM(E21:H21) -> 1349.296 | I25: =+SUM(F21:I21) -> 2526.767 | J25: =+SUM(G21:J21) -> 3233.314 | K25: =+SUM(H21:K21) -> 2681.947 | L25: =+SUM(I21:L21) -> 2599.299 | M25: =+SUM(J21:M21) -> 1290.31 | N25: =+SUM(K21:N21) -> 1661.431 | O25: =+SUM(L21:O21) -> 1839.334 | ... BC25: =+SUM(AZ21:BC21) -> 9762.8046
H26: =+SUM(E22:H22) -> 1795.13 | I26: =+SUM(F22:I22) -> 3154.231 | J26: =+SUM(G22:J22) -> 2763.793 | K26: =+SUM(H22:K22) -> 2556.526 | L26: =+SUM(I22:L22) -> 2685.724 | M26: =+SUM(J22:M22) -> 919.608 | N26: =+SUM(K22:N22) -> 2309.177 | O26: =+SUM(L22:O22) -> 2423.167 | ... BC26: =+SUM(AZ22:BC22) -> 3492.8063
H27: =+SUM(E23:H23) -> 802.535 | I27: =+SUM(F23:I23) -> 1605.07 | J27: =+SUM(G23:J23) -> 3202.806 | K27: =+SUM(H23:K23) -> 3184.287 | L27: =+SUM(I23:L23) -> 2972.743 | M27: =+SUM(J23:M23) -> 2652.718 | N27: =+SUM(K23:N23) -> 2182.3 | O27: =+SUM(L23:O23) -> 2261.075 | ... BC27: =+SUM(AZ23:BC23) -> 2270.4168
H28: =SUM(H25:H27) -> 3946.961 | I28: =SUM(I25:I27) -> 7286.068 | J28: =SUM(J25:J27) -> 9199.913 | K28: =SUM(K25:K27) -> 8422.76 | L28: =SUM(L25:L27) -> 8257.766 | M28: =SUM(M25:M27) -> 4862.636 | N28: =SUM(N25:N27) -> 6152.908 | O28: =SUM(O25:O27) -> 6523.576 | ... AE28: =SUM(AE25:AE27) -> 3912.017
O29: =O25/K25-1 -> -0.31417959 | P29: =P25/L25-1 -> -0.33129394 | Q29: =Q25/M25-1 -> 1.2711465 | R29: =R25/N25-1 -> 0.6183868 | S29: =S25/O25-1 -> 0.67852712 | T29: =T25/P25-1 -> 1.1501898 | U29: =U25/Q25-1 -> -0.096842056 | V29: =V25/R25-1 -> -0.06778839 | ... BC29: =BC25/AY25-1 -> 0.21080355
B31: Year | C31: 1999 | D31: =1+C31 -> 2000 | E31: =1+D31 -> 2001 | F31: =1+E31 -> 2002 | G31: =1+F31 -> 2003 | H31: =1+G31 -> 2004 | I31: =1+H31 -> 2005 | J31: =1+I31 -> 2006 | K31: =1+J31 -> 2007 | ... V31: =1+U31 -> 2018 | W31: 2019 | X31: 2020 | Y31: 2021 | Z31: 2022
A32: Civil Backlog | C32: 543.711 | D32: 737.367 | E32: 474.989 | F32: 210.562 | G32: 305.698 | H32: 230.711 | I32: 422.988 | J32: 429.685 | K32: 457.838 | L32: 528.005 | M32: 1001.507 | N32: 1360.1 | O32: 2222.2 | P32: 1774 | Q32: 3437.6 | R32: =+W3 -> 3563.2 | S32: =+AA3 -> 2743.7 | T32: =+AE3 -> 2672.1 | U32: =+AI3 -> 4118.2 | V32: =+AM3 -> 5141.863 | W32: =+AQ3 -> 6068.592 | X32: =+AU3 -> 7856.8468 | Y32: =+AV3 -> 9585.3531 | Z32: =+AW3 -> 9777.0602
A33: Civil Revenue | C33: 323.077 | D33: 279.46899 | E33: 353.957 | F33: 312.52802 | G33: 176.877 | H33: 138.095 | I33: 275.58401 | J33: 281.13699 | K33: 234.778 | L33: 310.72198 | M33: 361.677 | N33: 667.704 | O33: 896.896 | P33: 1290.61 | Q33: 1423.772 | R33: =+SUM(T16:W16) -> 1730.468 | S33: =+SUM(X16:AA16) -> 2005.193 | T33: =+SUM(AB16:AE16) -> 1791.635 | U33: =+SUM(AF16:AI16) -> 1827.461 | V33: =(U32*SLOPE($D33:U33,$C32:T32))+INTERCEPT($D33:U33,$C32:T32) -> 2431.1684 | W33: =(V32*SLOPE($D33:V33,$C32:U32))+INTERCEPT($D33:V33,$C32:U32) -> 3021.1949 | X33: =(W32*SLOPE($D33:W33,$C32:V32))+INTERCEPT($D33:W33,$C32:V32) -> 3555.3498 | Y33: =(X32*SLOPE($D33:X33,$C32:W32))+INTERCEPT($D33:X33,$C32:W32) -> 4586.0774 | Z33: =(Y32*SLOPE($D33:Y33,$C32:X32))+INTERCEPT($D33:Y33,$C32:X32) -> 5582.3667
A34: Building Backlog | C34: 1114.366 | D34: 1051.364 | E34: 738.546 | F34: 525.433 | G34: 896.799 | H34: 570.067 | I34: 7180.369 | J34: 7832.357 | K34: 6981.704 | L34: 5731.992 | M34: 3125.78 | N34: 2663.3 | O34: 2248.9 | P34: 1964.9 | Q34: 1654.4 | R34: =+W4 -> 2187.8 | S34: =+AA4 -> 2780.4 | T34: =+AE4 -> 1981.2 | U34: =+AI4 -> 1701.4 | V34: =+AM4 -> 2333.127 | W34: =+AQ4 -> 2678.924 | X34: =+AU4 -> 2787.6991 | Y34: =+AV4 -> 2815.576 | Z34: =+AW4 -> 2843.7318
A35: Building Revenue | C35: 696.40698 | D35: 826.19098 | E35: 1199.439 | F35: 772.513 | G35: 898.25403 | H35: 1298.771 | I35: 1181.103 | J35: 2515.051 | K35: 4248.814 | L35: 5146.563 | M35: 4484.937 | N35: 2326.98 | O35: 1825.468 | P35: 1467.91 | Q35: 1470.219 | R35: =+SUM(T17:W17) -> 1558.431 | S35: =+SUM(X17:AA17) -> 1900.493 | T35: =+SUM(AB17:AE17) -> 2124.111 | U35: =+SUM(AF17:AI17) -> 1986.941 | V35: =(U34*SLOPE($D35:U35,$C34:T34))+INTERCEPT($D35:U35,$C34:T34) -> 1519.5089 | W35: =(V34*SLOPE($D35:V35,$C34:U34))+INTERCEPT($D35:V35,$C34:U34) -> 1822.4582 | X35: =(W34*SLOPE($D35:W35,$C34:V34))+INTERCEPT($D35:W35,$C34:V34) -> 1988.2877 | Y35: =(X34*SLOPE($D35:X35,$C34:W34))+INTERCEPT($D35:X35,$C34:W34) -> 2040.4516 | Z35: =(Y34*SLOPE($D35:Y35,$C34:X34))+INTERCEPT($D35:Y35,$C34:X34) -> 2053.8202
A36: Spec Backlog | O36: 1371.5 | P36: 1507.3 | Q36: 1661.1 | R36: =+W5 -> 2080.7 | S36: =+AA5 -> 1941 | T36: =+AE5 -> 1573.8 | U36: =+AI5 -> 1463.8 | V36: =+AM5 -> 1821.701 | W36: =+AQ5 -> 2296.639 | X36: =+AU5 -> 2389.8918 | Y36: =+AV5 -> 2413.7907 | Z36: =+AW5 -> 2437.9286
A37: Spec Backlog T+1 | P37: =O36 -> 1371.5 | Q37: =P36 -> 1507.3 | R37: =Q36 -> 1661.1 | S37: =R36 -> 2080.7 | T37: =S36 -> 1941 | U37: =T36 -> 1573.8 | V37: =U36 -> 1463.8 | W37: =V36 -> 1821.701 | ... Z37: =Y36 -> 2413.7907
A38: Spec Revenue | O38: 802 | P38: 1183 | Q38: 1182 | R38: =+SUM(T18:W18) -> 1301.328 | S38: =+SUM(X18:AA18) -> 1228.029 | T38: =+SUM(AB18:AE18) -> 1234.271 | U38: =+SUM(AF18:AI18) -> 1213.708 | V38: =(V37*SLOPE($P$38:U38,$P$37:U37))+INTERCEPT($P$38:U38,$P$37:U37) -> 1208.9881 | W38: =(W37*SLOPE($P$38:V38,$P$37:V37))+INTERCEPT($P$38:V38,$P$37:V37) -> 1232.3809 | X38: =(X37*SLOPE($P$38:W38,$P$37:W37))+INTERCEPT($P$38:W38,$P$37:W37) -> 1263.4234 | Y38: =(Y37*SLOPE($P$38:X38,$P$37:X37))+INTERCEPT($P$38:X38,$P$37:X37) -> 1269.5185 | Z38: =(Z37*SLOPE($P$38:Y38,$P$37:Y37))+INTERCEPT($P$38:Y38,$P$37:Y37) -> 1271.0805
P39: =P38/P37 -> 0.86255924 | Q39: =Q38/Q37 -> 0.78418364 | R39: =R38/R37 -> 0.7834134 | S39: =S38/S37 -> 0.59019993 | T39: 0.83 | U39: 0.83 | V39: 0.83 | W39: 0.83 | X39: 0.83 | Y39: 0.83 | Z39: 0.83
Q40: Total Rev | R40: =R35+R33+R38 -> 4590.227 | S40: =S35+S33+S38 -> 5133.715 | T40: =T35+T33+T38 -> 5150.017 | U40: =U35+U33+U38 -> 5028.11 | V40: =V35+V33+V38 -> 5159.6654 | W40: =W35+W33+W38 -> 6076.034 | X40: =X35+X33+X38 -> 6807.0609 | Y40: =Y35+Y33+Y38 -> 7896.0475 | Z40: =Z35+Z33+Z38 -> 8907.2675
Q42: Backlog Growth rates
Q43: Building | R43: =+R32/Q32-1 -> 0.036537119 | S43: =+S32/R32-1 -> -0.2299899 | T43: =+T32/S32-1 -> -0.026096148 | U43: =+U32/T32-1 -> 0.54118484 | V43: =+V32/U32-1 -> 0.24857049 | W43: =+W32/V32-1 -> 0.18023215 | X43: =+X32/W32-1 -> 0.29467376 | Y43: =+Y32/X32-1 -> 0.22 | Z43: =+Z32/Y32-1 -> 0.02
Q44: Civil | R44: =+R34/Q34-1 -> 0.32241296 | S44: =+S34/R34-1 -> 0.27086571 | T44: =+T34/S34-1 -> -0.28744066 | U44: =+U34/T34-1 -> -0.14122754 | V44: =+V34/U34-1 -> 0.37129834 | W44: =+W34/V34-1 -> 0.14821182 | X44: =+X34/W34-1 -> 0.04060401 | Y44: =+Y34/X34-1 -> 0.01 | Z44: =+Z34/Y34-1 -> 0.01
Q45: Spec | R45: =+R36/Q36-1 -> 0.2526037 | S45: =+S36/R36-1 -> -0.067140866 | T45: =+T36/S36-1 -> -0.18918083 | U45: =+U36/T36-1 -> -0.069894523 | V45: =+V36/U36-1 -> 0.2445013 | W45: =+W36/V36-1 -> 0.26071128 | X45: =+X36/W36-1 -> 0.04060401 | Y45: =+Y36/X36-1 -> 0.01 | Z45: =+Z36/Y36-1 -> 0.01
B50: Slope | F50: =+SLOPE($D$35:G35,$C$34:F34) -> 0.24055982
B51: Intercept
D59: Price | E59: Backlog | F59: Price to backlog | G59: mean
C60: 40359 | D60: =_xll.FDS("TPC-US","FG_MKT_VALUE("&C60&")") -> #NAME? | E60: =HLOOKUP(C60,$E$2:$AI$8,7,FALSE) -> 4291.5 | F60: =D60/E60 -> #NAME? | G60: =AVERAGE($F$60:$F$83) -> #NAME? | H60: =STDEV($F$60:$F$83)+G60 -> #NAME? | I60: =(G60-(H60-G60)) -> #NAME?
C61: =+EOMONTH(C60,3) -> 40451 | D61: =_xll.FDS("TPC-US","FG_MKT_VALUE("&C61&")") -> #NAME? | E61: =HLOOKUP(C61,$E$2:$AI$8,7,FALSE) -> 4047.4 | F61: =D61/E61 -> #NAME? | G61: =AVERAGE($F$60:$F$83) -> #NAME? | H61: =STDEV($F$60:$F$83)+G61 -> #NAME? | I61: =(G61-(H61-G61)) -> #NAME?
C62: =+EOMONTH(C61,3) -> 40543 | D62: =_xll.FDS("TPC-US","FG_MKT_VALUE("&C62&")") -> #NAME? | E62: =HLOOKUP(C62,$E$2:$AI$8,7,FALSE) -> 4284.29 | F62: =D62/E62 -> #NAME? | G62: =AVERAGE($F$60:$F$83) -> #NAME? | H62: =STDEV($F$60:$F$83)+G62 -> #NAME? | I62: =(G62-(H62-G62)) -> #NAME?
C63: =+EOMONTH(C62,3) -> 40633 | D63: =_xll.FDS("TPC-US","FG_MKT_VALUE("&C63&")") -> #NAME? | E63: =HLOOKUP(C63,$E$2:$AI$8,7,FALSE) -> 4231.3 | F63: =D63/E63 -> #NAME? | G63: =AVERAGE($F$60:$F$83) -> #NAME? | H63: =STDEV($F$60:$F$83)+G63 -> #NAME? | I63: =(G63-(H63-G63)) -> #NAME?
C64: =+EOMONTH(C63,3) -> 40724 | D64: =_xll.FDS("TPC-US","FG_MKT_VALUE("&C64&")") -> #NAME? | E64: =HLOOKUP(C64,$E$2:$AI$8,7,FALSE) -> 4966 | F64: =D64/E64 -> #NAME? | G64: =AVERAGE($F$60:$F$83) -> #NAME? | H64: =STDEV($F$60:$F$83)+G64 -> #NAME? | I64: =(G64-(H64-G64)) -> #NAME?
C65: =+EOMONTH(C64,3) -> 40816 | D65: =_xll.FDS("TPC-US","FG_MKT_VALUE("&C65&")") -> #NAME? | E65: =HLOOKUP(C65,$E$2:$AI$8,7,FALSE) -> 6449.8 | F65: =D65/E65 -> #NAME? | G65: =AVERAGE($F$60:$F$83) -> #NAME? | H65: =STDEV($F$60:$F$83)+G65 -> #NAME? | I65: =(G65-(H65-G65)) -> #NAME?
C66: =+EOMONTH(C65,3) -> 40908 | D66: =_xll.FDS("TPC-US","FG_MKT_VALUE("&C66&")") -> #NAME? | E66: =HLOOKUP(C66,$E$2:$AI$8,7,FALSE) -> 6108.3 | F66: =D66/E66 -> #NAME? | G66: =AVERAGE($F$60:$F$83) -> #NAME? | H66: =STDEV($F$60:$F$83)+G66 -> #NAME? | I66: =(G66-(H66-G66)) -> #NAME?
C67: =+EOMONTH(C66,3) -> 40999 | D67: =_xll.FDS("TPC-US","FG_MKT_VALUE("&C67&")") -> #NAME? | E67: =HLOOKUP(C67,$E$2:$AI$8,7,FALSE) -> 5916.8 | F67: =D67/E67 -> #NAME? | G67: =AVERAGE($F$60:$F$83) -> #NAME? | H67: =STDEV($F$60:$F$83)+G67 -> #NAME? | I67: =(G67-(H67-G67)) -> #NAME?
C68: =+EOMONTH(C67,3) -> 41090 | D68: =_xll.FDS("TPC-US","FG_MKT_VALUE("&C68&")") -> #NAME? | E68: =HLOOKUP(C68,$E$2:$AI$8,7,FALSE) -> 5854.9 | F68: =D68/E68 -> #NAME? | G68: =AVERAGE($F$60:$F$83) -> #NAME? | H68: =STDEV($F$60:$F$83)+G68 -> #NAME? | I68: =(G68-(H68-G68)) -> #NAME?
C69: =+EOMONTH(C68,3) -> 41182 | D69: =_xll.FDS("TPC-US","FG_MKT_VALUE("&C69&")") -> #NAME? | E69: =HLOOKUP(C69,$E$2:$AI$8,7,FALSE) -> 5553.6 | F69: =D69/E69 -> #NAME? | G69: =AVERAGE($F$60:$F$83) -> #NAME? | H69: =STDEV($F$60:$F$83)+G69 -> #NAME? | I69: =(G69-(H69-G69)) -> #NAME?
C70: =+EOMONTH(C69,3) -> 41274 | D70: =_xll.FDS("TPC-US","FG_MKT_VALUE("&C70&")") -> #NAME? | E70: =HLOOKUP(C70,$E$2:$AI$8,7,FALSE) -> 5603.6 | F70: =D70/E70 -> #NAME? | G70: =AVERAGE($F$60:$F$83) -> #NAME? | H70: =STDEV($F$60:$F$83)+G70 -> #NAME? | I70: =(G70-(H70-G70)) -> #NAME?
C71: =+EOMONTH(C70,3) -> 41364 | D71: =_xll.FDS("TPC-US","FG_MKT_VALUE("&C71&")") -> #NAME? | E71: =HLOOKUP(C71,$E$2:$AI$8,7,FALSE) -> 5526.3 | F71: =D71/E71 -> #NAME? | G71: =AVERAGE($F$60:$F$83) -> #NAME? | H71: =STDEV($F$60:$F$83)+G71 -> #NAME? | I71: =(G71-(H71-G71)) -> #NAME?
C72: =+EOMONTH(C71,3) -> 41455 | D72: =_xll.FDS("TPC-US","FG_MKT_VALUE("&C72&")") -> #NAME? | E72: =HLOOKUP(C72,$E$2:$AI$8,7,FALSE) -> 6586.7 | F72: =D72/E72 -> #NAME? | G72: =AVERAGE($F$60:$F$83) -> #NAME? | H72: =STDEV($F$60:$F$83)+G72 -> #NAME? | I72: =(G72-(H72-G72)) -> #NAME?
... C79: =+EOMONTH(C78,3) -> 42094 | D79: =_xll.FDS("TPC-US","FG_MKT_VALUE("&C79&")") -> #NAME? | E79: =HLOOKUP(C79,$E$2:$AI$8,7,FALSE) -> 7788.7381 | F79: =D79/E79 -> #NAME? | G79: =AVERAGE($F$60:$F$83) -> #NAME? | H79: =STDEV($F$60:$F$83)+G79 -> #NAME? | I79: =(G79-(H79-G79)) -> #NAME?
C80: =+EOMONTH(C79,3) -> 42185 | D80: =_xll.FDS("TPC-US","FG_MKT_VALUE("&C80&")") -> #NAME? | E80: =HLOOKUP(C80,$E$2:$AI$8,7,FALSE) -> 7749.9037 | F80: =D80/E80 -> #NAME? | G80: =AVERAGE($F$60:$F$83) -> #NAME? | H80: =STDEV($F$60:$F$83)+G80 -> #NAME? | I80: =(G80-(H80-G80)) -> #NAME? | X80: Bidding Pipeline
C81: =+EOMONTH(C80,3) -> 42277 | D81: =_xll.FDS("TPC-US","FG_MKT_VALUE("&C81&")") -> #NAME? | E81: =HLOOKUP(C81,$E$2:$AI$8,7,FALSE) -> 7539.3728 | F81: =D81/E81 -> #NAME? | G81: =AVERAGE($F$60:$F$83) -> #NAME? | H81: =STDEV($F$60:$F$83)+G81 -> #NAME? | I81: =(G81-(H81-G81)) -> #NAME?
